Workbook

Sheet özet
D3: Kasım 2024'ten İtibaren Toplam Değerler | J3: Tamamlanan Sprint Değerleri
C4: Ürünler | D4: Toplam İş Adedi (Açık ve Kapalı Tüm Maddeleri, Bug Dahil) | E4: Toplam Bug Adedi | F4: Tamamlanan İş Adetleri | G4: Product Backlog Eritme oranı | J4: Tamamlanan Sprint içinde Üzerinde Çalışılan İş Adedi (Bug Dahil) | K4: Tamamlanan Sprint içinde Üzerinde Çalışılan Bug Adedi | L4: Tamamlanan İş Adetleri | M4: Tamamlanan Sprint Perf. Oranı
C5: CRM | D5: =VLOOKUP(C5,'Ürün İş Listesi'!$P$30:$Z$50,8,0) -> 152 | E5: =VLOOKUP(C5,'Ürün İş Listesi'!$AQ$32:$AR$48,2,0) -> 10 | F5: =G5*D5 -> 128 | G5: =VLOOKUP(C5,'Ürün İş Listesi'!$P$30:$Z$50,11,0) -> 0.84210526 | J5: =IFERROR(VLOOKUP(C5,'Ürün İş Listesi'!$AQ$5:$AT$23,4,0),"") -> 27 | K5: =IFERROR(VLOOKUP(C5,'Ürün İş Listesi'!$AQ$5:$AR$23,2,0),"") -> 0 | L5: =IFERROR(M5*J5,"-") -> 23 | M5: =IFERROR(VLOOKUP(C5,'Ürün İş Listesi'!$P$5:$Z$23,11,0),"") -> 0.85185185
C6: Destek Portal | D6: =VLOOKUP(C6,'Ürün İş Listesi'!$P$30:$Z$50,8,0) -> 29 | E6: =VLOOKUP(C6,'Ürün İş Listesi'!$AQ$32:$AR$48,2,0) -> 11 | F6: =G6*D6 -> 26 | G6: =VLOOKUP(C6,'Ürün İş Listesi'!$P$30:$Z$50,11,0) -> 0.89655172 | J6: =IFERROR(VLOOKUP(C6,'Ürün İş Listesi'!$AQ$5:$AT$23,4,0),"") -> 1 | K6: =IFERROR(VLOOKUP(C6,'Ürün İş Listesi'!$AQ$5:$AR$23,2,0),"") -> 0 | L6: =IFERROR(M6*J6,"-") -> - | M6: =IFERROR(VLOOKUP(C6,'Ürün İş Listesi'!$P$5:$Z$23,11,0),"")
C7: E-Defter | D7: =VLOOKUP(C7,'Ürün İş Listesi'!$P$30:$Z$50,8,0) -> 26 | E7: =VLOOKUP(C7,'Ürün İş Listesi'!$AQ$32:$AR$48,2,0) -> 12 | F7: =G7*D7 -> 26 | G7: =VLOOKUP(C7,'Ürün İş Listesi'!$P$30:$Z$50,11,0) -> 1 | J7: =IFERROR(VLOOKUP(C7,'Ürün İş Listesi'!$AQ$5:$AT$23,4,0),"") -> 5 | K7: =IFERROR(VLOOKUP(C7,'Ürün İş Listesi'!$AQ$5:$AR$23,2,0),"") -> 1 | L7: =IFERROR(M7*J7,"-") -> 2 | M7: =IFERROR(VLOOKUP(C7,'Ürün İş Listesi'!$P$5:$Z$23,11,0),"") -> 0.4
C8: E-Fatura | D8: =VLOOKUP(C8,'Ürün İş Listesi'!$P$30:$Z$50,8,0) -> 127 | E8: =VLOOKUP(C8,'Ürün İş Listesi'!$AQ$32:$AR$48,2,0) -> 39 | F8: =G8*D8 -> 108 | G8: =VLOOKUP(C8,'Ürün İş Listesi'!$P$30:$Z$50,11,0) -> 0.8503937 | J8: =IFERROR(VLOOKUP(C8,'Ürün İş Listesi'!$AQ$5:$AT$23,4,0),"") -> 5 | K8: =IFERROR(VLOOKUP(C8,'Ürün İş Listesi'!$AQ$5:$AR$23,2,0),"") -> 1 | L8: =IFERROR(M8*J8,"-") -> 2 | M8: =IFERROR(VLOOKUP(C8,'Ürün İş Listesi'!$P$5:$Z$23,11,0),"") -> 0.4
C9: Entegrasyon Suit | D9: =VLOOKUP(C9,'Ürün İş Listesi'!$P$30:$Z$50,8,0) -> 74 | E9: =VLOOKUP(C9,'Ürün İş Listesi'!$AQ$32:$AR$48,2,0) -> 37 | F9: =G9*D9 -> 65 | G9: =VLOOKUP(C9,'Ürün İş Listesi'!$P$30:$Z$50,11,0) -> 0.87837838 | J9: =IFERROR(VLOOKUP(C9,'Ürün İş Listesi'!$AQ$5:$AT$23,4,0),"") -> 2 | K9: =IFERROR(VLOOKUP(C9,'Ürün İş Listesi'!$AQ$5:$AR$23,2,0),"") -> 0 | L9: =IFERROR(M9*J9,"-") -> 1 | M9: =IFERROR(VLOOKUP(C9,'Ürün İş Listesi'!$P$5:$Z$23,11,0),"") -> 0.5
C10: KEP | D10: =VLOOKUP(C10,'Ürün İş Listesi'!$P$30:$Z$50,8,0) -> 48 | E10: =VLOOKUP(C10,'Ürün İş Listesi'!$AQ$32:$AR$48,2,0) -> 7 | F10: =G10*D10 -> 42 | G10: =VLOOKUP(C10,'Ürün İş Listesi'!$P$30:$Z$50,11,0) -> 0.875 | J10: =IFERROR(VLOOKUP(C10,'Ürün İş Listesi'!$AQ$5:$AT$23,4,0),"") -> 3 | K10: =IFERROR(VLOOKUP(C10,'Ürün İş Listesi'!$AQ$5:$AR$23,2,0),"") -> 0 | L10: =IFERROR(M10*J10,"-") -> 1 | M10: =IFERROR(VLOOKUP(C10,'Ürün İş Listesi'!$P$5:$Z$23,11,0),"") -> 0.33333333
C11: Kep Assist | D11: =VLOOKUP(C11,'Ürün İş Listesi'!$P$30:$Z$50,8,0) -> 49 | E11: =VLOOKUP(C11,'Ürün İş Listesi'!$AQ$32:$AR$48,2,0) -> 19 | F11: =G11*D11 -> 48 | G11: =VLOOKUP(C11,'Ürün İş Listesi'!$P$30:$Z$50,11,0) -> 0.97959184 | J11: =IFERROR(VLOOKUP(C11,'Ürün İş Listesi'!$AQ$5:$AT$23,4,0),"") -> 6 | K11: =IFERROR(VLOOKUP(C11,'Ürün İş Listesi'!$AQ$5:$AR$23,2,0),"") -> 1 | L11: =IFERROR(M11*J11,"-") -> 3 | M11: =IFERROR(VLOOKUP(C11,'Ürün İş Listesi'!$P$5:$Z$23,11,0),"") -> 0.5
C12: KEP İK BULUT | D12: =VLOOKUP(C12,'Ürün İş Listesi'!$P$30:$Z$50,8,0) -> 90 | E12: =VLOOKUP(C12,'Ürün İş Listesi'!$AQ$32:$AR$48,2,0) -> 33 | F12: =G12*D12 -> 82 | G12: =VLOOKUP(C12,'Ürün İş Listesi'!$P$30:$Z$50,11,0) -> 0.91111111 | J12: =IFERROR(VLOOKUP(C12,'Ürün İş Listesi'!$AQ$5:$AT$23,4,0),"") -> 6 | K12: =IFERROR(VLOOKUP(C12,'Ürün İş Listesi'!$AQ$5:$AR$23,2,0),"") -> 2 | L12: =IFERROR(M12*J12,"-") -> 2 | M12: =IFERROR(VLOOKUP(C12,'Ürün İş Listesi'!$P$5:$Z$23,11,0),"") -> 0.33333333
C13: Kep Web Servisi | D13: =VLOOKUP(C13,'Ürün İş Listesi'!$P$30:$Z$50,8,0) -> 6 | E13: =VLOOKUP(C13,'Ürün İş Listesi'!$AQ$32:$AR$48,2,0) -> 1 | F13: =G13*D13 -> 5 | G13: =VLOOKUP(C13,'Ürün İş Listesi'!$P$30:$Z$50,11,0) -> 0.83333333 | J13: =IFERROR(VLOOKUP(C13,'Ürün İş Listesi'!$AQ$5:$AT$23,4,0),"") | K13: =IFERROR(VLOOKUP(C13,'Ürün İş Listesi'!$AQ$5:$AR$23,2,0),"") | L13: =IFERROR(M13*J13,"-") -> - | M13: =IFERROR(VLOOKUP(C13,'Ürün İş Listesi'!$P$5:$Z$23,11,0),"")
C14: Mobil Uygulama | D14: =VLOOKUP(C14,'Ürün İş Listesi'!$P$30:$Z$50,8,0) -> 110 | E14: =VLOOKUP(C14,'Ürün İş Listesi'!$AQ$32:$AR$48,2,0) -> 65 | F14: =G14*D14 -> 97 | G14: =VLOOKUP(C14,'Ürün İş Listesi'!$P$30:$Z$50,11,0) -> 0.88181818 | J14: =IFERROR(VLOOKUP(C14,'Ürün İş Listesi'!$AQ$5:$AT$23,4,0),"") -> 5 | K14: =IFERROR(VLOOKUP(C14,'Ürün İş Listesi'!$AQ$5:$AR$23,2,0),"") -> 2 | L14: =IFERROR(M14*J14,"-") -> 5 | M14: =IFERROR(VLOOKUP(C14,'Ürün İş Listesi'!$P$5:$Z$23,11,0),"") -> 1
C15: Muhaberat Yönetim Sistemi | D15: =VLOOKUP(C15,'Ürün İş Listesi'!$P$30:$Z$50,8,0) -> 41 | E15: =VLOOKUP(C15,'Ürün İş Listesi'!$AQ$32:$AR$48,2,0) -> 17 | F15: =G15*D15 -> 41 | G15: =VLOOKUP(C15,'Ürün İş Listesi'!$P$30:$Z$50,11,0) -> 1 | J15: =IFERROR(VLOOKUP(C15,'Ürün İş Listesi'!$AQ$5:$AT$23,4,0),"") -> 2 | K15: =IFERROR(VLOOKUP(C15,'Ürün İş Listesi'!$AQ$5:$AR$23,2,0),"") -> 0 | L15: =IFERROR(M15*J15,"-") -> 1 | M15: =IFERROR(VLOOKUP(C15,'Ürün İş Listesi'!$P$5:$Z$23,11,0),"") -> 0.5
C16: TÜRKKEP İMZA | D16: =VLOOKUP(C16,'Ürün İş Listesi'!$P$30:$Z$50,8,0) -> 27 | E16: =VLOOKUP(C16,'Ürün İş Listesi'!$AQ$32:$AR$48,2,0) -> 10 | F16: =G16*D16 -> 25 | G16: =VLOOKUP(C16,'Ürün İş Listesi'!$P$30:$Z$50,11,0) -> 0.92592593 | J16: =IFERROR(VLOOKUP(C16,'Ürün İş Listesi'!$AQ$5:$AT$23,4,0),"") -> 1 | K16: =IFERROR(VLOOKUP(C16,'Ürün İş Listesi'!$AQ$5:$AR$23,2,0),"") -> 0 | L16: =IFERROR(M16*J16,"-") -> 0 | M16: =IFERROR(VLOOKUP(C16,'Ürün İş Listesi'!$P$5:$Z$23,11,0),"") -> 0
... C20: Yapay Zeka Destekli Çağrı Karşılama | D20: =VLOOKUP(C20,'Ürün İş Listesi'!$P$30:$Z$50,8,0) -> 11 | E20: =VLOOKUP(C20,'Ürün İş Listesi'!$AQ$32:$AR$48,2,0) -> 2 | F20: =G20*D20 -> 9 | G20: =VLOOKUP(C20,'Ürün İş Listesi'!$P$30:$Z$50,11,0) -> 0.81818182 | J20: =IFERROR(VLOOKUP(C20,'Ürün İş Listesi'!$AQ$5:$AT$23,4,0),"") | K20: =IFERROR(VLOOKUP(C20,'Ürün İş Listesi'!$AQ$5:$AR$23,2,0),"") | L20: =IFERROR(M20*J20,"-") -> - | M20: =IFERROR(VLOOKUP(C20,'Ürün İş Listesi'!$P$5:$Z$23,11,0),"")
C22: Genel Toplam | D22: =SUM(D5:D20) -> 862 | E22: =SUM(E5:E20) -> 269 | F22: =SUM(F5:F20) -> 770 | G22: =VLOOKUP(C22,'Ürün İş Listesi'!$P$30:$Z$50,11,0) -> 0.89425287 | J22: =SUM(J5:J19) -> 63 | K22: =SUM(K5:K19) -> 7 | L22: =SUM(L5:L19) -> 40 | M22: =L22/J22 -> 0.63492063 | N22: Bayram ve izin planlamaları dolayısıyla tamamlanma oranları düşük gerçekleşmiştir.

Sheet Ürün İş Listesi
A1: Issue Type | B1: Issue key | C1: Status | D1: Summary | E1: Project name | F1: x | G1: DEVAM EDEN SPRİNT | H1: GELECEK SPRİNT | I1: Durum | J1: Story Point2 | AQ1: DEVAM EDEN SPRİNT | AR1: Devam Eden Sprint
A2: Story | B2: CRM-281 | C2: To Do | D2: Türkkep -E-Güven CRM entegrasyonu Faz 2 | E2: CRM | F2: =VLOOKUP(B2,'Türkkep Jira'!B:F,5,0) -> #N/A | G2: =IF(IFERROR(VLOOKUP(B2,'Devam Eden Sprint'!B:B,1,0),"-")=B2,"Devam Eden Sprint","-") -> - | H2: =IF(IFERROR(VLOOKUP(B2,'Gelecek Sprint'!B:B,1,0),"-")=B2,"Gelecek Sprint","-") -> - | I2: =IFERROR(IF(AND(G2="Devam Eden Sprint",H2="Gelecek Sprint"),"Devam Eden ve Gelecek Sprint",IF(G2="Devam Eden Sprint","Devam Eden Sprint",IF(H2="Gelecek Sprint","Gelecek Sprint","Ürün İş Listesi"))),"Ürün İş Listesi") -> Ürün İş Listesi | P2: DEVAM EDEN SPRİNT | Q2: Devam Eden Sprint | AC2: DEVAM EDEN SPRİNT | AD2: Devam Eden Sprint | AQ2: Status | AR2: (Birden Çok Öğe)
A3: Story | B3: CRM-497 | C3: Done | D3: Saklama Kota Yükleme İşlemleri | E3: CRM | F3: =VLOOKUP(B3,'Türkkep Jira'!B:F,5,0) -> #N/A | G3: =IF(IFERROR(VLOOKUP(B3,'Devam Eden Sprint'!B:B,1,0),"-")=B3,"Devam Eden Sprint","-") -> - | H3: =IF(IFERROR(VLOOKUP(B3,'Gelecek Sprint'!B:B,1,0),"-")=B3,"Gelecek Sprint","-") -> - | I3: =IFERROR(IF(AND(G3="Devam Eden Sprint",H3="Gelecek Sprint"),"Devam Eden ve Gelecek Sprint",IF(G3="Devam Eden Sprint","Devam Eden Sprint",IF(H3="Gelecek Sprint","Gelecek Sprint","Ürün İş Listesi"))),"Ürün İş Listesi") -> Ürün İş Listesi
A4: Story | B4: CRM-533 | C4: Done | D4: KEP IK Mahremiyet & CRM Entegrasyonu | E4: CRM | F4: =VLOOKUP(B4,'Türkkep Jira'!B:F,5,0) -> #N/A | G4: =IF(IFERROR(VLOOKUP(B4,'Devam Eden Sprint'!B:B,1,0),"-")=B4,"Devam Eden Sprint","-") -> - | H4: =IF(IFERROR(VLOOKUP(B4,'Gelecek Sprint'!B:B,1,0),"-")=B4,"Gelecek Sprint","-") -> - | I4: =IFERROR(IF(AND(G4="Devam Eden Sprint",H4="Gelecek Sprint"),"Devam Eden ve Gelecek Sprint",IF(G4="Devam Eden Sprint","Devam Eden Sprint",IF(H4="Gelecek Sprint","Gelecek Sprint","Ürün İş Listesi"))),"Ürün İş Listesi") -> Ürün İş Listesi | P4: Say Durum | Q4: Sütun Etiketleri | AC4: Toplam Story Point2 | AD4: Sütun Etiketleri | AQ4: Say Durum | AR4: Sütun Etiketleri
A5: Story | B5: CRM-535 | C5: Done | D5: KEP IK Blulut NVİ Tamamlanan Çalışanların QR Kodlu Islak İmza Taahhütnamelerinin Üretilmesi | E5: CRM | F5: =VLOOKUP(B5,'Türkkep Jira'!B:F,5,0) -> #N/A | G5: =IF(IFERROR(VLOOKUP(B5,'Devam Eden Sprint'!B:B,1,0),"-")=B5,"Devam Eden Sprint","-") -> - | H5: =IF(IFERROR(VLOOKUP(B5,'Gelecek Sprint'!B:B,1,0),"-")=B5,"Gelecek Sprint","-") -> - | I5: =IFERROR(IF(AND(G5="Devam Eden Sprint",H5="Gelecek Sprint"),"Devam Eden ve Gelecek Sprint",IF(G5="Devam Eden Sprint","Devam Eden Sprint",IF(H5="Gelecek Sprint","Gelecek Sprint","Ürün İş Listesi"))),"Ürün İş Listesi") -> Ürün İş Listesi | P5: Satır Etiketleri | Q5: Done | R5: In Progress | S5: Publish | T5: To Do | U5: TO TEST | V5: In Test | W5: Genel Toplam | Y5: Sprint Perf. Oranı | AC5: Satır Etiketleri | AD5: Done | AE5: In Progress | AF5: In Test | AG5: Publish | AH5: To Do | AI5: TO TEST | AJ5: (boş) | AK5: Genel Toplam | AM5: Sprint Perf. Oranı | AQ5: Satır Etiketleri | AR5: Bug | AS5: Story | AT5: Genel Toplam
A6: Story | B6: CRM-541 | C6: Done | D6: Üretim Modülü için Tablo Modellenmesi | E6: CRM | F6: =VLOOKUP(B6,'Türkkep Jira'!B:F,5,0) -> #N/A | G6: =IF(IFERROR(VLOOKUP(B6,'Devam Eden Sprint'!B:B,1,0),"-")=B6,"Devam Eden Sprint","-") -> - | H6: =IF(IFERROR(VLOOKUP(B6,'Gelecek Sprint'!B:B,1,0),"-")=B6,"Gelecek Sprint","-") -> - | I6: =IFERROR(IF(AND(G6="Devam Eden Sprint",H6="Gelecek Sprint"),"Devam Eden ve Gelecek Sprint",IF(G6="Devam Eden Sprint","Devam Eden Sprint",IF(H6="Gelecek Sprint","Gelecek Sprint","Ürün İş Listesi"))),"Ürün İş Listesi") -> Ürün İş Listesi | P6: CRM | Q6: 5 | R6: 2 | T6: 2 | U6: 16 | V6: 2 | W6: 27 | Y6: =Q6/W6 -> 0.18518519 | Z6: =(Q6+SUM(U6:V6))/W6 -> 0.85185185 | AC6: CRM | AD6: 16 | AF6: 7 | AI6: 36 | AK6: 59 | AM6: =AD6/AK6 -> 0.27118644 | AQ6: CRM | AS6: 27 | AT6: 27
A7: Story | B7: CRM-542 | C7: Done | D7: Üretim Modülü için Anasayfa Filtre Ekranı | E7: CRM | F7: =VLOOKUP(B7,'Türkkep Jira'!B:F,5,0) -> #N/A | G7: =IF(IFERROR(VLOOKUP(B7,'Devam Eden Sprint'!B:B,1,0),"-")=B7,"Devam Eden Sprint","-") -> - | H7: =IF(IFERROR(VLOOKUP(B7,'Gelecek Sprint'!B:B,1,0),"-")=B7,"Gelecek Sprint","-") -> - | I7: =IFERROR(IF(AND(G7="Devam Eden Sprint",H7="Gelecek Sprint"),"Devam Eden ve Gelecek Sprint",IF(G7="Devam Eden Sprint","Devam Eden Sprint",IF(H7="Gelecek Sprint","Gelecek Sprint","Ürün İş Listesi"))),"Ürün İş Listesi") -> Ürün İş Listesi | J7: 3 | P7: E-Defter | Q7: 1 | R7: 1 | T7: 2 | U7: 1 | W7: 5 | Y7: =Q7/W7 -> 0.2 | Z7: =(Q7+SUM(U7:V7))/W7 -> 0.4 | AC7: E-Defter | AH7: 6 | AI7: 3 | AK7: 9 | AM7: =AD7/AK7 -> 0 | AQ7: Destek Portal | AS7: 1 | AT7: 1
A8: Story | B8: CRM-543 | C8: Done | D8: Üretim Modülü Liste Sayfasının Geliştirmesi | E8: CRM | F8: =VLOOKUP(B8,'Türkkep Jira'!B:F,5,0) -> #N/A | G8: =IF(IFERROR(VLOOKUP(B8,'Devam Eden Sprint'!B:B,1,0),"-")=B8,"Devam Eden Sprint","-") -> - | H8: =IF(IFERROR(VLOOKUP(B8,'Gelecek Sprint'!B:B,1,0),"-")=B8,"Gelecek Sprint","-") -> - | I8: =IFERROR(IF(AND(G8="Devam Eden Sprint",H8="Gelecek Sprint"),"Devam Eden ve Gelecek Sprint",IF(G8="Devam Eden Sprint","Devam Eden Sprint",IF(H8="Gelecek Sprint","Gelecek Sprint","Ürün İş Listesi"))),"Ürün İş Listesi") -> Ürün İş Listesi | J8: 5 | P8: E-Fatura | Q8: 1 | R8: 3 | U8: 1 | W8: 5 | Y8: =Q8/W8 -> 0.2 | Z8: =(Q8+SUM(U8:V8))/W8 -> 0.4 | AC8: E-Fatura | AM8: =AD8/AK8 -> #DIV/0! | AQ8: E-Defter | AR8: 1 | AS8: 4 | AT8: 5
A9: Story | B9: CRM-544 | C9: Done | D9: Üretim Modülü Mütabakat Sürecinin Geliştirmesi | E9: CRM | F9: =VLOOKUP(B9,'Türkkep Jira'!B:F,5,0) -> #N/A | G9: =IF(IFERROR(VLOOKUP(B9,'Devam Eden Sprint'!B:B,1,0),"-")=B9,"Devam Eden Sprint","-") -> - | H9: =IF(IFERROR(VLOOKUP(B9,'Gelecek Sprint'!B:B,1,0),"-")=B9,"Gelecek Sprint","-") -> - | I9: =IFERROR(IF(AND(G9="Devam Eden Sprint",H9="Gelecek Sprint"),"Devam Eden ve Gelecek Sprint",IF(G9="Devam Eden Sprint","Devam Eden Sprint",IF(H9="Gelecek Sprint","Gelecek Sprint","Ürün İş Listesi"))),"Ürün İş Listesi") -> Ürün İş Listesi | P9: Entegrasyon Suit | T9: 1 | U9: 1 | W9: 2 | Y9: =Q9/W9 -> 0 | Z9: =(Q9+SUM(U9:V9))/W9 -> 0.5 | AC9: Entegrasyon Suit | AI9: 2 | AK9: 2 | AM9: =AD9/AK9 -> 0 | AQ9: E-Fatura | AR9: 1 | AS9: 4 | AT9: 5
A10: Story | B10: CRM-545 | C10: Done | D10: KEP IK Bulut NVİ Tamamlanmayan Çalışanların QR Kodlu Islak İmza Taahhütnamelerinin Üretilmesi için Servis Geliştirmesi | E10: CRM | F10: =VLOOKUP(B10,'Türkkep Jira'!B:F,5,0) -> #N/A | G10: =IF(IFERROR(VLOOKUP(B10,'Devam Eden Sprint'!B:B,1,0),"-")=B10,"Devam Eden Sprint","-") -> - | H10: =IF(IFERROR(VLOOKUP(B10,'Gelecek Sprint'!B:B,1,0),"-")=B10,"Gelecek Sprint","-") -> - | I10: =IFERROR(IF(AND(G10="Devam Eden Sprint",H10="Gelecek Sprint"),"Devam Eden ve Gelecek Sprint",IF(G10="Devam Eden Sprint","Devam Eden Sprint",IF(H10="Gelecek Sprint","Gelecek Sprint","Ürün İş Listesi"))),"Ürün İş Listesi") -> Ürün İş Listesi | P10: KEP | Q10: 1 | R10: 2 | W10: 3 | Y10: =Q10/W10 -> 0.33333333 | Z10: =(Q10+SUM(U10:V10))/W10 -> 0.33333333 | AC10: KEP | AD10: 3 | AE10: 8 | AK10: 11 | AM10: =AD10/AK10 -> 0.27272727 | AQ10: Entegrasyon Suit | AS10: 2 | AT10: 2
A11: Story | B11: CRM-546 | C11: Done | D11: KEP IK Bulut Çalışanların QR Kodlu Islak İmza Taahhütnamelerinin Uygulama İçerisinden Toplu İndirilmesi | E11: CRM | F11: =VLOOKUP(B11,'Türkkep Jira'!B:F,5,0) -> #N/A | G11: =IF(IFERROR(VLOOKUP(B11,'Devam Eden Sprint'!B:B,1,0),"-")=B11,"Devam Eden Sprint","-") -> - | H11: =IF(IFERROR(VLOOKUP(B11,'Gelecek Sprint'!B:B,1,0),"-")=B11,"Gelecek Sprint","-") -> - | I11: =IFERROR(IF(AND(G11="Devam Eden Sprint",H11="Gelecek Sprint"),"Devam Eden ve Gelecek Sprint",IF(G11="Devam Eden Sprint","Devam Eden Sprint",IF(H11="Gelecek Sprint","Gelecek Sprint","Ürün İş Listesi"))),"Ürün İş Listesi") -> Ürün İş Listesi | P11: Kep Assist | Q11: 3 | R11: 2 | T11: 1 | W11: 6 | Y11: =Q11/W11 -> 0.5 | Z11: =(Q11+SUM(U11:V11))/W11 -> 0.5 | AC11: Kep Assist | AD11: 5 | AE11: 3 | AK11: 8 | AM11: =AD11/AK11 -> 0.625 | AQ11: KEP | AS11: 3 | AT11: 3
A12: Story | B12: CRM-550 | C12: Done | D12: Multikep Müşteri Bilgilerinin CRM Sözleşmeden Aktarılması | E12: CRM | F12: =VLOOKUP(B12,'Türkkep Jira'!B:F,5,0) -> #N/A | G12: =IF(IFERROR(VLOOKUP(B12,'Devam Eden Sprint'!B:B,1,0),"-")=B12,"Devam Eden Sprint","-") -> - | H12: =IF(IFERROR(VLOOKUP(B12,'Gelecek Sprint'!B:B,1,0),"-")=B12,"Gelecek Sprint","-") -> - | I12: =IFERROR(IF(AND(G12="Devam Eden Sprint",H12="Gelecek Sprint"),"Devam Eden ve Gelecek Sprint",IF(G12="Devam Eden Sprint","Devam Eden Sprint",IF(H12="Gelecek Sprint","Gelecek Sprint","Ürün İş Listesi"))),"Ürün İş Listesi") -> Ürün İş Listesi | P12: KEP İK BULUT | R12: 1 | S12: 1 | T12: 2 | U12: 2 | W12: 6 | Y12: =Q12/W12 -> 0 | Z12: =(Q12+SUM(U12:V12))/W12 -> 0.33333333 | AC12: KEP İK BULUT | AE12: 3 | AG12: 2 | AH12: 2 | AI12: 6 | AJ12: 3 | AK12: 16 | AM12: =AD12/AK12 -> 0 | AQ12: Kep Assist | AR12: 1 | AS12: 5 | AT12: 6
A13: Story | B13: CRM-551 | C13: Done | D13: Multikep Modüllerinin CRM İşlem Kaydından Aktif Edilmesi | E13: CRM | F13: =VLOOKUP(B13,'Türkkep Jira'!B:F,5,0) -> #N/A | G13: =IF(IFERROR(VLOOKUP(B13,'Devam Eden Sprint'!B:B,1,0),"-")=B13,"Devam Eden Sprint","-") -> - | H13: =IF(IFERROR(VLOOKUP(B13,'Gelecek Sprint'!B:B,1,0),"-")=B13,"Gelecek Sprint","-") -> - | I13: =IFERROR(IF(AND(G13="Devam Eden Sprint",H13="Gelecek Sprint"),"Devam Eden ve Gelecek Sprint",IF(G13="Devam Eden Sprint","Devam Eden Sprint",IF(H13="Gelecek Sprint","Gelecek Sprint","Ürün İş Listesi"))),"Ürün İş Listesi") -> Ürün İş Listesi | P13: Mobil Uygulama | Q13: 5 | W13: 5 | Y13: =Q13/W13 -> 1 | Z13: =(Q13+SUM(U13:V13))/W13 -> 1 | AC13: Mobil Uygulama | AD13: 11 | AK13: 11 | AM13: =AD13/AK13 -> 1 | AQ13: KEP İK BULUT | AR13: 2 | AS13: 4 | AT13: 6
A14: Story | B14: CRM-553 | C14: Done | D14: Multikep Aktarılan Kullanıcılarının Update Edilmesi | E14: CRM | F14: =VLOOKUP(B14,'Türkkep Jira'!B:F,5,0) -> #N/A | G14: =IF(IFERROR(VLOOKUP(B14,'Devam Eden Sprint'!B:B,1,0),"-")=B14,"Devam Eden Sprint","-") -> - | H14: =IF(IFERROR(VLOOKUP(B14,'Gelecek Sprint'!B:B,1,0),"-")=B14,"Gelecek Sprint","-") -> - | I14: =IFERROR(IF(AND(G14="Devam Eden Sprint",H14="Gelecek Sprint"),"Devam Eden ve Gelecek Sprint",IF(G14="Devam Eden Sprint","Devam Eden Sprint",IF(H14="Gelecek Sprint","Gelecek Sprint","Ürün İş Listesi"))),"Ürün İş Listesi") -> Ürün İş Listesi | P14: Muhaberat Yönetim Sistemi | Q14: 1 | T14: 1 | W14: 2 | Y14: =Q14/W14 -> 0.5 | Z14: =(Q14+SUM(U14:V14))/W14 -> 0.5 | AC14: Muhaberat Yönetim Sistemi | AD14: 3 | AH14: 8 | AK14: 11 | AM14: =AD14/AK14 -> 0.27272727 | AQ14: Mobil Uygulama | AR14: 2 | AS14: 3 | AT14: 5
A15: Story | B15: CRM-554 | C15: Done | D15: CRM Kurumsal Müşteri Oluşturma MERSİS Entegrasyonu | E15: CRM | F15: =VLOOKUP(B15,'Türkkep Jira'!B:F,5,0) -> #N/A | G15: =IF(IFERROR(VLOOKUP(B15,'Devam Eden Sprint'!B:B,1,0),"-")=B15,"Devam Eden Sprint","-") -> - | H15: =IF(IFERROR(VLOOKUP(B15,'Gelecek Sprint'!B:B,1,0),"-")=B15,"Gelecek Sprint","-") -> - | I15: =IFERROR(IF(AND(G15="Devam Eden Sprint",H15="Gelecek Sprint"),"Devam Eden ve Gelecek Sprint",IF(G15="Devam Eden Sprint","Devam Eden Sprint",IF(H15="Gelecek Sprint","Gelecek Sprint","Ürün İş Listesi"))),"Ürün İş Listesi") -> Ürün İş Listesi | J15: 5 | P15: TÜRKKEP İMZA | T15: 1 | W15: 1 | Y15: =Q15/W15 -> 0 | Z15: =(Q15+SUM(U15:V15))/W15 -> 0 | AC15: MULTİKEP | AM15: =AD15/AK15 -> #DIV/0! | AQ15: Muhaberat Yönetim Sistemi | AS15: 2 | AT15: 2
A16: Story | B16: CRM-555 | C16: Done | D16: KEP IK Toplu Açılış için CRM den Çalışan Listesini Insert Etme | E16: CRM | F16: =VLOOKUP(B16,'Türkkep Jira'!B:F,5,0) -> #N/A | G16: =IF(IFERROR(VLOOKUP(B16,'Devam Eden Sprint'!B:B,1,0),"-")=B16,"Devam Eden Sprint","-") -> - | H16: =IF(IFERROR(VLOOKUP(B16,'Gelecek Sprint'!B:B,1,0),"-")=B16,"Gelecek Sprint","-") -> - | I16: =IFERROR(IF(AND(G16="Devam Eden Sprint",H16="Gelecek Sprint"),"Devam Eden ve Gelecek Sprint",IF(G16="Devam Eden Sprint","Devam Eden Sprint",IF(H16="Gelecek Sprint","Gelecek Sprint","Ürün İş Listesi"))),"Ürün İş Listesi") -> Ürün İş Listesi | P16: UKDS | Q16: 4 | W16: 4 | Y16: =Q16/W16 -> 1 | Z16: =(Q16+SUM(U16:V16))/W16 -> 1 | AC16: TÜRKKEP İMZA | AM16: =AD16/AK16 -> #DIV/0! | AQ16: TÜRKKEP İMZA | AS16: 1 | AT16: 1
A17: Story | B17: CRM-558 | C17: Done | D17: KEP IK Kullanıcı için İşlem Yetkilisi Değişiklikleri | E17: CRM | F17: =VLOOKUP(B17,'Türkkep Jira'!B:F,5,0) -> #N/A | G17: =IF(IFERROR(VLOOKUP(B17,'Devam Eden Sprint'!B:B,1,0),"-")=B17,"Devam Eden Sprint","-") -> - | H17: =IF(IFERROR(VLOOKUP(B17,'Gelecek Sprint'!B:B,1,0),"-")=B17,"Gelecek Sprint","-") -> - | I17: =IFERROR(IF(AND(G17="Devam Eden Sprint",H17="Gelecek Sprint"),"Devam Eden ve Gelecek Sprint",IF(G17="Devam Eden Sprint","Devam Eden Sprint",IF(H17="Gelecek Sprint","Gelecek Sprint","Ürün İş Listesi"))),"Ürün İş Listesi") -> Ürün İş Listesi | P17: Genel Toplam | Q17: 21 | R17: 11 | S17: 1 | T17: 10 | U17: 21 | V17: 2 | W17: 66 | Y17: =Q17/W17 -> 0.31818182 | Z17: =(Q17+SUM(U17:V17))/W17 -> 0.66666667 | AC17: Genel Toplam | AD17: 38 | AE17: 14 | AF17: 7 | AG17: 2 | AH17: 16 | AI17: 47 | AJ17: 3 | AK17: 127 | AM17: =AD17/AK17 -> 0.2992126 | AQ17: Genel Toplam | AR17: 7 | AS17: 56 | AT17: 63
A18: Story | B18: CRM-559 | C18: Done | D18: e-İmza UKDS Bilgilendirme Hk. | E18: CRM | F18: =VLOOKUP(B18,'Türkkep Jira'!B:F,5,0) -> #N/A | G18: =IF(IFERROR(VLOOKUP(B18,'Devam Eden Sprint'!B:B,1,0),"-")=B18,"Devam Eden Sprint","-") -> - | H18: =IF(IFERROR(VLOOKUP(B18,'Gelecek Sprint'!B:B,1,0),"-")=B18,"Gelecek Sprint","-") -> - | I18: =IFERROR(IF(AND(G18="Devam Eden Sprint",H18="Gelecek Sprint"),"Devam Eden ve Gelecek Sprint",IF(G18="Devam Eden Sprint","Devam Eden Sprint",IF(H18="Gelecek Sprint","Gelecek Sprint","Ürün İş Listesi"))),"Ürün İş Listesi") -> Ürün İş Listesi | Y18: =Q18/W18 -> #DIV/0! | Z18: =(Q18+SUM(U18:V18))/W18 -> #DIV/0! | AM18: =AD18/AK18 -> #DIV/0!
A19: Story | B19: CRM-560 | C19: Done | D19: MultiKEP Ek Kullanıcı Aktarılması | E19: CRM | F19: =VLOOKUP(B19,'Türkkep Jira'!B:F,5,0) -> #N/A | G19: =IF(IFERROR(VLOOKUP(B19,'Devam Eden Sprint'!B:B,1,0),"-")=B19,"Devam Eden Sprint","-") -> - | H19: =IF(IFERROR(VLOOKUP(B19,'Gelecek Sprint'!B:B,1,0),"-")=B19,"Gelecek Sprint","-") -> - | I19: =IFERROR(IF(AND(G19="Devam Eden Sprint",H19="Gelecek Sprint"),"Devam Eden ve Gelecek Sprint",IF(G19="Devam Eden Sprint","Devam Eden Sprint",IF(H19="Gelecek Sprint","Gelecek Sprint","Ürün İş Listesi"))),"Ürün İş Listesi") -> Ürün İş Listesi | Y19: =Q19/W19 -> #DIV/0! | Z19: =(Q19+SUM(U19:V19))/W19 -> #DIV/0!
A20: Story | B20: CRM-562 | C20: Done | D20: Yenileme Hatırlatma Maili Akışına Pasif Kullanıcı Kuralının Eklenmesi | E20: CRM | F20: =VLOOKUP(B20,'Türkkep Jira'!B:F,5,0) -> #N/A | G20: =IF(IFERROR(VLOOKUP(B20,'Devam Eden Sprint'!B:B,1,0),"-")=B20,"Devam Eden Sprint","-") -> - | H20: =IF(IFERROR(VLOOKUP(B20,'Gelecek Sprint'!B:B,1,0),"-")=B20,"Gelecek Sprint","-") -> - | I20: =IFERROR(IF(AND(G20="Devam Eden Sprint",H20="Gelecek Sprint"),"Devam Eden ve Gelecek Sprint",IF(G20="Devam Eden Sprint","Devam Eden Sprint",IF(H20="Gelecek Sprint","Gelecek Sprint","Ürün İş Listesi"))),"Ürün İş Listesi") -> Ürün İş Listesi | J20: 3 | Y20: =Q20/W20 -> #DIV/0! | Z20: =(Q20+SUM(U20:V20))/W20 -> #DIV/0!
A21: Story | B21: CRM-565 | C21: Done | D21: Toplu Teklif Oluşturma İşlemi | E21: CRM | F21: =VLOOKUP(B21,'Türkkep Jira'!B:F,5,0) -> #N/A | G21: =IF(IFERROR(VLOOKUP(B21,'Devam Eden Sprint'!B:B,1,0),"-")=B21,"Devam Eden Sprint","-") -> - | H21: =IF(IFERROR(VLOOKUP(B21,'Gelecek Sprint'!B:B,1,0),"-")=B21,"Gelecek Sprint","-") -> - | I21: =IFERROR(IF(AND(G21="Devam Eden Sprint",H21="Gelecek Sprint"),"Devam Eden ve Gelecek Sprint",IF(G21="Devam Eden Sprint","Devam Eden Sprint",IF(H21="Gelecek Sprint","Gelecek Sprint","Ürün İş Listesi"))),"Ürün İş Listesi") -> Ürün İş Listesi | Y21: =Q21/W21 -> #DIV/0! | Z21: =(Q21+SUM(U21:V21))/W21 -> #DIV/0!
A22: Story | B22: CRM-568 | C22: Done | D22: MERSİS Ek Geliştirme | E22: CRM | F22: =VLOOKUP(B22,'Türkkep Jira'!B:F,5,0) -> #N/A | G22: =IF(IFERROR(VLOOKUP(B22,'Devam Eden Sprint'!B:B,1,0),"-")=B22,"Devam Eden Sprint","-") -> - | H22: =IF(IFERROR(VLOOKUP(B22,'Gelecek Sprint'!B:B,1,0),"-")=B22,"Gelecek Sprint","-") -> - | I22: =IFERROR(IF(AND(G22="Devam Eden Sprint",H22="Gelecek Sprint"),"Devam Eden ve Gelecek Sprint",IF(G22="Devam Eden Sprint","Devam Eden Sprint",IF(H22="Gelecek Sprint","Gelecek Sprint","Ürün İş Listesi"))),"Ürün İş Listesi") -> Ürün İş Listesi | J22: 3 | Y22: =Q22/W22 -> #DIV/0! | Z22: =(Q22+SUM(U22:V22))/W22 -> #DIV/0!
A23: Story | B23: CRM-569 | C23: Done | D23: Satış Rapor Yeni Müşteri Statüsü | E23: CRM | F23: =VLOOKUP(B23,'Türkkep Jira'!B:F,5,0) -> #N/A | G23: =IF(IFERROR(VLOOKUP(B23,'Devam Eden Sprint'!B:B,1,0),"-")=B23,"Devam Eden Sprint","-") -> - | H23: =IF(IFERROR(VLOOKUP(B23,'Gelecek Sprint'!B:B,1,0),"-")=B23,"Gelecek Sprint","-") -> - | I23: =IFERROR(IF(AND(G23="Devam Eden Sprint",H23="Gelecek Sprint"),"Devam Eden ve Gelecek Sprint",IF(G23="Devam Eden Sprint","Devam Eden Sprint",IF(H23="Gelecek Sprint","Gelecek Sprint","Ürün İş Listesi"))),"Ürün İş Listesi") -> Ürün İş Listesi | J23: 2
A24: Bug | B24: CRM-570 | C24: Done | D24: Duplicate Teklif Numarası Hatası | E24: CRM | F24: =VLOOKUP(B24,'Türkkep Jira'!B:F,5,0) -> #N/A | G24: =IF(IFERROR(VLOOKUP(B24,'Devam Eden Sprint'!B:B,1,0),"-")=B24,"Devam Eden Sprint","-") -> - | H24: =IF(IFERROR(VLOOKUP(B24,'Gelecek Sprint'!B:B,1,0),"-")=B24,"Gelecek Sprint","-") -> - | I24: =IFERROR(IF(AND(G24="Devam Eden Sprint",H24="Gelecek Sprint"),"Devam Eden ve Gelecek Sprint",IF(G24="Devam Eden Sprint","Devam Eden Sprint",IF(H24="Gelecek Sprint","Gelecek Sprint","Ürün İş Listesi"))),"Ürün İş Listesi") -> Ürün İş Listesi | J24: 3
A25: Bug | B25: CRM-571 | C25: Done | D25: İş Bankası Sanal POS Api User Değişikliği | E25: CRM | F25: =VLOOKUP(B25,'Türkkep Jira'!B:F,5,0) -> #N/A | G25: =IF(IFERROR(VLOOKUP(B25,'Devam Eden Sprint'!B:B,1,0),"-")=B25,"Devam Eden Sprint","-") -> - | H25: =IF(IFERROR(VLOOKUP(B25,'Gelecek Sprint'!B:B,1,0),"-")=B25,"Gelecek Sprint","-") -> - | I25: =IFERROR(IF(AND(G25="Devam Eden Sprint",H25="Gelecek Sprint"),"Devam Eden ve Gelecek Sprint",IF(G25="Devam Eden Sprint","Devam Eden Sprint",IF(H25="Gelecek Sprint","Gelecek Sprint","Ürün İş Listesi"))),"Ürün İş Listesi") -> Ürün İş Listesi | J25: 1
A26: Bug | B26: CRM-572 | C26: Done | D26: Pazarama Bundle Hatası | E26: CRM | F26: =VLOOKUP(B26,'Türkkep Jira'!B:F,5,0) -> #N/A | G26: =IF(IFERROR(VLOOKUP(B26,'Devam Eden Sprint'!B:B,1,0),"-")=B26,"Devam Eden Sprint","-") -> - | H26: =IF(IFERROR(VLOOKUP(B26,'Gelecek Sprint'!B:B,1,0),"-")=B26,"Gelecek Sprint","-") -> - | I26: =IFERROR(IF(AND(G26="Devam Eden Sprint",H26="Gelecek Sprint"),"Devam Eden ve Gelecek Sprint",IF(G26="Devam Eden Sprint","Devam Eden Sprint",IF(H26="Gelecek Sprint","Gelecek Sprint","Ürün İş Listesi"))),"Ürün İş Listesi") -> Ürün İş Listesi | J26: 3
A27: Story | B27: CRM-573 | C27: Done | D27: Müşteri Modülünde Mail Adresi İle Müşteri Listeleme | E27: CRM | F27: =VLOOKUP(B27,'Türkkep Jira'!B:F,5,0) -> #N/A | G27: =IF(IFERROR(VLOOKUP(B27,'Devam Eden Sprint'!B:B,1,0),"-")=B27,"Devam Eden Sprint","-") -> - | H27: =IF(IFERROR(VLOOKUP(B27,'Gelecek Sprint'!B:B,1,0),"-")=B27,"Gelecek Sprint","-") -> - | I27: =IFERROR(IF(AND(G27="Devam Eden Sprint",H27="Gelecek Sprint"),"Devam Eden ve Gelecek Sprint",IF(G27="Devam Eden Sprint","Devam Eden Sprint",IF(H27="Gelecek Sprint","Gelecek Sprint","Ürün İş Listesi"))),"Ürün İş Listesi") -> Ürün İş Listesi | J27: 3 | P27: DEVAM EDEN SPRİNT | Q27: (Tümü) | AC27: Tüm Ürün İş Listesi
A28: Story | B28: CRM-574 | C28: Done | D28: Güvenlik Grubu Değişiklik Tarihçesi Hk. | E28: CRM | F28: =VLOOKUP(B28,'Türkkep Jira'!B:F,5,0) -> #N/A | G28: =IF(IFERROR(VLOOKUP(B28,'Devam Eden Sprint'!B:B,1,0),"-")=B28,"Devam Eden Sprint","-") -> - | H28: =IF(IFERROR(VLOOKUP(B28,'Gelecek Sprint'!B:B,1,0),"-")=B28,"Gelecek Sprint","-") -> - | I28: =IFERROR(IF(AND(G28="Devam Eden Sprint",H28="Gelecek Sprint"),"Devam Eden ve Gelecek Sprint",IF(G28="Devam Eden Sprint","Devam Eden Sprint",IF(H28="Gelecek Sprint","Gelecek Sprint","Ürün İş Listesi"))),"Ürün İş Listesi") -> Ürün İş Listesi | J28: 3 | AC28: Status | AD28: (Birden Çok Öğe)
A29: Story | B29: CRM-577 | C29: Done | D29: Dijikolay Potansiyel Müşteri Entegrasyonu Hk. | E29: CRM | F29: =VLOOKUP(B29,'Türkkep Jira'!B:F,5,0) -> #N/A | G29: =IF(IFERROR(VLOOKUP(B29,'Devam Eden Sprint'!B:B,1,0),"-")=B29,"Devam Eden Sprint","-") -> - | H29: =IF(IFERROR(VLOOKUP(B29,'Gelecek Sprint'!B:B,1,0),"-")=B29,"Gelecek Sprint","-") -> - | I29: =IFERROR(IF(AND(G29="Devam Eden Sprint",H29="Gelecek Sprint"),"Devam Eden ve Gelecek Sprint",IF(G29="Devam Eden Sprint","Devam Eden Sprint",IF(H29="Gelecek Sprint","Gelecek Sprint","Ürün İş Listesi"))),"Ürün İş Listesi") -> Ürün İş Listesi | J29: 1 | P29: Say Durum | Q29: Sütun Etiketleri
A30: Story | B30: CRM-580 | C30: Done | D30: KEP IK Toplu Açılış için CRM den Çalışan Listesini Insert Etme Ek Geliştirme | E30: CRM | F30: =VLOOKUP(B30,'Türkkep Jira'!B:F,5,0) -> #N/A | G30: =IF(IFERROR(VLOOKUP(B30,'Devam Eden Sprint'!B:B,1,0),"-")=B30,"Devam Eden Sprint","-") -> - | H30: =IF(IFERROR(VLOOKUP(B30,'Gelecek Sprint'!B:B,1,0),"-")=B30,"Gelecek Sprint","-") -> - | I30: =IFERROR(IF(AND(G30="Devam Eden Sprint",H30="Gelecek Sprint"),"Devam Eden ve Gelecek Sprint",IF(G30="Devam Eden Sprint","Devam Eden Sprint",IF(H30="Gelecek Sprint","Gelecek Sprint","Ürün İş Listesi"))),"Ürün İş Listesi") -> Ürün İş Listesi | J30: 8 | P30: Satır Etiketleri | Q30: Done | R30: In Progress | S30: In Test | T30: To Do | U30: TO TEST | V30: Publish | W30: Genel Toplam | AC30: Say Durum | AD30: Sütun Etiketleri | AJ30: İş Adedi | AQ30: Say Durum | AR30: Sütun Etiketleri
A31: Story | B31: CRM-581 | C31: Done | D31: Toplu IK Excel Yüklemede Hatalı Excelin Export Edilmesi | E31: CRM | F31: =VLOOKUP(B31,'Türkkep Jira'!B:F,5,0) -> #N/A | G31: =IF(IFERROR(VLOOKUP(B31,'Devam Eden Sprint'!B:B,1,0),"-")=B31,"Devam Eden Sprint","-") -> - | H31: =IF(IFERROR(VLOOKUP(B31,'Gelecek Sprint'!B:B,1,0),"-")=B31,"Gelecek Sprint","-") -> - | I31: =IFERROR(IF(AND(G31="Devam Eden Sprint",H31="Gelecek Sprint"),"Devam Eden ve Gelecek Sprint",IF(G31="Devam Eden Sprint","Devam Eden Sprint",IF(H31="Gelecek Sprint","Gelecek Sprint","Ürün İş Listesi"))),"Ürün İş Listesi") -> Ürün İş Listesi | J31: 3 | P31: CRM | Q31: 128 | S31: 5 | T31: 14 | U31: 5 | W31: 152 | Z31: =Q31/W31 -> 0.84210526 | AC31: Satır Etiketleri | AD31: Ürün İş Listesi | AE31: Devam Eden Sprint | AF31: Devam Eden ve Gelecek Sprint | AG31: Gelecek Sprint | AH31: Genel Toplam | AJ31: Tamamlanan Sprint | AK31: Gelecek Sprint | AQ31: Satır Etiketleri | AR31: Bug | AS31: Story | AT31: Sub-task | AU31: Task | AV31: Genel Toplam
A32: Bug | B32: CRM-582 | C32: Done | D32: Toplu KEP IK Açılış Excelinde Güvenlik Kelimesi | E32: CRM | F32: =VLOOKUP(B32,'Türkkep Jira'!B:F,5,0) -> #N/A | G32: =IF(IFERROR(VLOOKUP(B32,'Devam Eden Sprint'!B:B,1,0),"-")=B32,"Devam Eden Sprint","-") -> - | H32: =IF(IFERROR(VLOOKUP(B32,'Gelecek Sprint'!B:B,1,0),"-")=B32,"Gelecek Sprint","-") -> - | I32: =IFERROR(IF(AND(G32="Devam Eden Sprint",H32="Gelecek Sprint"),"Devam Eden ve Gelecek Sprint",IF(G32="Devam Eden Sprint","Devam Eden Sprint",IF(H32="Gelecek Sprint","Gelecek Sprint","Ürün İş Listesi"))),"Ürün İş Listesi") -> Ürün İş Listesi | J32: 2 | P32: Destek Portal | Q32: 26 | T32: 3 | W32: 29 | Z32: =Q32/W32 -> 0.89655172 | AC32: CRM | AD32: 177 | AE32: 5 | AF32: 22 | AG32: 2 | AH32: 206 | AJ32: =SUM(AD32:AE32) -> 182 | AK32: =ROUNDUP(SUM(AE32:AF32),0) -> 27 | AQ32: CRM | AR32: 10 | AS32: 196 | AV32: 206
A33: Story | B33: CRM-583 | C33: Done | D33: Toplu KEP IK Açılışlarında Bildirim Gönderilmesi | E33: CRM | F33: =VLOOKUP(B33,'Türkkep Jira'!B:F,5,0) -> #N/A | G33: =IF(IFERROR(VLOOKUP(B33,'Devam Eden Sprint'!B:B,1,0),"-")=B33,"Devam Eden Sprint","-") -> - | H33: =IF(IFERROR(VLOOKUP(B33,'Gelecek Sprint'!B:B,1,0),"-")=B33,"Gelecek Sprint","-") -> - | I33: =IFERROR(IF(AND(G33="Devam Eden Sprint",H33="Gelecek Sprint"),"Devam Eden ve Gelecek Sprint",IF(G33="Devam Eden Sprint","Devam Eden Sprint",IF(H33="Gelecek Sprint","Gelecek Sprint","Ürün İş Listesi"))),"Ürün İş Listesi") -> Ürün İş Listesi | J33: 3 | P33: E-Defter | Q33: 26 | W33: 26 | Z33: =Q33/W33 -> 1 | AC33: Destek Portal | AD33: 30 | AH33: 30 | AJ33: =SUM(AD33:AE33) -> 30 | AK33: =ROUNDUP(SUM(AE33:AF33),0) -> 0 | AQ33: Destek Portal | AR33: 11 | AS33: 20 | AV33: 31
A34: Story | B34: CRM-584 | C34: Done | D34: KEP Adresi ile Arama | E34: CRM | F34: =VLOOKUP(B34,'Türkkep Jira'!B:F,5,0) -> #N/A | G34: =IF(IFERROR(VLOOKUP(B34,'Devam Eden Sprint'!B:B,1,0),"-")=B34,"Devam Eden Sprint","-") -> - | H34: =IF(IFERROR(VLOOKUP(B34,'Gelecek Sprint'!B:B,1,0),"-")=B34,"Gelecek Sprint","-") -> - | I34: =IFERROR(IF(AND(G34="Devam Eden Sprint",H34="Gelecek Sprint"),"Devam Eden ve Gelecek Sprint",IF(G34="Devam Eden Sprint","Devam Eden Sprint",IF(H34="Gelecek Sprint","Gelecek Sprint","Ürün İş Listesi"))),"Ürün İş Listesi") -> Ürün İş Listesi | J34: 3 | P34: E-Fatura | Q34: 108 | T34: 19 | W34: 127 | Z34: =Q34/W34 -> 0.8503937 | AC34: E-Defter | AD34: 37 | AE34: 2 | AF34: 3 | AG34: 3 | AH34: 45 | AJ34: =SUM(AD34:AE34) -> 39 | AK34: =ROUNDUP(SUM(AE34:AF34),0) -> 5 | AQ34: E-Defter | AR34: 12 | AS34: 35 | AV34: 47
A35: Story | B35: CRM-587 | C35: To Do | D35: e-İmza Başvuruları için Dış Servis Yazılması | E35: CRM | F35: =VLOOKUP(B35,'Türkkep Jira'!B:F,5,0) -> #N/A | G35: =IF(IFERROR(VLOOKUP(B35,'Devam Eden Sprint'!B:B,1,0),"-")=B35,"Devam Eden Sprint","-") -> - | H35: =IF(IFERROR(VLOOKUP(B35,'Gelecek Sprint'!B:B,1,0),"-")=B35,"Gelecek Sprint","-") -> - | I35: =IFERROR(IF(AND(G35="Devam Eden Sprint",H35="Gelecek Sprint"),"Devam Eden ve Gelecek Sprint",IF(G35="Devam Eden Sprint","Devam Eden Sprint",IF(H35="Gelecek Sprint","Gelecek Sprint","Ürün İş Listesi"))),"Ürün İş Listesi") -> Ürün İş Listesi | P35: Entegrasyon Suit | Q35: 65 | R35: 1 | T35: 7 | U35: 1 | W35: 74 | Z35: =Q35/W35 -> 0.87837838 | AC35: E-Fatura | AD35: 166 | AE35: 1 | AF35: 4 | AG35: 7 | AH35: 178 | AJ35: =SUM(AD35:AE35) -> 167 | AK35: =ROUNDUP(SUM(AE35:AF35),0) -> 5 | AQ35: E-Fatura | AR35: 39 | AS35: 137 | AT35: 2 | AU35: 1 | AV35: 179
A36: Story | B36: CRM-588 | C36: Done | D36: Üretim Modülü Fatura Tahsilatların İşlenmesi | E36: CRM | F36: =VLOOKUP(B36,'Türkkep Jira'!B:F,5,0) -> #N/A | G36: =IF(IFERROR(VLOOKUP(B36,'Devam Eden Sprint'!B:B,1,0),"-")=B36,"Devam Eden Sprint","-") -> - | H36: =IF(IFERROR(VLOOKUP(B36,'Gelecek Sprint'!B:B,1,0),"-")=B36,"Gelecek Sprint","-") -> - | I36: =IFERROR(IF(AND(G36="Devam Eden Sprint",H36="Gelecek Sprint"),"Devam Eden ve Gelecek Sprint",IF(G36="Devam Eden Sprint","Devam Eden Sprint",IF(H36="Gelecek Sprint","Gelecek Sprint","Ürün İş Listesi"))),"Ürün İş Listesi") -> Ürün İş Listesi | J36: 3 | P36: KEP | Q36: 42 | R36: 1 | T36: 5 | W36: 48 | Z36: =Q36/W36 -> 0.875 | AC36: Entegrasyon Suit | AD36: 95 | AE36: 1 | AF36: 1 | AG36: 2 | AH36: 99 | AJ36: =SUM(AD36:AE36) -> 96 | AK36: =ROUNDUP(SUM(AE36:AF36),0) -> 2 | AQ36: Entegrasyon Suit | AR36: 37 | AS36: 62 | AV36: 99
A37: Story | B37: CRM-589 | C37: Done | D37: Duplicate Teklif Numarası için Alarm Maili Oluşturulması | E37: CRM | F37: =VLOOKUP(B37,'Türkkep Jira'!B:F,5,0) -> #N/A | G37: =IF(IFERROR(VLOOKUP(B37,'Devam Eden Sprint'!B:B,1,0),"-")=B37,"Devam Eden Sprint","-") -> - | H37: =IF(IFERROR(VLOOKUP(B37,'Gelecek Sprint'!B:B,1,0),"-")=B37,"Gelecek Sprint","-") -> - | I37: =IFERROR(IF(AND(G37="Devam Eden Sprint",H37="Gelecek Sprint"),"Devam Eden ve Gelecek Sprint",IF(G37="Devam Eden Sprint","Devam Eden Sprint",IF(H37="Gelecek Sprint","Gelecek Sprint","Ürün İş Listesi"))),"Ürün İş Listesi") -> Ürün İş Listesi | J37: 1 | P37: Kep Assist | Q37: 48 | T37: 1 | W37: 49 | Z37: =Q37/W37 -> 0.97959184 | AC37: KEP | AD37: 50 | AE37: 3 | AH37: 53 | AJ37: =SUM(AD37:AE37) -> 53 | AK37: =ROUNDUP(SUM(AE37:AF37),0) -> 3 | AQ37: KEP | AR37: 7 | AS37: 46 | AV37: 53
A38: Story | B38: CRM-590 | C38: Done | D38: Aynı TCKN ye Ait Birden Fazla KEP Adresinin KEP IK Aktarım Süreci | E38: CRM | F38: =VLOOKUP(B38,'Türkkep Jira'!B:F,5,0) -> #N/A | G38: =IF(IFERROR(VLOOKUP(B38,'Devam Eden Sprint'!B:B,1,0),"-")=B38,"Devam Eden Sprint","-") -> - | H38: =IF(IFERROR(VLOOKUP(B38,'Gelecek Sprint'!B:B,1,0),"-")=B38,"Gelecek Sprint","-") -> - | I38: =IFERROR(IF(AND(G38="Devam Eden Sprint",H38="Gelecek Sprint"),"Devam Eden ve Gelecek Sprint",IF(G38="Devam Eden Sprint","Devam Eden Sprint",IF(H38="Gelecek Sprint","Gelecek Sprint","Ürün İş Listesi"))),"Ürün İş Listesi") -> Ürün İş Listesi | P38: KEP İK BULUT | Q38: 82 | T38: 8 | W38: 90 | Z38: =Q38/W38 -> 0.91111111 | AC38: Kep Assist | AD38: 68 | AE38: 4 | AF38: 2 | AG38: 1 | AH38: 75 | AJ38: =SUM(AD38:AE38) -> 72 | AK38: =ROUNDUP(SUM(AE38:AF38),0) -> 6 | AQ38: Kep Assist | AR38: 19 | AS38: 53 | AT38: 3 | AV38: 75
A39: Story | B39: CRM-591 | C39: Done | D39: Pasif Olan KEP Adresin Tekrar Aktif Edilmesi (UKDS) | E39: CRM | F39: =VLOOKUP(B39,'Türkkep Jira'!B:F,5,0) -> #N/A | G39: =IF(IFERROR(VLOOKUP(B39,'Devam Eden Sprint'!B:B,1,0),"-")=B39,"Devam Eden Sprint","-") -> - | H39: =IF(IFERROR(VLOOKUP(B39,'Gelecek Sprint'!B:B,1,0),"-")=B39,"Gelecek Sprint","-") -> - | I39: =IFERROR(IF(AND(G39="Devam Eden Sprint",H39="Gelecek Sprint"),"Devam Eden ve Gelecek Sprint",IF(G39="Devam Eden Sprint","Devam Eden Sprint",IF(H39="Gelecek Sprint","Gelecek Sprint","Ürün İş Listesi"))),"Ürün İş Listesi") -> Ürün İş Listesi | P39: Mobil Uygulama | Q39: 97 | T39: 10 | U39: 2 | V39: 1 | W39: 110 | Z39: =Q39/W39 -> 0.88181818 | AC39: KEP İK BULUT | AD39: 130 | AE39: 7 | AG39: 3 | AH39: 140 | AJ39: =SUM(AD39:AE39) -> 137 | AK39: =ROUNDUP(SUM(AE39:AF39),0) -> 7 | AQ39: KEP İK BULUT | AR39: 33 | AS39: 104 | AT39: 3 | AV39: 140
A40: Story | B40: CRM-592 | C40: Done | D40: Pasif Olan KEP Hesabın Tekrar Aktif Edilmesi (CRM) | E40: CRM | F40: =VLOOKUP(B40,'Türkkep Jira'!B:F,5,0) -> #N/A | G40: =IF(IFERROR(VLOOKUP(B40,'Devam Eden Sprint'!B:B,1,0),"-")=B40,"Devam Eden Sprint","-") -> - | H40: =IF(IFERROR(VLOOKUP(B40,'Gelecek Sprint'!B:B,1,0),"-")=B40,"Gelecek Sprint","-") -> - | I40: =IFERROR(IF(AND(G40="Devam Eden Sprint",H40="Gelecek Sprint"),"Devam Eden ve Gelecek Sprint",IF(G40="Devam Eden Sprint","Devam Eden Sprint",IF(H40="Gelecek Sprint","Gelecek Sprint","Ürün İş Listesi"))),"Ürün İş Listesi") -> Ürün İş Listesi | P40: Muhaberat Yönetim Sistemi | Q40: 41 | W40: 41 | Z40: =Q40/W40 -> 1 | AC40: Mobil Uygulama | AD40: 140 | AE40: 5 | AG40: 6 | AH40: 151 | AJ40: =SUM(AD40:AE40) -> 145 | AK40: =ROUNDUP(SUM(AE40:AF40),0) -> 5 | AQ40: Mobil Uygulama | AR40: 65 | AS40: 86 | AV40: 151
A41: Story | B41: CRM-593 | C41: Done | D41: Mersis sorgu sonucunda dönen NACE kodu bilgisinin alınması | E41: CRM | F41: =VLOOKUP(B41,'Türkkep Jira'!B:F,5,0) -> #N/A | G41: =IF(IFERROR(VLOOKUP(B41,'Devam Eden Sprint'!B:B,1,0),"-")=B41,"Devam Eden Sprint","-") -> - | H41: =IF(IFERROR(VLOOKUP(B41,'Gelecek Sprint'!B:B,1,0),"-")=B41,"Gelecek Sprint","-") -> - | I41: =IFERROR(IF(AND(G41="Devam Eden Sprint",H41="Gelecek Sprint"),"Devam Eden ve Gelecek Sprint",IF(G41="Devam Eden Sprint","Devam Eden Sprint",IF(H41="Gelecek Sprint","Gelecek Sprint","Ürün İş Listesi"))),"Ürün İş Listesi") -> Ürün İş Listesi | J41: 1 | P41: TÜRKKEP İMZA | Q41: 25 | T41: 2 | W41: 27 | Z41: =Q41/W41 -> 0.92592593 | AC41: Muhaberat Yönetim Sistemi | AD41: 56 | AE41: 1 | AF41: 1 | AH41: 58 | AJ41: =SUM(AD41:AE41) -> 57 | AK41: =ROUNDUP(SUM(AE41:AF41),0) -> 2 | AQ41: Muhaberat Yönetim Sistemi | AR41: 17 | AS41: 41 | AV41: 58
A42: Story | B42: CRM-594 | C42: To Do | D42: KEP Assist ürün kullanım raporu | E42: CRM | F42: =VLOOKUP(B42,'Türkkep Jira'!B:F,5,0) -> #N/A | G42: =IF(IFERROR(VLOOKUP(B42,'Devam Eden Sprint'!B:B,1,0),"-")=B42,"Devam Eden Sprint","-") -> - | H42: =IF(IFERROR(VLOOKUP(B42,'Gelecek Sprint'!B:B,1,0),"-")=B42,"Gelecek Sprint","-") -> - | I42: =IFERROR(IF(AND(G42="Devam Eden Sprint",H42="Gelecek Sprint"),"Devam Eden ve Gelecek Sprint",IF(G42="Devam Eden Sprint","Devam Eden Sprint",IF(H42="Gelecek Sprint","Gelecek Sprint","Ürün İş Listesi"))),"Ürün İş Listesi") -> Ürün İş Listesi | J42: 5 | P42: UETS | Q42: 9 | T42: 1 | W42: 10 | Z42: =Q42/W42 -> 0.9 | AC42: TÜRKKEP İMZA | AD42: 28 | AE42: 1 | AH42: 29 | AJ42: =SUM(AD42:AE42) -> 29 | AK42: =ROUNDUP(SUM(AE42:AF42),0) -> 1 | AQ42: TÜRKKEP İMZA | AR42: 10 | AS42: 27 | AV42: 37
A43: Story | B43: CRM-597 | C43: Done | D43: Sipariş detayında MERSİS sorgu sonucu başarılı dönmemesi | E43: CRM | F43: =VLOOKUP(B43,'Türkkep Jira'!B:F,5,0) -> #N/A | G43: =IF(IFERROR(VLOOKUP(B43,'Devam Eden Sprint'!B:B,1,0),"-")=B43,"Devam Eden Sprint","-") -> - | H43: =IF(IFERROR(VLOOKUP(B43,'Gelecek Sprint'!B:B,1,0),"-")=B43,"Gelecek Sprint","-") -> - | I43: =IFERROR(IF(AND(G43="Devam Eden Sprint",H43="Gelecek Sprint"),"Devam Eden ve Gelecek Sprint",IF(G43="Devam Eden Sprint","Devam Eden Sprint",IF(H43="Gelecek Sprint","Gelecek Sprint","Ürün İş Listesi"))),"Ürün İş Listesi") -> Ürün İş Listesi | J43: 1 | P43: UZAKTAN KİMLİK DOĞRULAMA | Q43: 49 | T43: 3 | W43: 52 | Z43: =Q43/W43 -> 0.94230769 | AC43: UETS | AD43: 11 | AH43: 11 | AJ43: =SUM(AD43:AE43) -> 11 | AK43: =ROUNDUP(SUM(AE43:AF43),0) -> 0 | AQ43: UETS | AS43: 11 | AV43: 11
A44: Story | B44: CRM-598 | C44: Done | D44: Kamu/Oda/Vakıf/Dernek müşteri tipi için KEP hesap oluşturulabilmesi | E44: CRM | F44: =VLOOKUP(B44,'Türkkep Jira'!B:F,5,0) -> #N/A | G44: =IF(IFERROR(VLOOKUP(B44,'Devam Eden Sprint'!B:B,1,0),"-")=B44,"Devam Eden Sprint","-") -> - | H44: =IF(IFERROR(VLOOKUP(B44,'Gelecek Sprint'!B:B,1,0),"-")=B44,"Gelecek Sprint","-") -> - | I44: =IFERROR(IF(AND(G44="Devam Eden Sprint",H44="Gelecek Sprint"),"Devam Eden ve Gelecek Sprint",IF(G44="Devam Eden Sprint","Devam Eden Sprint",IF(H44="Gelecek Sprint","Gelecek Sprint","Ürün İş Listesi"))),"Ürün İş Listesi") -> Ürün İş Listesi | J44: 1 | P44: Kep Web Servisi | Q44: 5 | R44: 1 | W44: 6 | Z44: =Q44/W44 -> 0.83333333 | AC44: UZAKTAN KİMLİK DOĞRULAMA | AD44: 61 | AH44: 61 | AJ44: =SUM(AD44:AE44) -> 61 | AK44: =ROUNDUP(SUM(AE44:AF44),0) -> 0 | AQ44: UZAKTAN KİMLİK DOĞRULAMA | AR44: 6 | AS44: 56 | AV44: 62
A45: Story | B45: CRM-599 | C45: Done | D45: Manuel müşteri kaydı oluşturma | E45: CRM | F45: =VLOOKUP(B45,'Türkkep Jira'!B:F,5,0) -> #N/A | G45: =IF(IFERROR(VLOOKUP(B45,'Devam Eden Sprint'!B:B,1,0),"-")=B45,"Devam Eden Sprint","-") -> - | H45: =IF(IFERROR(VLOOKUP(B45,'Gelecek Sprint'!B:B,1,0),"-")=B45,"Gelecek Sprint","-") -> - | I45: =IFERROR(IF(AND(G45="Devam Eden Sprint",H45="Gelecek Sprint"),"Devam Eden ve Gelecek Sprint",IF(G45="Devam Eden Sprint","Devam Eden Sprint",IF(H45="Gelecek Sprint","Gelecek Sprint","Ürün İş Listesi"))),"Ürün İş Listesi") -> Ürün İş Listesi | J45: 1 | P45: Detsis | Q45: 10 | W45: 10 | Z45: =Q45/W45 -> 1 | AC45: Kep Web Servisi | AD45: 6 | AH45: 6 | AJ45: =SUM(AD45:AE45) -> 6 | AK45: =ROUNDUP(SUM(AE45:AF45),0) -> 0 | AQ45: Kep Web Servisi | AR45: 1 | AS45: 5 | AV45: 6
A46: Story | B46: CRM-600 | C46: Done | D46: MERSİS sonucunda eşleşme sağlanamaması | E46: CRM | F46: =VLOOKUP(B46,'Türkkep Jira'!B:F,5,0) -> #N/A | G46: =IF(IFERROR(VLOOKUP(B46,'Devam Eden Sprint'!B:B,1,0),"-")=B46,"Devam Eden Sprint","-") -> - | H46: =IF(IFERROR(VLOOKUP(B46,'Gelecek Sprint'!B:B,1,0),"-")=B46,"Gelecek Sprint","-") -> - | I46: =IFERROR(IF(AND(G46="Devam Eden Sprint",H46="Gelecek Sprint"),"Devam Eden ve Gelecek Sprint",IF(G46="Devam Eden Sprint","Devam Eden Sprint",IF(H46="Gelecek Sprint","Gelecek Sprint","Ürün İş Listesi"))),"Ürün İş Listesi") -> Ürün İş Listesi | J46: 1 | P46: Imza Entegrasyon Uygulaması | Q46: 8 | W46: 8 | Z46: =Q46/W46 -> 1 | AC46: Detsis | AD46: 10 | AH46: 10 | AJ46: =SUM(AD46:AE46) -> 10 | AK46: =ROUNDUP(SUM(AE46:AF46),0) -> 0 | AQ46: Detsis | AS46: 10 | AV46: 10
A47: Story | B47: CRM-601 | C47: Done | D47: KEP Assist rapor servisine entegrasyon sağlanması | E47: CRM | F47: =VLOOKUP(B47,'Türkkep Jira'!B:F,5,0) -> #N/A | G47: =IF(IFERROR(VLOOKUP(B47,'Devam Eden Sprint'!B:B,1,0),"-")=B47,"Devam Eden Sprint","-") -> - | H47: =IF(IFERROR(VLOOKUP(B47,'Gelecek Sprint'!B:B,1,0),"-")=B47,"Gelecek Sprint","-") -> - | I47: =IFERROR(IF(AND(G47="Devam Eden Sprint",H47="Gelecek Sprint"),"Devam Eden ve Gelecek Sprint",IF(G47="Devam Eden Sprint","Devam Eden Sprint",IF(H47="Gelecek Sprint","Gelecek Sprint","Ürün İş Listesi"))),"Ürün İş Listesi") -> Ürün İş Listesi | J47: 1 | P47: Yapay Zeka Destekli Çağrı Karşılama | Q47: 9 | R47: 1 | T47: 1 | W47: 11 | Z47: =Q47/W47 -> 0.81818182 | AC47: Yapay Zeka Destekli Çağrı Karşılama | AD47: 13 | AH47: 13 | AJ47: =SUM(AD47:AE47) -> 13 | AK47: =ROUNDUP(SUM(AE47:AF47),0) -> 0 | AQ47: Yapay Zeka Destekli Çağrı Karşılama | AR47: 2 | AS47: 11 | AV47: 13
A48: Story | B48: CRM-602 | C48: Done | D48: KEP Assist organizasyon ID bilgisinin kaydedilmesi | E48: CRM | F48: =VLOOKUP(B48,'Türkkep Jira'!B:F,5,0) -> #N/A | G48: =IF(IFERROR(VLOOKUP(B48,'Devam Eden Sprint'!B:B,1,0),"-")=B48,"Devam Eden Sprint","-") -> - | H48: =IF(IFERROR(VLOOKUP(B48,'Gelecek Sprint'!B:B,1,0),"-")=B48,"Gelecek Sprint","-") -> - | I48: =IFERROR(IF(AND(G48="Devam Eden Sprint",H48="Gelecek Sprint"),"Devam Eden ve Gelecek Sprint",IF(G48="Devam Eden Sprint","Devam Eden Sprint",IF(H48="Gelecek Sprint","Gelecek Sprint","Ürün İş Listesi"))),"Ürün İş Listesi") -> Ürün İş Listesi | J48: 1 | P48: Genel Toplam | Q48: 778 | R48: 4 | S48: 5 | T48: 74 | U48: 8 | V48: 1 | W48: 870 | Z48: =Q48/W48 -> 0.89425287 | AC48: Genel Toplam | AD48: 1078 | AE48: 30 | AF48: 33 | AG48: 24 | AH48: 1165 | AJ48: =SUM(AD48:AE48) -> 1108 | AK48: =ROUNDUP(SUM(AE48:AF48),0) -> 63 | AQ48: Genel Toplam | AR48: 269 | AS48: 900 | AT48: 8 | AU48: 1 | AV48: 1178
A49: Story | B49: CRM-603 | C49: Done | D49: Sözleşmeler sayfasına kullanım bilgilerinin kaydedilmesi | E49: CRM | F49: =VLOOKUP(B49,'Türkkep Jira'!B:F,5,0) -> #N/A | G49: =IF(IFERROR(VLOOKUP(B49,'Devam Eden Sprint'!B:B,1,0),"-")=B49,"Devam Eden Sprint","-") -> - | H49: =IF(IFERROR(VLOOKUP(B49,'Gelecek Sprint'!B:B,1,0),"-")=B49,"Gelecek Sprint","-") -> - | I49: =IFERROR(IF(AND(G49="Devam Eden Sprint",H49="Gelecek Sprint"),"Devam Eden ve Gelecek Sprint",IF(G49="Devam Eden Sprint","Devam Eden Sprint",IF(H49="Gelecek Sprint","Gelecek Sprint","Ürün İş Listesi"))),"Ürün İş Listesi") -> Ürün İş Listesi | J49: 5 | AJ49: =SUM(AD49:AE49) -> 0 | AK49: =ROUNDUP(SUM(AE49:AF49),0) -> 0
A50: Story | B50: CRM-604 | C50: Done | D50: Kullanım bilgilerinin güncellenmesi için job yazılması | E50: CRM | F50: =VLOOKUP(B50,'Türkkep Jira'!B:F,5,0) -> #N/A | G50: =IF(IFERROR(VLOOKUP(B50,'Devam Eden Sprint'!B:B,1,0),"-")=B50,"Devam Eden Sprint","-") -> - | H50: =IF(IFERROR(VLOOKUP(B50,'Gelecek Sprint'!B:B,1,0),"-")=B50,"Gelecek Sprint","-") -> - | I50: =IFERROR(IF(AND(G50="Devam Eden Sprint",H50="Gelecek Sprint"),"Devam Eden ve Gelecek Sprint",IF(G50="Devam Eden Sprint","Devam Eden Sprint",IF(H50="Gelecek Sprint","Gelecek Sprint","Ürün İş Listesi"))),"Ürün İş Listesi") -> Ürün İş Listesi | J50: 2
A51: Story | B51: CRM-605 | C51: Done | D51: Belirli tarih aralığındaki kullanım bilgilerinin gösterilmesi | E51: CRM | F51: =VLOOKUP(B51,'Türkkep Jira'!B:F,5,0) -> #N/A | G51: =IF(IFERROR(VLOOKUP(B51,'Devam Eden Sprint'!B:B,1,0),"-")=B51,"Devam Eden Sprint","-") -> - | H51: =IF(IFERROR(VLOOKUP(B51,'Gelecek Sprint'!B:B,1,0),"-")=B51,"Gelecek Sprint","-") -> - | I51: =IFERROR(IF(AND(G51="Devam Eden Sprint",H51="Gelecek Sprint"),"Devam Eden ve Gelecek Sprint",IF(G51="Devam Eden Sprint","Devam Eden Sprint",IF(H51="Gelecek Sprint","Gelecek Sprint","Ürün İş Listesi"))),"Ürün İş Listesi") -> Ürün İş Listesi | J51: 3
A52: Story | B52: CRM-608 | C52: Done | D52: Duplicate Fatura Numaraları için Düzenleme | E52: CRM | F52: =VLOOKUP(B52,'Türkkep Jira'!B:F,5,0) -> #N/A | G52: =IF(IFERROR(VLOOKUP(B52,'Devam Eden Sprint'!B:B,1,0),"-")=B52,"Devam Eden Sprint","-") -> - | H52: =IF(IFERROR(VLOOKUP(B52,'Gelecek Sprint'!B:B,1,0),"-")=B52,"Gelecek Sprint","-") -> - | I52: =IFERROR(IF(AND(G52="Devam Eden Sprint",H52="Gelecek Sprint"),"Devam Eden ve Gelecek Sprint",IF(G52="Devam Eden Sprint","Devam Eden Sprint",IF(H52="Gelecek Sprint","Gelecek Sprint","Ürün İş Listesi"))),"Ürün İş Listesi") -> Ürün İş Listesi | J52: 2
A53: Story | B53: CRM-609 | C53: Done | D53: Müşterinin Oluşturulma Tarihi Düzenlemesi | E53: CRM | F53: =VLOOKUP(B53,'Türkkep Jira'!B:F,5,0) -> #N/A | G53: =IF(IFERROR(VLOOKUP(B53,'Devam Eden Sprint'!B:B,1,0),"-")=B53,"Devam Eden Sprint","-") -> - | H53: =IF(IFERROR(VLOOKUP(B53,'Gelecek Sprint'!B:B,1,0),"-")=B53,"Gelecek Sprint","-") -> - | I53: =IFERROR(IF(AND(G53="Devam Eden Sprint",H53="Gelecek Sprint"),"Devam Eden ve Gelecek Sprint",IF(G53="Devam Eden Sprint","Devam Eden Sprint",IF(H53="Gelecek Sprint","Gelecek Sprint","Ürün İş Listesi"))),"Ürün İş Listesi") -> Ürün İş Listesi | J53: 1
A54: Story | B54: CRM-610 | C54: Done | D54: Test ortamı MERSİS entegrasyonu kontrol adımları | E54: CRM | F54: =VLOOKUP(B54,'Türkkep Jira'!B:F,5,0) -> #N/A | G54: =IF(IFERROR(VLOOKUP(B54,'Devam Eden Sprint'!B:B,1,0),"-")=B54,"Devam Eden Sprint","-") -> - | H54: =IF(IFERROR(VLOOKUP(B54,'Gelecek Sprint'!B:B,1,0),"-")=B54,"Gelecek Sprint","-") -> - | I54: =IFERROR(IF(AND(G54="Devam Eden Sprint",H54="Gelecek Sprint"),"Devam Eden ve Gelecek Sprint",IF(G54="Devam Eden Sprint","Devam Eden Sprint",IF(H54="Gelecek Sprint","Gelecek Sprint","Ürün İş Listesi"))),"Ürün İş Listesi") -> Ürün İş Listesi | J54: 2
A55: Story | B55: CRM-613 | C55: Done | D55: Test ortamında NACE kodu bilgisi alanının getirilmesi | E55: CRM | F55: =VLOOKUP(B55,'Türkkep Jira'!B:F,5,0) -> #N/A | G55: =IF(IFERROR(VLOOKUP(B55,'Devam Eden Sprint'!B:B,1,0),"-")=B55,"Devam Eden Sprint","-") -> - | H55: =IF(IFERROR(VLOOKUP(B55,'Gelecek Sprint'!B:B,1,0),"-")=B55,"Gelecek Sprint","-") -> - | I55: =IFERROR(IF(AND(G55="Devam Eden Sprint",H55="Gelecek Sprint"),"Devam Eden ve Gelecek Sprint",IF(G55="Devam Eden Sprint","Devam Eden Sprint",IF(H55="Gelecek Sprint","Gelecek Sprint","Ürün İş Listesi"))),"Ürün İş Listesi") -> Ürün İş Listesi | J55: 1
A56: Story | B56: CRM-614 | C56: Done | D56: Tobb Mersis servisi bakiye kontrolü için bildirim maili gönderilmesi | E56: CRM | F56: =VLOOKUP(B56,'Türkkep Jira'!B:F,5,0) -> #N/A | G56: =IF(IFERROR(VLOOKUP(B56,'Devam Eden Sprint'!B:B,1,0),"-")=B56,"Devam Eden Sprint","-") -> - | H56: =IF(IFERROR(VLOOKUP(B56,'Gelecek Sprint'!B:B,1,0),"-")=B56,"Gelecek Sprint","-") -> - | I56: =IFERROR(IF(AND(G56="Devam Eden Sprint",H56="Gelecek Sprint"),"Devam Eden ve Gelecek Sprint",IF(G56="Devam Eden Sprint","Devam Eden Sprint",IF(H56="Gelecek Sprint","Gelecek Sprint","Ürün İş Listesi"))),"Ürün İş Listesi") -> Ürün İş Listesi | J56: 2
A57: Story | B57: CRM-616 | C57: Done | D57: Turmob servis tüketim bilgilerinin kaydedilmesi | E57: CRM | F57: =VLOOKUP(B57,'Türkkep Jira'!B:F,5,0) -> #N/A | G57: =IF(IFERROR(VLOOKUP(B57,'Devam Eden Sprint'!B:B,1,0),"-")=B57,"Devam Eden Sprint","-") -> - | H57: =IF(IFERROR(VLOOKUP(B57,'Gelecek Sprint'!B:B,1,0),"-")=B57,"Gelecek Sprint","-") -> - | I57: =IFERROR(IF(AND(G57="Devam Eden Sprint",H57="Gelecek Sprint"),"Devam Eden ve Gelecek Sprint",IF(G57="Devam Eden Sprint","Devam Eden Sprint",IF(H57="Gelecek Sprint","Gelecek Sprint","Ürün İş Listesi"))),"Ürün İş Listesi") -> Ürün İş Listesi | J57: 3
A58: Story | B58: CRM-617 | C58: Done | D58: Turmob servis tüketim verilerinin Fatura bakiyesinden düşülmesi | E58: CRM | F58: =VLOOKUP(B58,'Türkkep Jira'!B:F,5,0) -> #N/A | G58: =IF(IFERROR(VLOOKUP(B58,'Devam Eden Sprint'!B:B,1,0),"-")=B58,"Devam Eden Sprint","-") -> - | H58: =IF(IFERROR(VLOOKUP(B58,'Gelecek Sprint'!B:B,1,0),"-")=B58,"Gelecek Sprint","-") -> - | I58: =IFERROR(IF(AND(G58="Devam Eden Sprint",H58="Gelecek Sprint"),"Devam Eden ve Gelecek Sprint",IF(G58="Devam Eden Sprint","Devam Eden Sprint",IF(H58="Gelecek Sprint","Gelecek Sprint","Ürün İş Listesi"))),"Ürün İş Listesi") -> Ürün İş Listesi | J58: 1
A59: Story | B59: CRM-618 | C59: Done | D59: Fatura tüketim verileri içeren raporların güncellenmesi | E59: CRM | F59: =VLOOKUP(B59,'Türkkep Jira'!B:F,5,0) -> #N/A | G59: =IF(IFERROR(VLOOKUP(B59,'Devam Eden Sprint'!B:B,1,0),"-")=B59,"Devam Eden Sprint","-") -> - | H59: =IF(IFERROR(VLOOKUP(B59,'Gelecek Sprint'!B:B,1,0),"-")=B59,"Gelecek Sprint","-") -> - | I59: =IFERROR(IF(AND(G59="Devam Eden Sprint",H59="Gelecek Sprint"),"Devam Eden ve Gelecek Sprint",IF(G59="Devam Eden Sprint","Devam Eden Sprint",IF(H59="Gelecek Sprint","Gelecek Sprint","Ürün İş Listesi"))),"Ürün İş Listesi") -> Ürün İş Listesi | J59: 1
A60: Story | B60: DP-266 | C60: Done | D60: İptal Firmaların Veri Teslimi İçin Sorgu Ekranı Eklenmesi | E60: Destek Portal | F60: =VLOOKUP(B60,'Türkkep Jira'!B:F,5,0) -> #N/A | G60: =IF(IFERROR(VLOOKUP(B60,'Devam Eden Sprint'!B:B,1,0),"-")=B60,"Devam Eden Sprint","-") -> - | H60: =IF(IFERROR(VLOOKUP(B60,'Gelecek Sprint'!B:B,1,0),"-")=B60,"Gelecek Sprint","-") -> - | I60: =IFERROR(IF(AND(G60="Devam Eden Sprint",H60="Gelecek Sprint"),"Devam Eden ve Gelecek Sprint",IF(G60="Devam Eden Sprint","Devam Eden Sprint",IF(H60="Gelecek Sprint","Gelecek Sprint","Ürün İş Listesi"))),"Ürün İş Listesi") -> Ürün İş Listesi | J60: 2
A61: Bug | B61: DP-267 | C61: Done | D61: E-Defter Firma Raporu Excelinin Güncellenmesi | E61: Destek Portal | F61: =VLOOKUP(B61,'Türkkep Jira'!B:F,5,0) -> #N/A | G61: =IF(IFERROR(VLOOKUP(B61,'Devam Eden Sprint'!B:B,1,0),"-")=B61,"Devam Eden Sprint","-") -> - | H61: =IF(IFERROR(VLOOKUP(B61,'Gelecek Sprint'!B:B,1,0),"-")=B61,"Gelecek Sprint","-") -> - | I61: =IFERROR(IF(AND(G61="Devam Eden Sprint",H61="Gelecek Sprint"),"Devam Eden ve Gelecek Sprint",IF(G61="Devam Eden Sprint","Devam Eden Sprint",IF(H61="Gelecek Sprint","Gelecek Sprint","Ürün İş Listesi"))),"Ürün İş Listesi") -> Ürün İş Listesi | J61: 2
... A68: Story | B68: DS-10 | C68: Done | D68: Hata loglarının LogSign üzerinden bildirim olarak gönderilmesi | E68: Detsis | F68: =VLOOKUP(B68,'Türkkep Jira'!B:F,5,0) -> #N/A | G68: =IF(IFERROR(VLOOKUP(B68,'Devam Eden Sprint'!B:B,1,0),"-")=B68,"Devam Eden Sprint","-") -> - | H68: =IF(IFERROR(VLOOKUP(B68,'Gelecek Sprint'!B:B,1,0),"-")=B68,"Gelecek Sprint","-") -> - | I68: =IFERROR(IF(AND(G68="Devam Eden Sprint",H68="Gelecek Sprint"),"Devam Eden ve Gelecek Sprint",IF(G68="Devam Eden Sprint","Devam Eden Sprint",IF(H68="Gelecek Sprint","Gelecek Sprint","Ürün İş Listesi"))),"Ürün İş Listesi") -> Ürün İş Listesi | J68: 3
A69: Story | B69: EDF-748 | C69: Done | D69: e-Defter Kebir Dosyalarının Ocak 2025 Dönemi İtibarı ile GİB Sistemlerine Yüklenmemesi İçin Değişiklik | E69: E-Defter | F69: =VLOOKUP(B69,'Türkkep Jira'!B:F,5,0) -> #N/A | G69: =IF(IFERROR(VLOOKUP(B69,'Devam Eden Sprint'!B:B,1,0),"-")=B69,"Devam Eden Sprint","-") -> - | H69: =IF(IFERROR(VLOOKUP(B69,'Gelecek Sprint'!B:B,1,0),"-")=B69,"Gelecek Sprint","-") -> - | I69: =IFERROR(IF(AND(G69="Devam Eden Sprint",H69="Gelecek Sprint"),"Devam Eden ve Gelecek Sprint",IF(G69="Devam Eden Sprint","Devam Eden Sprint",IF(H69="Gelecek Sprint","Gelecek Sprint","Ürün İş Listesi"))),"Ürün İş Listesi") -> Ürün İş Listesi
A70: Story | B70: EDF-750 | C70: Done | D70: E-Defter Client Defter İmzalama İçin .jar Dosyasının Güncellenmesi | E70: E-Defter | F70: =VLOOKUP(B70,'Türkkep Jira'!B:F,5,0) -> #N/A | G70: =IF(IFERROR(VLOOKUP(B70,'Devam Eden Sprint'!B:B,1,0),"-")=B70,"Devam Eden Sprint","-") -> - | H70: =IF(IFERROR(VLOOKUP(B70,'Gelecek Sprint'!B:B,1,0),"-")=B70,"Gelecek Sprint","-") -> - | I70: =IFERROR(IF(AND(G70="Devam Eden Sprint",H70="Gelecek Sprint"),"Devam Eden ve Gelecek Sprint",IF(G70="Devam Eden Sprint","Devam Eden Sprint",IF(H70="Gelecek Sprint","Gelecek Sprint","Ürün İş Listesi"))),"Ürün İş Listesi") -> Ürün İş Listesi
A71: Story | B71: EDF-751 | C71: Done | D71: Büyük Parçalı Firma (LOFT) Portalde İşlem Yapabilmesi İçin Exe Yazılması | E71: E-Defter | F71: =VLOOKUP(B71,'Türkkep Jira'!B:F,5,0) -> #N/A | G71: =IF(IFERROR(VLOOKUP(B71,'Devam Eden Sprint'!B:B,1,0),"-")=B71,"Devam Eden Sprint","-") -> - | H71: =IF(IFERROR(VLOOKUP(B71,'Gelecek Sprint'!B:B,1,0),"-")=B71,"Gelecek Sprint","-") -> - | I71: =IFERROR(IF(AND(G71="Devam Eden Sprint",H71="Gelecek Sprint"),"Devam Eden ve Gelecek Sprint",IF(G71="Devam Eden Sprint","Devam Eden Sprint",IF(H71="Gelecek Sprint","Gelecek Sprint","Ürün İş Listesi"))),"Ürün İş Listesi") -> Ürün İş Listesi | J71: 3
A72: Story | B72: EDF-752 | C72: Done | D72: CST_Contract Tablosunda Yer Almayan Müşterinin Portale Girişinin Engellediği Geliştirmenin Geri Alınması | E72: E-Defter | F72: =VLOOKUP(B72,'Türkkep Jira'!B:F,5,0) -> #N/A | G72: =IF(IFERROR(VLOOKUP(B72,'Devam Eden Sprint'!B:B,1,0),"-")=B72,"Devam Eden Sprint","-") -> - | H72: =IF(IFERROR(VLOOKUP(B72,'Gelecek Sprint'!B:B,1,0),"-")=B72,"Gelecek Sprint","-") -> - | I72: =IFERROR(IF(AND(G72="Devam Eden Sprint",H72="Gelecek Sprint"),"Devam Eden ve Gelecek Sprint",IF(G72="Devam Eden Sprint","Devam Eden Sprint",IF(H72="Gelecek Sprint","Gelecek Sprint","Ürün İş Listesi"))),"Ürün İş Listesi") -> Ürün İş Listesi | J72: 2
A73: Story | B73: EDF-755 | C73: Done | D73: Sözleşmesi Dolacak Müşteriler İçin Portalde Uyarı Metni Gösterimi | E73: E-Defter | F73: =VLOOKUP(B73,'Türkkep Jira'!B:F,5,0) -> #N/A | G73: =IF(IFERROR(VLOOKUP(B73,'Devam Eden Sprint'!B:B,1,0),"-")=B73,"Devam Eden Sprint","-") -> - | H73: =IF(IFERROR(VLOOKUP(B73,'Gelecek Sprint'!B:B,1,0),"-")=B73,"Gelecek Sprint","-") -> - | I73: =IFERROR(IF(AND(G73="Devam Eden Sprint",H73="Gelecek Sprint"),"Devam Eden ve Gelecek Sprint",IF(G73="Devam Eden Sprint","Devam Eden Sprint",IF(H73="Gelecek Sprint","Gelecek Sprint","Ürün İş Listesi"))),"Ürün İş Listesi") -> Ürün İş Listesi | J73: 13
A74: Story | B74: EFT-1669 | C74: Blocked | D74: Şifreli Tutulan Verilerin SHA-2 Algoritması İle Hashlenmesi | E74: E-Fatura | F74: =VLOOKUP(B74,'Türkkep Jira'!B:F,5,0) -> #N/A | G74: =IF(IFERROR(VLOOKUP(B74,'Devam Eden Sprint'!B:B,1,0),"-")=B74,"Devam Eden Sprint","-") -> - | H74: =IF(IFERROR(VLOOKUP(B74,'Gelecek Sprint'!B:B,1,0),"-")=B74,"Gelecek Sprint","-") -> - | I74: =IFERROR(IF(AND(G74="Devam Eden Sprint",H74="Gelecek Sprint"),"Devam Eden ve Gelecek Sprint",IF(G74="Devam Eden Sprint","Devam Eden Sprint",IF(H74="Gelecek Sprint","Gelecek Sprint","Ürün İş Listesi"))),"Ürün İş Listesi") -> Ürün İş Listesi
A75: Story | B75: EFT-1934 | C75: Done | D75: Sözleşme ve aktivasyon süreçlerinin istemci ile gerçekleştirilmesi | E75: E-Fatura | F75: =VLOOKUP(B75,'Türkkep Jira'!B:F,5,0) -> #N/A | G75: =IF(IFERROR(VLOOKUP(B75,'Devam Eden Sprint'!B:B,1,0),"-")=B75,"Devam Eden Sprint","-") -> - | H75: =IF(IFERROR(VLOOKUP(B75,'Gelecek Sprint'!B:B,1,0),"-")=B75,"Gelecek Sprint","-") -> - | I75: =IFERROR(IF(AND(G75="Devam Eden Sprint",H75="Gelecek Sprint"),"Devam Eden ve Gelecek Sprint",IF(G75="Devam Eden Sprint","Devam Eden Sprint",IF(H75="Gelecek Sprint","Gelecek Sprint","Ürün İş Listesi"))),"Ürün İş Listesi") -> Ürün İş Listesi | J75: 3
A76: Story | B76: EFT-2043 | C76: Done | D76: Kamu Faturaları Düzenlemeleri | E76: E-Fatura | F76: =VLOOKUP(B76,'Türkkep Jira'!B:F,5,0) -> #N/A | G76: =IF(IFERROR(VLOOKUP(B76,'Devam Eden Sprint'!B:B,1,0),"-")=B76,"Devam Eden Sprint","-") -> - | H76: =IF(IFERROR(VLOOKUP(B76,'Gelecek Sprint'!B:B,1,0),"-")=B76,"Gelecek Sprint","-") -> - | I76: =IFERROR(IF(AND(G76="Devam Eden Sprint",H76="Gelecek Sprint"),"Devam Eden ve Gelecek Sprint",IF(G76="Devam Eden Sprint","Devam Eden Sprint",IF(H76="Gelecek Sprint","Gelecek Sprint","Ürün İş Listesi"))),"Ürün İş Listesi") -> Ürün İş Listesi | J76: 2
A77: Story | B77: EFT-2068 | C77: Done | D77: Portalde Excel İle Fatura Yükleme | E77: E-Fatura | F77: =VLOOKUP(B77,'Türkkep Jira'!B:F,5,0) -> #N/A | G77: =IF(IFERROR(VLOOKUP(B77,'Devam Eden Sprint'!B:B,1,0),"-")=B77,"Devam Eden Sprint","-") -> - | H77: =IF(IFERROR(VLOOKUP(B77,'Gelecek Sprint'!B:B,1,0),"-")=B77,"Gelecek Sprint","-") -> - | I77: =IFERROR(IF(AND(G77="Devam Eden Sprint",H77="Gelecek Sprint"),"Devam Eden ve Gelecek Sprint",IF(G77="Devam Eden Sprint","Devam Eden Sprint",IF(H77="Gelecek Sprint","Gelecek Sprint","Ürün İş Listesi"))),"Ürün İş Listesi") -> Ürün İş Listesi
A78: Story | B78: EFT-2085 | C78: Done | D78: İlaç ve Tıbbi Cihaz Fatura Tipinde Fatura Oluşturulup Gönderilmesi | E78: E-Fatura | F78: =VLOOKUP(B78,'Türkkep Jira'!B:F,5,0) -> #N/A | G78: =IF(IFERROR(VLOOKUP(B78,'Devam Eden Sprint'!B:B,1,0),"-")=B78,"Devam Eden Sprint","-") -> - | H78: =IF(IFERROR(VLOOKUP(B78,'Gelecek Sprint'!B:B,1,0),"-")=B78,"Gelecek Sprint","-") -> - | I78: =IFERROR(IF(AND(G78="Devam Eden Sprint",H78="Gelecek Sprint"),"Devam Eden ve Gelecek Sprint",IF(G78="Devam Eden Sprint","Devam Eden Sprint",IF(H78="Gelecek Sprint","Gelecek Sprint","Ürün İş Listesi"))),"Ürün İş Listesi") -> Ürün İş Listesi | J78: 13
A79: Story | B79: EFT-2087 | C79: Done | D79: DeliveryCustomerParty Alanında TCKN Giriliyorsa Ad Soyad Girme Zorunluluğu Ekleme | E79: E-Fatura | F79: =VLOOKUP(B79,'Türkkep Jira'!B:F,5,0) -> #N/A | G79: =IF(IFERROR(VLOOKUP(B79,'Devam Eden Sprint'!B:B,1,0),"-")=B79,"Devam Eden Sprint","-") -> - | H79: =IF(IFERROR(VLOOKUP(B79,'Gelecek Sprint'!B:B,1,0),"-")=B79,"Gelecek Sprint","-") -> - | I79: =IFERROR(IF(AND(G79="Devam Eden Sprint",H79="Gelecek Sprint"),"Devam Eden ve Gelecek Sprint",IF(G79="Devam Eden Sprint","Devam Eden Sprint",IF(H79="Gelecek Sprint","Gelecek Sprint","Ürün İş Listesi"))),"Ürün İş Listesi") -> Ürün İş Listesi | J79: 3
A80: Story | B80: EFT-2094 | C80: Done | D80: Portal İlaç ve Tıbbi Cihaz Fatura Tipinde Fatura Oluşturulup Gönderilmesi | E80: E-Fatura | F80: =VLOOKUP(B80,'Türkkep Jira'!B:F,5,0) -> #N/A | G80: =IF(IFERROR(VLOOKUP(B80,'Devam Eden Sprint'!B:B,1,0),"-")=B80,"Devam Eden Sprint","-") -> - | H80: =IF(IFERROR(VLOOKUP(B80,'Gelecek Sprint'!B:B,1,0),"-")=B80,"Gelecek Sprint","-") -> - | I80: =IFERROR(IF(AND(G80="Devam Eden Sprint",H80="Gelecek Sprint"),"Devam Eden ve Gelecek Sprint",IF(G80="Devam Eden Sprint","Devam Eden Sprint",IF(H80="Gelecek Sprint","Gelecek Sprint","Ürün İş Listesi"))),"Ürün İş Listesi") -> Ürün İş Listesi | J80: 5
A81: Bug | B81: EFT-2095 | C81: Done | D81: Ef-Admin Portalde Şifremi Unuttum Alanının Çalışmaması | E81: E-Fatura | F81: =VLOOKUP(B81,'Türkkep Jira'!B:F,5,0) -> #N/A | G81: =IF(IFERROR(VLOOKUP(B81,'Devam Eden Sprint'!B:B,1,0),"-")=B81,"Devam Eden Sprint","-") -> - | H81: =IF(IFERROR(VLOOKUP(B81,'Gelecek Sprint'!B:B,1,0),"-")=B81,"Gelecek Sprint","-") -> - | I81: =IFERROR(IF(AND(G81="Devam Eden Sprint",H81="Gelecek Sprint"),"Devam Eden ve Gelecek Sprint",IF(G81="Devam Eden Sprint","Devam Eden Sprint",IF(H81="Gelecek Sprint","Gelecek Sprint","Ürün İş Listesi"))),"Ürün İş Listesi") -> Ürün İş Listesi | J81: 3
A82: Story | B82: EFT-2100 | C82: Done | D82: IHRACKAYITLI fatura tipi için GTİP ve Satır Kodu Zorunluluğu | E82: E-Fatura | F82: =VLOOKUP(B82,'Türkkep Jira'!B:F,5,0) -> #N/A | G82: =IF(IFERROR(VLOOKUP(B82,'Devam Eden Sprint'!B:B,1,0),"-")=B82,"Devam Eden Sprint","-") -> - | H82: =IF(IFERROR(VLOOKUP(B82,'Gelecek Sprint'!B:B,1,0),"-")=B82,"Gelecek Sprint","-") -> - | I82: =IFERROR(IF(AND(G82="Devam Eden Sprint",H82="Gelecek Sprint"),"Devam Eden ve Gelecek Sprint",IF(G82="Devam Eden Sprint","Devam Eden Sprint",IF(H82="Gelecek Sprint","Gelecek Sprint","Ürün İş Listesi"))),"Ürün İş Listesi") -> Ürün İş Listesi | J82: 5
A83: Story | B83: EFT-2101 | C83: Done | D83: İade ve Tevkifatiade Fatura Tiplerinde İadeye Konu Olan Fatura Numarası ve Tarihi Boş Olmaması | E83: E-Fatura | F83: =VLOOKUP(B83,'Türkkep Jira'!B:F,5,0) -> #N/A | G83: =IF(IFERROR(VLOOKUP(B83,'Devam Eden Sprint'!B:B,1,0),"-")=B83,"Devam Eden Sprint","-") -> - | H83: =IF(IFERROR(VLOOKUP(B83,'Gelecek Sprint'!B:B,1,0),"-")=B83,"Gelecek Sprint","-") -> - | I83: =IFERROR(IF(AND(G83="Devam Eden Sprint",H83="Gelecek Sprint"),"Devam Eden ve Gelecek Sprint",IF(G83="Devam Eden Sprint","Devam Eden Sprint",IF(H83="Gelecek Sprint","Gelecek Sprint","Ürün İş Listesi"))),"Ürün İş Listesi") -> Ürün İş Listesi | J83: 5
A84: Story | B84: EFT-2102 | C84: Done | D84: TaxExemptionReasonCodeType Güncellenmesi | E84: E-Fatura | F84: =VLOOKUP(B84,'Türkkep Jira'!B:F,5,0) -> #N/A | G84: =IF(IFERROR(VLOOKUP(B84,'Devam Eden Sprint'!B:B,1,0),"-")=B84,"Devam Eden Sprint","-") -> - | H84: =IF(IFERROR(VLOOKUP(B84,'Gelecek Sprint'!B:B,1,0),"-")=B84,"Gelecek Sprint","-") -> - | I84: =IFERROR(IF(AND(G84="Devam Eden Sprint",H84="Gelecek Sprint"),"Devam Eden ve Gelecek Sprint",IF(G84="Devam Eden Sprint","Devam Eden Sprint",IF(H84="Gelecek Sprint","Gelecek Sprint","Ürün İş Listesi"))),"Ürün İş Listesi") -> Ürün İş Listesi | J84: 1
A85: Story | B85: EFT-2108 | C85: Done | D85: ERP Binding Müşterilerine GİB Zorunlulukları İçin Geliştirme | E85: E-Fatura | F85: =VLOOKUP(B85,'Türkkep Jira'!B:F,5,0) -> #N/A | G85: =IF(IFERROR(VLOOKUP(B85,'Devam Eden Sprint'!B:B,1,0),"-")=B85,"Devam Eden Sprint","-") -> - | H85: =IF(IFERROR(VLOOKUP(B85,'Gelecek Sprint'!B:B,1,0),"-")=B85,"Gelecek Sprint","-") -> - | I85: =IFERROR(IF(AND(G85="Devam Eden Sprint",H85="Gelecek Sprint"),"Devam Eden ve Gelecek Sprint",IF(G85="Devam Eden Sprint","Devam Eden Sprint",IF(H85="Gelecek Sprint","Gelecek Sprint","Ürün İş Listesi"))),"Ürün İş Listesi") -> Ürün İş Listesi | J85: 3
A86: Story | B86: EFT-2109 | C86: Done | D86: MLP İade Faturası Geliştirmesi | E86: E-Fatura | F86: =VLOOKUP(B86,'Türkkep Jira'!B:F,5,0) -> #N/A | G86: =IF(IFERROR(VLOOKUP(B86,'Devam Eden Sprint'!B:B,1,0),"-")=B86,"Devam Eden Sprint","-") -> - | H86: =IF(IFERROR(VLOOKUP(B86,'Gelecek Sprint'!B:B,1,0),"-")=B86,"Gelecek Sprint","-") -> - | I86: =IFERROR(IF(AND(G86="Devam Eden Sprint",H86="Gelecek Sprint"),"Devam Eden ve Gelecek Sprint",IF(G86="Devam Eden Sprint","Devam Eden Sprint",IF(H86="Gelecek Sprint","Gelecek Sprint","Ürün İş Listesi"))),"Ürün İş Listesi") -> Ürün İş Listesi | J86: 2
A87: Story | B87: EFT-2114 | C87: Done | D87: HSM Lisans Süresini Uzatılması | E87: E-Fatura | F87: =VLOOKUP(B87,'Türkkep Jira'!B:F,5,0) -> #N/A | G87: =IF(IFERROR(VLOOKUP(B87,'Devam Eden Sprint'!B:B,1,0),"-")=B87,"Devam Eden Sprint","-") -> - | H87: =IF(IFERROR(VLOOKUP(B87,'Gelecek Sprint'!B:B,1,0),"-")=B87,"Gelecek Sprint","-") -> - | I87: =IFERROR(IF(AND(G87="Devam Eden Sprint",H87="Gelecek Sprint"),"Devam Eden ve Gelecek Sprint",IF(G87="Devam Eden Sprint","Devam Eden Sprint",IF(H87="Gelecek Sprint","Gelecek Sprint","Ürün İş Listesi"))),"Ürün İş Listesi") -> Ürün İş Listesi | J87: 1
A88: Story | B88: EFT-2116 | C88: Done | D88: Yapılan Türmob sorgularının veri tablosuna kaydedilmesi | E88: E-Fatura | F88: =VLOOKUP(B88,'Türkkep Jira'!B:F,5,0) -> #N/A | G88: =IF(IFERROR(VLOOKUP(B88,'Devam Eden Sprint'!B:B,1,0),"-")=B88,"Devam Eden Sprint","-") -> - | H88: =IF(IFERROR(VLOOKUP(B88,'Gelecek Sprint'!B:B,1,0),"-")=B88,"Gelecek Sprint","-") -> - | I88: =IFERROR(IF(AND(G88="Devam Eden Sprint",H88="Gelecek Sprint"),"Devam Eden ve Gelecek Sprint",IF(G88="Devam Eden Sprint","Devam Eden Sprint",IF(H88="Gelecek Sprint","Gelecek Sprint","Ürün İş Listesi"))),"Ürün İş Listesi") -> Ürün İş Listesi | J88: 3
A89: Story | B89: EFT-2117 | C89: Done | D89: Konnektör VKN/TCKN Alanı Minimum 10 Hane ve Ücretlendirme Uyarısı | E89: E-Fatura | F89: =VLOOKUP(B89,'Türkkep Jira'!B:F,5,0) -> #N/A | G89: =IF(IFERROR(VLOOKUP(B89,'Devam Eden Sprint'!B:B,1,0),"-")=B89,"Devam Eden Sprint","-") -> - | H89: =IF(IFERROR(VLOOKUP(B89,'Gelecek Sprint'!B:B,1,0),"-")=B89,"Gelecek Sprint","-") -> - | I89: =IFERROR(IF(AND(G89="Devam Eden Sprint",H89="Gelecek Sprint"),"Devam Eden ve Gelecek Sprint",IF(G89="Devam Eden Sprint","Devam Eden Sprint",IF(H89="Gelecek Sprint","Gelecek Sprint","Ürün İş Listesi"))),"Ürün İş Listesi") -> Ürün İş Listesi | J89: 1
... A103: Story | B103: EFT-2143 | C103: Done | D103: Modellerin, servislerin ve SPlerin oluşması | E103: E-Fatura | F103: =VLOOKUP(B103,'Türkkep Jira'!B:F,5,0) -> #N/A | G103: =IF(IFERROR(VLOOKUP(B103,'Devam Eden Sprint'!B:B,1,0),"-")=B103,"Devam Eden Sprint","-") -> - | H103: =IF(IFERROR(VLOOKUP(B103,'Gelecek Sprint'!B:B,1,0),"-")=B103,"Gelecek Sprint","-") -> - | I103: =IFERROR(IF(AND(G103="Devam Eden Sprint",H103="Gelecek Sprint"),"Devam Eden ve Gelecek Sprint",IF(G103="Devam Eden Sprint","Devam Eden Sprint",IF(H103="Gelecek Sprint","Gelecek Sprint","Ürün İş Listesi"))),"Ürün İş Listesi") -> Ürün İş Listesi | J103: 3
A104: Story | B104: IEU-114 | C104: Done | D104: Pdf hash imza - client | E104: Entegrasyon Suit | F104: =VLOOKUP(B104,'Türkkep Jira'!B:F,5,0) -> #N/A | G104: =IF(IFERROR(VLOOKUP(B104,'Devam Eden Sprint'!B:B,1,0),"-")=B104,"Devam Eden Sprint","-") -> - | H104: =IF(IFERROR(VLOOKUP(B104,'Gelecek Sprint'!B:B,1,0),"-")=B104,"Gelecek Sprint","-") -> - | I104: =IFERROR(IF(AND(G104="Devam Eden Sprint",H104="Gelecek Sprint"),"Devam Eden ve Gelecek Sprint",IF(G104="Devam Eden Sprint","Devam Eden Sprint",IF(H104="Gelecek Sprint","Gelecek Sprint","Ürün İş Listesi"))),"Ürün İş Listesi") -> Ürün İş Listesi
A105: Story | B105: IEU-115 | C105: Done | D105: PDF Dosyasının Hash Değerini Alma | E105: Entegrasyon Suit | F105: =VLOOKUP(B105,'Türkkep Jira'!B:F,5,0) -> #N/A | G105: =IF(IFERROR(VLOOKUP(B105,'Devam Eden Sprint'!B:B,1,0),"-")=B105,"Devam Eden Sprint","-") -> - | H105: =IF(IFERROR(VLOOKUP(B105,'Gelecek Sprint'!B:B,1,0),"-")=B105,"Gelecek Sprint","-") -> - | I105: =IFERROR(IF(AND(G105="Devam Eden Sprint",H105="Gelecek Sprint"),"Devam Eden ve Gelecek Sprint",IF(G105="Devam Eden Sprint","Devam Eden Sprint",IF(H105="Gelecek Sprint","Gelecek Sprint","Ürün İş Listesi"))),"Ürün İş Listesi") -> Ürün İş Listesi | J105: 5
A106: Story | B106: IEU-122 | C106: Done | D106: Veritabanının farklı sunucuya taşınması (Hubtest) | E106: Entegrasyon Suit | F106: =VLOOKUP(B106,'Türkkep Jira'!B:F,5,0) -> #N/A | G106: =IF(IFERROR(VLOOKUP(B106,'Devam Eden Sprint'!B:B,1,0),"-")=B106,"Devam Eden Sprint","-") -> - | H106: =IF(IFERROR(VLOOKUP(B106,'Gelecek Sprint'!B:B,1,0),"-")=B106,"Gelecek Sprint","-") -> - | I106: =IFERROR(IF(AND(G106="Devam Eden Sprint",H106="Gelecek Sprint"),"Devam Eden ve Gelecek Sprint",IF(G106="Devam Eden Sprint","Devam Eden Sprint",IF(H106="Gelecek Sprint","Gelecek Sprint","Ürün İş Listesi"))),"Ürün İş Listesi") -> Ürün İş Listesi | J106: 3
A107: Bug | B107: IEU-127 | C107: To Do | D107: XAdES çoklu imza doğrulama hatası | E107: Entegrasyon Suit | F107: =VLOOKUP(B107,'Türkkep Jira'!B:F,5,0) -> #N/A | G107: =IF(IFERROR(VLOOKUP(B107,'Devam Eden Sprint'!B:B,1,0),"-")=B107,"Devam Eden Sprint","-") -> - | H107: =IF(IFERROR(VLOOKUP(B107,'Gelecek Sprint'!B:B,1,0),"-")=B107,"Gelecek Sprint","-") -> - | I107: =IFERROR(IF(AND(G107="Devam Eden Sprint",H107="Gelecek Sprint"),"Devam Eden ve Gelecek Sprint",IF(G107="Devam Eden Sprint","Devam Eden Sprint",IF(H107="Gelecek Sprint","Gelecek Sprint","Ürün İş Listesi"))),"Ürün İş Listesi") -> Ürün İş Listesi
A108: Bug | B108: IEU-128 | C108: Done | D108: XAdES çoklu imzalama hatası hakkında | E108: Entegrasyon Suit | F108: =VLOOKUP(B108,'Türkkep Jira'!B:F,5,0) -> #N/A | G108: =IF(IFERROR(VLOOKUP(B108,'Devam Eden Sprint'!B:B,1,0),"-")=B108,"Devam Eden Sprint","-") -> - | H108: =IF(IFERROR(VLOOKUP(B108,'Gelecek Sprint'!B:B,1,0),"-")=B108,"Gelecek Sprint","-") -> - | I108: =IFERROR(IF(AND(G108="Devam Eden Sprint",H108="Gelecek Sprint"),"Devam Eden ve Gelecek Sprint",IF(G108="Devam Eden Sprint","Devam Eden Sprint",IF(H108="Gelecek Sprint","Gelecek Sprint","Ürün İş Listesi"))),"Ürün İş Listesi") -> Ürün İş Listesi
A109: Story | B109: IEU-13 | C109: Done | D109: Mobil İmza modülüne XAdES imzalama özelliği eklenmesi | E109: Entegrasyon Suit | F109: =VLOOKUP(B109,'Türkkep Jira'!B:F,5,0) -> #N/A | G109: =IF(IFERROR(VLOOKUP(B109,'Devam Eden Sprint'!B:B,1,0),"-")=B109,"Devam Eden Sprint","-") -> - | H109: =IF(IFERROR(VLOOKUP(B109,'Gelecek Sprint'!B:B,1,0),"-")=B109,"Gelecek Sprint","-") -> - | I109: =IFERROR(IF(AND(G109="Devam Eden Sprint",H109="Gelecek Sprint"),"Devam Eden ve Gelecek Sprint",IF(G109="Devam Eden Sprint","Devam Eden Sprint",IF(H109="Gelecek Sprint","Gelecek Sprint","Ürün İş Listesi"))),"Ürün İş Listesi") -> Ürün İş Listesi | J109: 5
A110: Story | B110: IEU-149 | C110: Done | D110: UETS servisinin Hubtest'e alınması | E110: Entegrasyon Suit | F110: =VLOOKUP(B110,'Türkkep Jira'!B:F,5,0) -> #N/A | G110: =IF(IFERROR(VLOOKUP(B110,'Devam Eden Sprint'!B:B,1,0),"-")=B110,"Devam Eden Sprint","-") -> - | H110: =IF(IFERROR(VLOOKUP(B110,'Gelecek Sprint'!B:B,1,0),"-")=B110,"Gelecek Sprint","-") -> - | I110: =IFERROR(IF(AND(G110="Devam Eden Sprint",H110="Gelecek Sprint"),"Devam Eden ve Gelecek Sprint",IF(G110="Devam Eden Sprint","Devam Eden Sprint",IF(H110="Gelecek Sprint","Gelecek Sprint","Ürün İş Listesi"))),"Ürün İş Listesi") -> Ürün İş Listesi
A111: Story | B111: IEU-151 | C111: Done | D111: Webmail ile Mobil İmza Entegrasyonu | E111: Entegrasyon Suit | F111: =VLOOKUP(B111,'Türkkep Jira'!B:F,5,0) -> #N/A | G111: =IF(IFERROR(VLOOKUP(B111,'Devam Eden Sprint'!B:B,1,0),"-")=B111,"Devam Eden Sprint","-") -> - | H111: =IF(IFERROR(VLOOKUP(B111,'Gelecek Sprint'!B:B,1,0),"-")=B111,"Gelecek Sprint","-") -> - | I111: =IFERROR(IF(AND(G111="Devam Eden Sprint",H111="Gelecek Sprint"),"Devam Eden ve Gelecek Sprint",IF(G111="Devam Eden Sprint","Devam Eden Sprint",IF(H111="Gelecek Sprint","Gelecek Sprint","Ürün İş Listesi"))),"Ürün İş Listesi") -> Ürün İş Listesi
A112: Story | B112: IEU-153 | C112: Done | D112: /api/v1/crg/search/account-info Metodunun Yeniden Yapılandırılması | E112: Entegrasyon Suit | F112: =VLOOKUP(B112,'Türkkep Jira'!B:F,5,0) -> #N/A | G112: =IF(IFERROR(VLOOKUP(B112,'Devam Eden Sprint'!B:B,1,0),"-")=B112,"Devam Eden Sprint","-") -> - | H112: =IF(IFERROR(VLOOKUP(B112,'Gelecek Sprint'!B:B,1,0),"-")=B112,"Gelecek Sprint","-") -> - | I112: =IFERROR(IF(AND(G112="Devam Eden Sprint",H112="Gelecek Sprint"),"Devam Eden ve Gelecek Sprint",IF(G112="Devam Eden Sprint","Devam Eden Sprint",IF(H112="Gelecek Sprint","Gelecek Sprint","Ürün İş Listesi"))),"Ürün İş Listesi") -> Ürün İş Listesi
A113: Story | B113: IEU-154 | C113: Done | D113: Son Ui Getiren Metotların Hubtest'e Alınması | E113: Entegrasyon Suit | F113: =VLOOKUP(B113,'Türkkep Jira'!B:F,5,0) -> #N/A | G113: =IF(IFERROR(VLOOKUP(B113,'Devam Eden Sprint'!B:B,1,0),"-")=B113,"Devam Eden Sprint","-") -> - | H113: =IF(IFERROR(VLOOKUP(B113,'Gelecek Sprint'!B:B,1,0),"-")=B113,"Gelecek Sprint","-") -> - | I113: =IFERROR(IF(AND(G113="Devam Eden Sprint",H113="Gelecek Sprint"),"Devam Eden ve Gelecek Sprint",IF(G113="Devam Eden Sprint","Devam Eden Sprint",IF(H113="Gelecek Sprint","Gelecek Sprint","Ürün İş Listesi"))),"Ürün İş Listesi") -> Ürün İş Listesi | J113: 3
A114: Story | B114: IEU-155 | C114: To Do | D114: İmzalama servislerinde toplu imzalama imkanı | E114: Entegrasyon Suit | F114: =VLOOKUP(B114,'Türkkep Jira'!B:F,5,0) -> #N/A | G114: =IF(IFERROR(VLOOKUP(B114,'Devam Eden Sprint'!B:B,1,0),"-")=B114,"Devam Eden Sprint","-") -> - | H114: =IF(IFERROR(VLOOKUP(B114,'Gelecek Sprint'!B:B,1,0),"-")=B114,"Gelecek Sprint","-") -> - | I114: =IFERROR(IF(AND(G114="Devam Eden Sprint",H114="Gelecek Sprint"),"Devam Eden ve Gelecek Sprint",IF(G114="Devam Eden Sprint","Devam Eden Sprint",IF(H114="Gelecek Sprint","Gelecek Sprint","Ürün İş Listesi"))),"Ürün İş Listesi") -> Ürün İş Listesi
A115: Story | B115: IEU-158 | C115: Done | D115: KEP Rehber - Genel Adres Doğrulama Metodunun Eklenmesi | E115: Entegrasyon Suit | F115: =VLOOKUP(B115,'Türkkep Jira'!B:F,5,0) -> #N/A | G115: =IF(IFERROR(VLOOKUP(B115,'Devam Eden Sprint'!B:B,1,0),"-")=B115,"Devam Eden Sprint","-") -> - | H115: =IF(IFERROR(VLOOKUP(B115,'Gelecek Sprint'!B:B,1,0),"-")=B115,"Gelecek Sprint","-") -> - | I115: =IFERROR(IF(AND(G115="Devam Eden Sprint",H115="Gelecek Sprint"),"Devam Eden ve Gelecek Sprint",IF(G115="Devam Eden Sprint","Devam Eden Sprint",IF(H115="Gelecek Sprint","Gelecek Sprint","Ürün İş Listesi"))),"Ürün İş Listesi") -> Ürün İş Listesi | J115: 3
A116: Story | B116: IEU-159 | C116: Done | D116: Merkezi KEP Rehberi Metodunda Hatalı Dönüşün Açıklamasının Eklenmesi | E116: Entegrasyon Suit | F116: =VLOOKUP(B116,'Türkkep Jira'!B:F,5,0) -> #N/A | G116: =IF(IFERROR(VLOOKUP(B116,'Devam Eden Sprint'!B:B,1,0),"-")=B116,"Devam Eden Sprint","-") -> - | H116: =IF(IFERROR(VLOOKUP(B116,'Gelecek Sprint'!B:B,1,0),"-")=B116,"Gelecek Sprint","-") -> - | I116: =IFERROR(IF(AND(G116="Devam Eden Sprint",H116="Gelecek Sprint"),"Devam Eden ve Gelecek Sprint",IF(G116="Devam Eden Sprint","Devam Eden Sprint",IF(H116="Gelecek Sprint","Gelecek Sprint","Ürün İş Listesi"))),"Ürün İş Listesi") -> Ürün İş Listesi | J116: 3
A117: Story | B117: IEU-160 | C117: Done | D117: İmzaClient Güncellemesi | E117: Entegrasyon Suit | F117: =VLOOKUP(B117,'Türkkep Jira'!B:F,5,0) -> #N/A | G117: =IF(IFERROR(VLOOKUP(B117,'Devam Eden Sprint'!B:B,1,0),"-")=B117,"Devam Eden Sprint","-") -> - | H117: =IF(IFERROR(VLOOKUP(B117,'Gelecek Sprint'!B:B,1,0),"-")=B117,"Gelecek Sprint","-") -> - | I117: =IFERROR(IF(AND(G117="Devam Eden Sprint",H117="Gelecek Sprint"),"Devam Eden ve Gelecek Sprint",IF(G117="Devam Eden Sprint","Devam Eden Sprint",IF(H117="Gelecek Sprint","Gelecek Sprint","Ürün İş Listesi"))),"Ürün İş Listesi") -> Ürün İş Listesi | J117: 3
A118: Bug | B118: IEU-162 | C118: Done | D118: Mobil imza cades tipinde imzalanan belgenin imzalı datasını çağırma hk. | E118: Entegrasyon Suit | F118: =VLOOKUP(B118,'Türkkep Jira'!B:F,5,0) -> #N/A | G118: =IF(IFERROR(VLOOKUP(B118,'Devam Eden Sprint'!B:B,1,0),"-")=B118,"Devam Eden Sprint","-") -> - | H118: =IF(IFERROR(VLOOKUP(B118,'Gelecek Sprint'!B:B,1,0),"-")=B118,"Gelecek Sprint","-") -> - | I118: =IFERROR(IF(AND(G118="Devam Eden Sprint",H118="Gelecek Sprint"),"Devam Eden ve Gelecek Sprint",IF(G118="Devam Eden Sprint","Devam Eden Sprint",IF(H118="Gelecek Sprint","Gelecek Sprint","Ürün İş Listesi"))),"Ürün İş Listesi") -> Ürün İş Listesi | J118: 3
A119: Story | B119: IEU-164 | C119: Done | D119: TCKN ve VKN ile Kep Adresi Sorgulama | E119: Entegrasyon Suit | F119: =VLOOKUP(B119,'Türkkep Jira'!B:F,5,0) -> #N/A | G119: =IF(IFERROR(VLOOKUP(B119,'Devam Eden Sprint'!B:B,1,0),"-")=B119,"Devam Eden Sprint","-") -> - | H119: =IF(IFERROR(VLOOKUP(B119,'Gelecek Sprint'!B:B,1,0),"-")=B119,"Gelecek Sprint","-") -> - | I119: =IFERROR(IF(AND(G119="Devam Eden Sprint",H119="Gelecek Sprint"),"Devam Eden ve Gelecek Sprint",IF(G119="Devam Eden Sprint","Devam Eden Sprint",IF(H119="Gelecek Sprint","Gelecek Sprint","Ürün İş Listesi"))),"Ürün İş Listesi") -> Ürün İş Listesi
...

Sheet Devam Eden Sprint
A1: Issue Type | B1: Issue key | C1: Status | D1: Summary | E1: Project Name | F1: Canlıya Alma (E/H) | G1: Story Point
A2: Story | B2: EFT-2351 | C2: Development | D2: API v2.4 POC'un İncelemesi ve Olası Değişiklik Senaryolarının Değerlendirilmesi | E2: E-Fatura | G2: 13 | H2: =VLOOKUP(B2,'Ürün İş Listesi'!B:B,1,0) -> EFT-2351
A3: Story | B3: EFT-2389 | C3: Done | D3: Fatura Ürünü için 2FA Fonksiyonun Aktifleştirilmesi | E3: E-Fatura | G3: 8 | H3: =VLOOKUP(B3,'Ürün İş Listesi'!B:B,1,0) -> EFT-2389
A4: Story | B4: EFT-2395 | C4: Development | D4: IIS Sunucularında Gereksiz Dosya ve Dizinlerin Kontrolü ve Temizlenmesi | E4: E-Fatura | H4: =VLOOKUP(B4,'Ürün İş Listesi'!B:B,1,0) -> EFT-2395
A5: Story | B5: EFT-2390 | C5: Development | D5: INVOICEHISTORYID Kolon Kapasite İyileştirme Çalışması | E5: E-Fatura | G5: 5 | H5: =VLOOKUP(B5,'Ürün İş Listesi'!B:B,1,0) -> EFT-2390
A6: Bug | B6: EFT-2396 | C6: TO TEST | D6: Web Servis FaturaGönder / UBLFaturaGönder – KDV %0 Faturalar İçin İstisna Kodu Kontrolü | E6: E-Fatura | H6: =VLOOKUP(B6,'Ürün İş Listesi'!B:B,1,0) -> EFT-2396
A7: Story | B7: EDF-813 | C7: Publish | D7: e-Envanter Defteri - Şematron Kontrolü Alanı | E7: E-Defter | G7: 3 | H7: =VLOOKUP(B7,'Ürün İş Listesi'!B:B,1,0) -> EDF-813
A8: Bug | B8: EDF-814 | C8: To Do | D8: e-Defter Sözleşme Ekranında Link Güncellenmesi | E8: E-Defter | G8: 1 | H8: =VLOOKUP(B8,'Ürün İş Listesi'!B:B,1,0) -> EDF-814
A9: Story | B9: EDF-815 | C9: To Do | D9: e-Envanter Defteri - Client İmzalama İşlemleri | E9: E-Defter | G9: 5 | H9: =VLOOKUP(B9,'Ürün İş Listesi'!B:B,1,0) -> EDF-815
A10: Story | B10: EDF-822 | C10: Done | D10: Defter Ürünü için 2FA Fonksiyonun Güncellenmesi | E10: E-Defter | G10: 5 | H10: =VLOOKUP(B10,'Ürün İş Listesi'!B:B,1,0) -> EDF-822
A11: Story | B11: EDF-824 | C11: Development | D11: e-Defter Code Refactoring | E11: E-Defter | G11: 13 | H11: =VLOOKUP(B11,'Ürün İş Listesi'!B:B,1,0) -> EDF-824
A12: Story | B12: ES-306 | C12: In progress | D12: e-Saklama Code Refactoring | E12: E-Saklama | G12: 13 | H12: =VLOOKUP(B12,'Ürün İş Listesi'!B:B,1,0) -> ES-306
A13: Story | B13: ES-305 | C13: Done | D13: 2FA Fonksiyonun Güncellenmesi | E13: E-Saklama | G13: 5 | H13: =VLOOKUP(B13,'Ürün İş Listesi'!B:B,1,0) -> ES-305
A14: Story | B14: DP-292 | C14: TEST | D14: Günlük e-Belge Hata Loglarının Excel Raporu Olarak e-mail ile Gönderilmesi | E14: Destek Portal | G14: 2 | H14: =VLOOKUP(B14,'Ürün İş Listesi'!B:B,1,0) -> DP-292
A15: Story | B15: CRM-639 | D15: KEP İK Kullanıcı Yetkilendirme Modülü Entegrasyonu | E15: CRM | G15: 5 | H15: =VLOOKUP(B15,'Ürün İş Listesi'!B:B,1,0) -> CRM-639
A16: Story | B16: CRM-649 | D16: E-Fatura ve E-Arşiv Ürünleri Trafik Bilgileri Detay Görünüm | E16: CRM | G16: 3 | H16: =VLOOKUP(B16,'Ürün İş Listesi'!B:B,1,0) -> CRM-649
A17: Story | B17: CRM-682 | D17: E-Belge Entegrasyon Yönetimi Alanı Düzenleme | E17: CRM | G17: 2 | H17: =VLOOKUP(B17,'Ürün İş Listesi'!B:B,1,0) -> CRM-682
A18: Story | B18: CRM-737 | D18: Kurumsal Çözümler Zorunlu Eşitlemeler | E18: CRM | G18: 2 | H18: =VLOOKUP(B18,'Ürün İş Listesi'!B:B,1,0) -> CRM-737
A19: Story | B19: CRM-754 | D19: Kurumsal KEP Oluştur Butonunun JOB'a Bağlanması | E19: CRM | G19: 1 | H19: =VLOOKUP(B19,'Ürün İş Listesi'!B:B,1,0) -> CRM-754
A20: Story | B20: CRM-763 | D20: CRM Satış Raporuna Hatalı Yansıyan Kayıt Tiplerinin İncelenmesi | E20: CRM | G20: 5 | H20: =VLOOKUP(B20,'Ürün İş Listesi'!B:B,1,0) -> CRM-763
A21: Story | B21: CRM-766 | D21: E-Güven Servis | E21: CRM | G21: 3 | H21: =VLOOKUP(B21,'Ürün İş Listesi'!B:B,1,0) -> CRM-766
A22: Story | B22: CRM-738 | D22: KEP Opsiyonel Eşitlemeler | E22: CRM | G22: 3 | H22: =VLOOKUP(B22,'Ürün İş Listesi'!B:B,1,0) -> CRM-738
A23: Story | B23: CRM-764 | D23: KİDOS - Hesap Durum Bildirimi | E23: CRM | G23: 3 | H23: =VLOOKUP(B23,'Ürün İş Listesi'!B:B,1,0) -> CRM-764
A24: Story | B24: CRM-780 | D24: E-Güven Servis - İmza Yenileme Tarihi | E24: CRM | G24: 5 | H24: =VLOOKUP(B24,'Ürün İş Listesi'!B:B,1,0) -> CRM-780
A25: Story | B25: CRM-789 | D25: CRM&MultiKEP Ent. - Ek Geliştirme | E25: CRM | G25: 5 | H25: =VLOOKUP(B25,'Ürün İş Listesi'!B:B,1,0) -> CRM-789
A26: Story | B26: CRM-762 | D26: CRM Satış Raporu – Müşteri İlgi Seviyesi Tanımlama Kuralları | E26: CRM | G26: 2 | H26: =VLOOKUP(B26,'Ürün İş Listesi'!B:B,1,0) -> CRM-762
... A41: Story | B41: CRM-828 | D41: Halkbank Projesi - Prod Ortam Bağlantısı | E41: CRM | G41: 1 | H41: =VLOOKUP(B41,'Ürün İş Listesi'!B:B,1,0) -> CRM-828
A42: Story | B42: KEP-302 | D42: e-Güven İmzalama API Testi | E42: KEP | F42: Devam Ediyor | G42: 8 | H42: =VLOOKUP(B42,'Ürün İş Listesi'!B:B,1,0) -> KEP-302
A43: Story | B43: KEP-315 | D43: API v2.4 POC'un İncelemesi ve Olası Değişiklik Senaryolarının Değerlendirilmesi | E43: KEP | F43: Devam Ediyor | H43: =VLOOKUP(B43,'Ürün İş Listesi'!B:B,1,0) -> KEP-315
A44: Story | B44: KEP-318 | D44: Şifremi Unuttum Akışı – TCKN ve Cep Telefonu ile Adres Listeleme Servisi Geliştirilmesi | E44: KEP | F44: Tamamlandı | G44: 3 | H44: =VLOOKUP(B44,'Ürün İş Listesi'!B:B,1,0) -> KEP-318
A45: Story | B45: WIK-783 | D45: API v2.4 POC'un İncelemesi ve Olası Değişiklik Senaryolarının Değerlendirilmesi | E45: KEP İK BULUT | F45: Devam Ediyor | H45: =VLOOKUP(B45,'Ürün İş Listesi'!B:B,1,0) -> WIK-783
A46: Story | B46: WIK-793 | D46: Belge Üzerine Eklenen Doğrulama Kodu için Ölçeklendirme | E46: KEP İK BULUT | F46: Test | G46: 3 | H46: =VLOOKUP(B46,'Ürün İş Listesi'!B:B,1,0) -> WIK-793
A47: Story | B47: WIK-791 | D47: Duyuru Modülünde Çoklu Grup Seçimi ve Grup Dışı Çalışanları Ekleme Özelliği | E47: KEP İK BULUT | F47: Devam Ediyor | G47: 3 | H47: =VLOOKUP(B47,'Ürün İş Listesi'!B:B,1,0) -> WIK-791
A48: Story | B48: WIK-792 | D48: Duyurunun Birden Fazla Çalışana Bağlanabilmesi | E48: KEP İK Bulut | F48: Devan Ediyor | H48: =VLOOKUP(B48,'Ürün İş Listesi'!B:B,1,0) -> WIK-792
A49: Bug | B49: WIK-823 | D49: Yeni Dönem/Ay Açılışında Ayın Başında Mükerrer Dönem Oluşması | E49: KEP İK Bulut | F49: Devam ediyor | G49: 2 | H49: =VLOOKUP(B49,'Ürün İş Listesi'!B:B,1,0) -> WIK-823
A50: Bug | B50: WIK-824 | D50: E imza Logosunun PDF Dosyası İçerisinde Taşma Sorunu | E50: KEP İK Bulut | F50: Devam Ediyor | G50: 2 | H50: =VLOOKUP(B50,'Ürün İş Listesi'!B:B,1,0) -> WIK-824
A51: Bug | B51: WIK-825 | D51: KEP İK Dönem Servisi Metotunda Mükerer Çalışan Yüklenmesi | E51: KEP İK Bulut | F51: Test | G51: 3 | H51: =VLOOKUP(B51,'Ürün İş Listesi'!B:B,1,0) -> WIK-825
A52: Story | B52: WIK-826 | D52: Kep Delil Raporu/ Pasif Kullanıcıların Listelenmesi ve Rapor Oluşturulabilmesi | E52: KEP İK Bulut | F52: Tamamlandı | G52: 2 | H52: =VLOOKUP(B52,'Ürün İş Listesi'!B:B,1,0) -> #N/A
A53: Story | B53: WIK-827 | D53: Analiz-Çalışan Ekranı Liste Sayfasında Duyuru Detayının Pop-up Olarak Gösterilmesi | E53: KEP İK Bulut | F53: Tamamlandı | H53: =VLOOKUP(B53,'Ürün İş Listesi'!B:B,1,0) -> #N/A
A54: Story | B54: MUL-215 | D54: 2FA Fonksiyonun Geliştirilmesi | E54: MULTİKEP | F54: Devam Ediyor | G54: 3 | H54: =VLOOKUP(B54,'Ürün İş Listesi'!B:B,1,0) -> MUL-215
A55: Story | B55: TIM-456 | D55: API v2.4 POC'un İncelemesi ve Olası Değişiklik Senaryolarının Değerlendirilmesi | E55: TÜRKKEP İMZA | F55: Devam Ediyor | H55: =VLOOKUP(B55,'Ürün İş Listesi'!B:B,1,0) -> TIM-456
A56: Story | B56: UKDS-223 | D56: Özel Müşteri Seçiminde CRM rezerv metotuna id gönderilmemesi | E56: UKDS | F56: Tamamlandı | G56: 1 | H56: =VLOOKUP(B56,'Ürün İş Listesi'!B:B,1,0) -> UKDS-223
A57: Story | B57: UKDS-219 | D57: Sonradan sisteme dahil olan müşterilerin CRM’den UKDS’ye gelmesi için metot geliştirilmesi | E57: UKDS | F57: Test | G57: 3 | H57: =VLOOKUP(B57,'Ürün İş Listesi'!B:B,1,0) -> UKDS-219
A58: Story | B58: UKDS-221 | D58: Yeni başvuru ekleme adımına ‘’Özel Müşteri’’ parametresinin eklemesi. | E58: UKDS | F58: Tamamlandı | G58: 2 | H58: =VLOOKUP(B58,'Ürün İş Listesi'!B:B,1,0) -> UKDS-221
A59: Story | B59: UKDS-220 | D59: Ön ödemeli/Müşteri Ödemeli seçimleri için metot güncellenmesi | E59: UKDS | F59: Tamamlandı | G59: 1 | H59: =VLOOKUP(B59,'Ürün İş Listesi'!B:B,1,0) -> UKDS-220
A60: Story | B60: UKDS-222 | D60: Varsayılan olarak ‘’Ön Ödemeli’’ seçeneği tanımının gelmesi | E60: UKDS | F60: Tamamlandı | G60: 1 | H60: =VLOOKUP(B60,'Ürün İş Listesi'!B:B,1,0) -> UKDS-222
A61: Story | B61: IEU-264 | D61: Entegrasyon Suit - UKDS Web Servis Entegrasyonunun Teknik Dokümantasyonunun Hazırlanması | E61: Entegrasyon Suit | H61: =VLOOKUP(B61,'Ürün İş Listesi'!B:B,1,0) -> IEU-264
A62: Story | B62: IEU-324 | D62: Teknik Analiz- On-Prem Uygulama Otomatik Deploy Edilebilmesi | E62: Entegrasyon Suit | G62: 5 | H62: =VLOOKUP(B62,'Ürün İş Listesi'!B:B,1,0) -> IEU-324
A63: Story | B63: KA-1588 | D63: Prod ortamda Türkçe olmayan kelimelerin tespit edilmesi ve Türkçeleştirilmesi | E63: Kep Assist | H63: =VLOOKUP(B63,'Ürün İş Listesi'!B:B,1,0) -> KA-1588
A64: Story | B64: MU-188 | D64: Şifremi Unuttum/ KEP Adres Seçimine Göre Şifre Değişikliği | E64: Mobil Uygulama | G64: 5 | H64: =VLOOKUP(B64,'Ürün İş Listesi'!B:B,1,0) -> MU-188
A65: Story | B65: KA-1596 | D65: UETS ve KEP Alım Servislerinin Ayrıştırılması | E65: Kep Assist | G65: 5 | H65: =VLOOKUP(B65,'Ürün İş Listesi'!B:B,1,0) -> KA-1596
A66: Story | B66: KA-1597 | D66: Güncelleme Paketi hazırlanması | E66: Kep Assist | G66: 3 | H66: =VLOOKUP(B66,'Ürün İş Listesi'!B:B,1,0) -> KA-1597
A67: Bug | B67: IMC-1 | D67: İmza Client Jar Test Bulguları | E67: İmza Client JAR | G67: 2 | H67: =VLOOKUP(B67,'Ürün İş Listesi'!B:B,1,0) -> IMC-1
A68: Story | B68: MU-223 | D68: Başvuru ve Ödeme Adımının Parametrik Yönetimi | E68: Mobil Uygulama | G68: 8 | H68: =VLOOKUP(B68,'Ürün İş Listesi'!B:B,1,0) -> MU-223
A69: Story | B69: KA-1604 | D69: Araştırma- Giriş Süreçlerinde Güvenlik Artırımı için SMS, Captcha ve Parametrik Yönetim Araştırması | E69: Kep Assist | G69: 3 | H69: =VLOOKUP(B69,'Ürün İş Listesi'!B:B,1,0) -> KA-1604
A70: Story | B70: MYS-856 | D70: Araştırma- Giriş Süreçlerinde Güvenlik Artırımı için SMS, Captcha ve Parametrik Yönetim Araştırması | E70: Muhaberat Yönetim Sistemi | G70: 3 | H70: =VLOOKUP(B70,'Ürün İş Listesi'!B:B,1,0) -> MYS-856
A71: Bug | B71: KA-1605 | D71: İleti Raporu Sayısal Veri Uyuşmazlığı | E71: Kep Assist | G71: 2 | H71: =VLOOKUP(B71,'Ürün İş Listesi'!B:B,1,0) -> KA-1605
A72: Bug | B72: MU-224 | D72: Biometrik Giriş Sırasında İnternet Bağlantı Hatası | E72: Mobil Uygulama | G72: 3 | H72: =VLOOKUP(B72,'Ürün İş Listesi'!B:B,1,0) -> MU-224
A73: Story | B73: MU-225 | D73: Mobil Şifremi unuttum ekranları | E73: Mobil Uygulama | G73: 5 | H73: =VLOOKUP(B73,'Ürün İş Listesi'!B:B,1,0) -> MU-225
A74: Bug | B74: MU-226 | D74: Login / OTP Geri Sayım Sayacının Hatalı Çalışması | E74: Mobil Uygulama | G74: 3 | H74: =VLOOKUP(B74,'Ürün İş Listesi'!B:B,1,0) -> MU-226
A75: Bug | B75: IMC-2 | D75: İmza Clientdaki bulguların sebeplerinin netleştirilmesi- Araştırma | E75: İmza Client JAR | G75: 3 | H75: =VLOOKUP(B75,'Ürün İş Listesi'!B:B,1,0) -> IMC-2
... A77: Story | B77: KA-1608 | D77: IIS Sunucularında Gereksiz Dosya ve Dizinlerin Kontrolü ve Temizlenmesi | E77: Kep Assist | G77: 3 | H77: =VLOOKUP(B77,'Ürün İş Listesi'!B:B,1,0) -> KA-1608

Sheet Gelecek Sprint
A1: Issue Type | B1: Issue key | C1: Status | D1: Summary | E1: Project Name | F1: Canlıya Alma (E/H) | G1: Story Point
A2: Story | B2: DP-292 | C2: TO TEST | D2: Günlük e-Belge Hata Loglarının Excel Raporu Olarak e-mail ile Gönderilmesi | E2: Destek Portal | G2: 3 | H2: =VLOOKUP(B2,'Ürün İş Listesi'!B:B,1,0) -> DP-292
A3: Story | B3: EDF-801 | C3: Development | D3: e-Defter Alanına Envanter Defteri Alanı | E3: E-Defter | G3: 13 | H3: =VLOOKUP(B3,'Ürün İş Listesi'!B:B,1,0) -> EDF-801
A4: Story | B4: EDF-808 | C4: To Do | D4: Anasayfa - Envanter Defteri Widget Alanı | E4: E-Defter | G4: 3 | H4: =VLOOKUP(B4,'Ürün İş Listesi'!B:B,1,0) -> EDF-808
A5: Story | B5: EDF-812 | C5: To Do | D5: Anasayfa - Envanter Defteri Berat Widget Alanı | E5: E-Defter | G5: 2 | H5: =VLOOKUP(B5,'Ürün İş Listesi'!B:B,1,0) -> EDF-812
A6: Story | B6: EDF-813 | C6: Publish | D6: e-Envanter Defteri - Şematron Kontrolü Alanı | E6: E-Defter | G6: 3 | H6: =VLOOKUP(B6,'Ürün İş Listesi'!B:B,1,0) -> EDF-813
A7: Bug | B7: EDF-814 | C7: To Do | D7: e-Defter Sözleşme Ekranında Link Güncellenmesi | E7: E-Defter | G7: 1 | H7: =VLOOKUP(B7,'Ürün İş Listesi'!B:B,1,0) -> EDF-814
A8: Story | B8: EDF-824 | C8: Development | D8: e-Defter Code Refactoring | E8: E-Defter | G8: 13 | H8: =VLOOKUP(B8,'Ürün İş Listesi'!B:B,1,0) -> EDF-824
A9: Story | B9: EFT-2322 | C9: To Do | D9: GİB Sicil Servis Canlı Entegresi | E9: E-Fatura | G9: 13 | H9: =VLOOKUP(B9,'Ürün İş Listesi'!B:B,1,0) -> EFT-2322
A10: Story | B10: EFT-2325 | C10: To Do | D10: GİB Sicil Servis Test Entegresi | E10: E-Fatura | G10: 8 | H10: =VLOOKUP(B10,'Ürün İş Listesi'!B:B,1,0) -> EFT-2325
A11: Story | B11: EFT-2351 | C11: Development | D11: API v2.4 POC'un İncelemesi ve Olası Değişiklik Senaryolarının Değerlendirilmesi | E11: E-Fatura | G11: 13 | H11: =VLOOKUP(B11,'Ürün İş Listesi'!B:B,1,0) -> EFT-2351
A12: Story | B12: EFT-2390 | C12: Development | D12: INVOICEHISTORYID Kolon Kapasite İyileştirme Çalışması | E12: E-Fatura | G12: 5 | H12: =VLOOKUP(B12,'Ürün İş Listesi'!B:B,1,0) -> EFT-2390
A13: Story | B13: EFT-2395 | C13: Development | D13: IIS Sunucularında Gereksiz Dosya ve Dizinlerin Kontrolü ve Temizlenmesi | E13: E-Fatura | H13: =VLOOKUP(B13,'Ürün İş Listesi'!B:B,1,0) -> EFT-2395
A14: Bug | B14: EFT-2396 | C14: TO TEST | D14: Web Servis FaturaGönder / UBLFaturaGönder – KDV %0 Faturalar İçin İstisna Kodu Kontrolü | E14: E-Fatura | H14: =VLOOKUP(B14,'Ürün İş Listesi'!B:B,1,0) -> EFT-2396
A15: Story | B15: EFT-2397 | C15: To Do | D15: GİB - e-Fatura Paketi Güncelleme(V 1.42) | E15: E-Fatura | G15: 1 | H15: =VLOOKUP(B15,'Ürün İş Listesi'!B:B,1,0) -> EFT-2397
A16: Story | B16: EFT-2398 | C16: To Do | D16: Portal - Nace Kodu - 555 İstisna | E16: E-Fatura | H16: =VLOOKUP(B16,'Ürün İş Listesi'!B:B,1,0) -> EFT-2398
A17: Story | B17: EFT-2399 | C17: To Do | D17: WebServis - Nace Kodu - 555 İstisna | E17: E-Fatura | H17: =VLOOKUP(B17,'Ürün İş Listesi'!B:B,1,0) -> EFT-2399
A18: Story | B18: EFT-2400 | C18: Development | D18: Nace Kodu - Veritabanına Yeni Mükellef Detay Tablosu Eklenmesi | E18: E-Fatura | G18: 3 | H18: =VLOOKUP(B18,'Ürün İş Listesi'!B:B,1,0) -> EFT-2400
A19: Story | B19: EFT-2401 | C19: To Do | D19: Konnektör - Nace Kodu - 555 İstisna | E19: E-Fatura | H19: =VLOOKUP(B19,'Ürün İş Listesi'!B:B,1,0) -> EFT-2401
A20: Story | B20: CRM-639 | C20: TO TEST | D20: KEP İK Kullanıcı Yetkilendirme Modülü Entegrasyonu | E20: CRM | G20: 5 | H20: =VLOOKUP(B20,'Ürün İş Listesi'!B:B,1,0) -> CRM-639
A21: Story | B21: CRM-649 | C21: TO TEST | D21: E-Fatura ve E-Arşiv Ürünleri Trafik Bilgileri Detay Görünüm | E21: CRM | G21: 3 | H21: =VLOOKUP(B21,'Ürün İş Listesi'!B:B,1,0) -> CRM-649
A22: Story | B22: CRM-682 | C22: TO TEST | D22: E-Belge Entegrasyon Yönetimi Alanı Düzenleme | E22: CRM | G22: 2 | H22: =VLOOKUP(B22,'Ürün İş Listesi'!B:B,1,0) -> CRM-682
A23: Story | B23: CRM-754 | C23: TO TEST | D23: Kurumsal KEP Oluştur Butonunun JOB'a Bağlanması | E23: CRM | G23: 1 | H23: =VLOOKUP(B23,'Ürün İş Listesi'!B:B,1,0) -> CRM-754
A24: Story | B24: CRM-763 | C24: TO TEST | D24: CRM Satış Raporuna Hatalı Yansıyan Kayıt Tiplerinin İncelenmesi | E24: CRM | G24: 5 | H24: =VLOOKUP(B24,'Ürün İş Listesi'!B:B,1,0) -> CRM-763
A25: Story | B25: CRM-766 | C25: TO TEST | D25: E-Güven Servis | E25: CRM | G25: 3 | H25: =VLOOKUP(B25,'Ürün İş Listesi'!B:B,1,0) -> CRM-766
A26: Story | B26: CRM-737 | C26: TO TEST | D26: Kurumsal Çözümler Zorunlu Eşitlemeler | E26: CRM | G26: 2 | H26: =VLOOKUP(B26,'Ürün İş Listesi'!B:B,1,0) -> CRM-737
A27: Story | B27: CRM-738 | C27: TO TEST | D27: KEP Opsiyonel Eşitlemeler | E27: CRM | G27: 3 | H27: =VLOOKUP(B27,'Ürün İş Listesi'!B:B,1,0) -> CRM-738
A28: Story | B28: CRM-764 | C28: TO TEST | D28: KİDOS - Hesap Durum Bildirimi | E28: CRM | G28: 3 | H28: =VLOOKUP(B28,'Ürün İş Listesi'!B:B,1,0) -> CRM-764
A29: Story | B29: CRM-780 | C29: TO TEST | D29: E-Güven Servis - İmza Yenileme Tarihi | E29: CRM | G29: 5 | H29: =VLOOKUP(B29,'Ürün İş Listesi'!B:B,1,0) -> CRM-780
A30: Story | B30: CRM-789 | C30: TO TEST | D30: CRM&MultiKEP Ent. - Ek Geliştirme | E30: CRM | G30: 5 | H30: =VLOOKUP(B30,'Ürün İş Listesi'!B:B,1,0) -> CRM-789
A31: Story | B31: CRM-762 | C31: TO TEST | D31: CRM Satış Raporu – Müşteri İlgi Seviyesi Tanımlama Kuralları | E31: CRM | G31: 2 | H31: =VLOOKUP(B31,'Ürün İş Listesi'!B:B,1,0) -> CRM-762
... A43: Story | B43: CRM-827 | C43: To Do | D43: Halkbank Projesi - Statü Kodu Senaryo | E43: CRM | G43: 2 | H43: =VLOOKUP(B43,'Ürün İş Listesi'!B:B,1,0) -> CRM-827
A44: Bug | B44: WIK-832 | D44: Çalışan Ekle- Tek Başvuru Ekleme Adımı Karakter ve Parametre Kontrolü | E44: KEP İK BULUT | G44: 2 | H44: =VLOOKUP(B44,'Ürün İş Listesi'!B:B,1,0) -> WIK-832
A45: Bug | B45: WIK-834 | D45: KEP Delil Raporlarının Sıralanması | E45: KEP İK BULUT | G45: 1 | H45: =VLOOKUP(B45,'Ürün İş Listesi'!B:B,1,0) -> WIK-834
A46: Bug | B46: WIK-833 | D46: Sistem Ayarları Sayfasında ''Kaydet'' Aşamasının Uyarısı | E46: KEP İK BULUT | G46: 1 | H46: =VLOOKUP(B46,'Ürün İş Listesi'!B:B,1,0) -> WIK-833
A47: Bug | B47: UKDS-228 | D47: Kampanya Başvuru Sayfası Cep Telefonu Numarası Girişi | E47: UKDS | G47: 2 | H47: =VLOOKUP(B47,'Ürün İş Listesi'!B:B,1,0) -> UKDS-228
A48: Story | B48: UKDS-229 | D48: IKENTEGRATORBIREYSEL- Ön Başvuru Süreç Linkinde Firma Bilgilerinin Gösterimi | E48: UKDS | G48: 3 | H48: =VLOOKUP(B48,'Ürün İş Listesi'!B:B,1,0) -> UKDS-229
A49: Story | B49: IEU-264 | D49: Entegrasyon Suit - UKDS Web Servis Entegrasyonunun Teknik Dokümantasyonunun Hazırlanması | E49: Entegrasyon Suit | H49: =VLOOKUP(B49,'Ürün İş Listesi'!B:B,1,0) -> IEU-264
A50: Story | B50: KA-1588 | D50: Prod ortamda Türkçe olmayan kelimelerin tespit edilmesi ve Türkçeleştirilmesi | E50: Kep Assist | H50: =VLOOKUP(B50,'Ürün İş Listesi'!B:B,1,0) -> KA-1588
A51: Story | B51: IEU-342 | D51: Utify Servisi: Tebligat Dönüşleri Detaylı KEP Adresi Raporu ve Adetleri (Başarısız Olanlar) Eklenmesi | E51: Entegrasyon Suit | G51: 2 | H51: =VLOOKUP(B51,'Ürün İş Listesi'!B:B,1,0) -> IEU-342
A52: Story | B52: IEU-343 | D52: Versiyon Sisteminin İncelenmesi | E52: Entegrasyon Suit | G52: 5 | H52: =VLOOKUP(B52,'Ürün İş Listesi'!B:B,1,0) -> IEU-343
A53: Story | B53: KA-1608 | D53: IIS Sunucularında Gereksiz Dosya ve Dizinlerin Kontrolü ve Temizlenmesi | E53: Kep Assist | G53: 3 | H53: =VLOOKUP(B53,'Ürün İş Listesi'!B:B,1,0) -> KA-1608
A54: Story | B54: KA-1599 | D54: 2FA Fonksiyonun Güncellenmesi | E54: Kep Assist | G54: 5 | H54: =VLOOKUP(B54,'Ürün İş Listesi'!B:B,1,0) -> KA-1599
A55: Story | B55: MYS-853 | D55: 2FA Fonksiyonun Güncellenmesi | E55: Muhaberat Yönetim Sistemi | G55: 8 | H55: =VLOOKUP(B55,'Ürün İş Listesi'!B:B,1,0) -> MYS-853
A56: Story | B56: MU-230 | D56: Mobil Uygulama için Widget ve Unit Testlerin Yazılması (UI ve API Kapsamlı) | E56: Mobil Uygulama | G56: 13 | H56: =VLOOKUP(B56,'Ürün İş Listesi'!B:B,1,0) -> MU-230
A57: Story | B57: MU-89 | D57: MU-Merkezi KEP Rehberi Sorgulamasının Yapılması | E57: Mobil Uygulama | G57: 3 | H57: =VLOOKUP(B57,'Ürün İş Listesi'!B:B,1,0) -> MU-89
A58: Story | B58: MU-229 | D58: BE- Merkezi KEP Rehberi Sorgulamasının Yapılması | E58: Mobil Uygulama | G58: 3 | H58: =VLOOKUP(B58,'Ürün İş Listesi'!B:B,1,0) -> MU-229
A59: Story | B59: MU-228 | D59: MU- Giden Kutusunda “Teslim Edilemedi” ve “Reddedildi” Delil Türleri İçin Sebep Açıklaması Gösterimi | E59: Mobil Uygulama | G59: 5 | H59: =VLOOKUP(B59,'Ürün İş Listesi'!B:B,1,0) -> MU-228
A60: Story | B60: MU-100 | D60: BE- Giden Kutusunda “Teslim Edilemedi” ve “Reddedildi” Delil Türleri İçin Sebep Açıklaması Gösterimi | E60: Mobil Uygulama | G60: 5 | H60: =VLOOKUP(B60,'Ürün İş Listesi'!B:B,1,0) -> MU-100
A61: Story | B61: MU-227 | D61: Yüksek Boyutlu İleti Açılış Performans Analizi | E61: Mobil Uygulama | H61: =VLOOKUP(B61,'Ürün İş Listesi'!B:B,1,0) -> MU-227

Sheet Türkkep Jira
A1: Summary | B1: Issue key | C1: Issue id | D1: Parent id | E1: Issue Type | F1: Status | G1: Project key | H1: Project name | I1: Project type | J1: Project lead | K1: Project description | L1: Project url | M1: Priority | N1: Resolution | O1: Assignee | P1: Reporter | Q1: Creator | R1: Created | S1: Updated | T1: Last Viewed | U1: Resolved | V1: Fix Version/s | W1: Component/s | X1: Due Date | Y1: Votes | Z1: Labels | AA1: Description | AB1: Environment | AC1: Watchers | AD1: Watchers_1 | AE1: Watchers_2 | AF1: Watchers_3 | AG1: Watchers_4 | AH1: Log Work | AI1: Log Work_5 | AJ1: Log Work_6 | AK1: Log Work_7 | AL1: Log Work_8 | AM1: Log Work_9 | AN1: Log Work_10 | AO1: Log Work_11 | AP1: Log Work_12 | AQ1: Log Work_13 | AR1: Log Work_14 | AS1: Log Work_15 | AT1: Log Work_16 | AU1: Log Work_17 | AV1: Log Work_18 | AW1: Log Work_19 | AX1: Log Work_20 | AY1: Log Work_21 | AZ1: Log Work_22 | BA1: Log Work_23 | BB1: Log Work_24 | BC1: Log Work_25 | BD1: Log Work_26 | BE1: Log Work_27 | BF1: Log Work_28 | BG1: Log Work_29 | BH1: Log Work_30 | BI1: Log Work_31 | BJ1: Log Work_32 | BK1: Log Work_33 | BL1: Log Work_34 | BM1: Log Work_35 | BN1: Log Work_36 | BO1: Log Work_37 | BP1: Original Estimate | BQ1: Remaining Estimate | BR1: Time Spent | BS1: Work Ratio | BT1: Σ Original Estimate | BU1: Σ Remaining Estimate | BV1: Σ Time Spent | BW1: Security Level | BX1: Outward issue link (Cloners) | BY1: Outward issue link (Relates) | BZ1: Attachment | CA1: Attachment_38 | CB1: Attachment_39 | CC1: Attachment_40 | CD1: Attachment_41 | CE1: Attachment_42 | CF1: Attachment_43 | CG1: Attachment_44 | CH1: Attachment_45 | CI1: Attachment_46 | CJ1: Custom field (Analyst) | CK1: Custom field (Başlama Tarihi) | CL1: Custom field (Epic Color) | CM1: Custom field (Epic Link) | CN1: Custom field (Epic Name) | CO1: Custom field (Epic Status) | CP1: Custom field (Ortak - Kayda Atanan) | CQ1: Custom field (Ortak - Kaydı Açan) | CR1: Custom field (Pending Reason) | CS1: Custom field (Product Owner) | CT1: Custom field (Rank) | CU1: Sprint | CV1: Sprint_47 | CW1: Sprint_48 | CX1: Sprint_49 | CY1: Sprint_50 | CZ1: Sprint_51 | DA1: Sprint_52 | DB1: Sprint_53 | DC1: Sprint_54 | DD1: Sprint_55 | DE1: Sprint_56 | DF1: Sprint_57 | DG1: Sprint_58 | DH1: Sprint_59 | DI1: Custom field (Story Points) | DJ1: Custom field (Talep Sahibi - CRM) | DK1: Custom field (Tester) | DL1: Comment | DM1: Comment_60 | DN1: Comment_61 | DO1: Comment_62 | DP1: Comment_63 | DQ1: Comment_64 | DR1: Comment_65 | DS1: Comment_66 | DT1: Comment_67 | DU1: Comment_68 | DV1: Comment_69 | DW1: Comment_70 | DX1: Comment_71 | DY1: Comment_72 | DZ1: Comment_73 | EA1: Comment_74 | EB1: Comment_75 | EC1: Comment_76 | ED1: Comment_77 | EE1: Comment_78 | EF1: Comment_79 | EG1: Comment_80 | EH1: Comment_81
A2: n8n ile HTML/XML Parse (BeautifulSoup Benzeri) Yetkinlik Araştırması | B2: YZCK-46 | C2: 23133 | E2: Task | F2: Done | G2: YZCK | H2: Yapay Zeka Destekli Çağrı Karşılama | I2: software | J2: elvan.gurler | M2: Medium | N2: Done | O2: basak.ayverdi | P2: elvan.gurler | Q2: elvan.gurler | R2: 46090.47 | S2: 46097.688 | T2: 46100.369 | U2: 46097.688 | Y2: 0 | AA2: n8n platformunda web sayfalarından veri çekme ve HTML/XML parse işlemlerinin yapılabilirliği araştırılacaktır. Bu kapsamda Python kütüphanesi olan Beautiful Soup ile yapılan işlemlerin n8n üzerinde ** benzeri yöntemlerle gerçekleştirilip gerçekleştirilemeyeceği incelenecektir._x000D_ _x000D_ Araştırma kapsamında:_x000D_ * Web sayfasından veri çekme (HTTP Request)_x000D_ _x000D_ * HTML içinden veri parse etme (selector kullanımı)_x000D_ _x000D_ * Karmaşık HTML yapılarının işlenebilirliği_x000D_ _x000D_ * Gerekirse JavaScript veya harici servis kullanımı_x000D_ _x000D_ konuları değerlendirilerek teknik yapılabilirlik analizi yapılacaktır. | AC2: elvan.gurler | AH2: n8n platformunda web sayfalarından veri çekme ve HTML/XML parse işlemlerinin yapılabilirliği araştırıldı._x000D_ HTTP Request kullanarak sayfa içeriğinin alınması, CSS selector ile veri çıkarılması ve karmaşık HTML yapılarını işleme yöntemleri incelendi._x000D_ Dinamik web sayfaları için harici scraping servislerinin (Browserless, ScrapingBee vb.) kullanım senaryoları değerlendirildi._x000D_ Elde edilen bulgular doğrultusunda teknik değerlendirme raporu hazırlanarak dokümante edildi.;09/Mar/26 4:42 PM;basak.ayverdi;21600 | AI2: n8n kullanılarak rakip ürün takip sistemi kurulmasının teknik fizibilitesi araştırıldı ve sistem mimarisi ile önerilen workflow’u içeren teknik dokümantasyon hazırlandı.;10/Mar/26 5:08 PM;basak.ayverdi;21600 | BQ2: 0 | BR2: 43200 | BU2: 0 | BV2: 43200 | BZ2: 09/Mar/26 4:40 PM;basak.ayverdi;bsoup_n8n değerlendirme.docx;http://192.168.124.186:8080/secure/attachment/15990/bsoup_n8n+de%C4%9Ferlendirme.docx | CA2: 10/Mar/26 5:09 PM;basak.ayverdi;rakip_urun_takip_sistemi.docx;http://192.168.124.186:8080/secure/attachment/16018/rakip_urun_takip_sistemi.docx | CT2: 0|i01ef0:w | CU2: YZCK Sprint 4
A3: Değerlendirme ve Cevap Alınmayan Soruların İletildiği Workflow İncelenmesi | B3: YZCK-45 | C3: 23112 | E3: Bug | F3: Done | G3: YZCK | H3: Yapay Zeka Destekli Çağrı Karşılama | I3: software | J3: elvan.gurler | M3: Medium | N3: Done | O3: omer.saritoy | P3: elvan.gurler | Q3: elvan.gurler | R3: 46087.566 | S3: 46091.647 | T3: 46100.369 | U3: 46091.647 | Y3: 0 | AA3: Değerlendirme ve cevap alınmayan soruların iletildiği workflowda cevaplandığı halde sorular cevaplanmamış gibi dönüyor. Tekrar düzenleme yapılması gerekmektedir. | AC3: elvan.gurler | AH3: Bota gelen unanswered questions workflow’unda tespit edilen hata doğrultusunda gerekli güncelleme yapılmış ve testleri gerçekleştirilmiştir.;06/Mar/26 4:29 PM;basak.ayverdi;10800 | AI3: Unanswerdquestion wf da sorular cevaplanmasına rağmen cevaplanmadı şeklinde excel verilerine eklenmiş bu hata üzerinde çalışmalar yapıldı ve giderildi .Test aşamasına kadar getirildi ;06/Mar/26 4:33 PM;omer.saritoy;10800 | AJ3: İlgili Bug Tespit edilip sorun giderildi ;10/Mar/26 3:30 PM;omer.saritoy;10800 | BQ3: 0 | BR3: 32400 | BU3: 0 | BV3: 32400 | CT3: 0|i01ef6:5i | CU3: YZCK Sprint 4
A4: İK AI Asistanı – Araştırma ve Kapsam Belirleme | B4: YZCK-44 | C4: 23111 | E4: Story | F4: Done | G4: YZCK | H4: Yapay Zeka Destekli Çağrı Karşılama | I4: software | J4: elvan.gurler | M4: Medium | N4: Done | O4: basak.ayverdi | P4: elvan.gurler | Q4: elvan.gurler | R4: 46087.557 | S4: 46090.371 | T4: 46100.369 | U4: 46090.371 | Y4: 0 | AA4: Dün yapılan YK toplantısında İK süreçlerini destekleyecek bir AI asistan geliştirilmesi ihtiyacı gündeme gelmiştir. Bu kapsamda, İK için geliştirilebilecek AI asistanın fonksiyonları ve MVP kapsamında hangi modüllerin önceliklendirileceği konusunda ön araştırma yapılacaktır._x000D_ _x000D_ Araştırma kapsamında:_x000D_ * İK AI asistanı kullanım senaryolarının incelenmesi (Recruitment AI, Employee Experience, People Analytics)_x000D_ _x000D_ * Piyasadaki benzer çözümlerin (ATS, HR AI araçları vb.) analiz edilmesi_x000D_ _x000D_ * MVP için önerilen modüllerin belirlenmesi (İşe alım ön eleme ve çalışan SSS asistanı)_x000D_ _x000D_ * Kurum içi sistemlerle olası entegrasyonların değerlendirilmesi (ERP, Teams vb.) | AC4: basak.ayverdi | AD4: elvan.gurler | AH4: Agent araştırma taskı kapsamında geliştirilebilecek feature’ların değerlendirilmesi amacıyla toplantı öncesinde dokümantasyon hazırlanmış ve ilgili toplantıya katılım sağlanmıştır.;06/Mar/26 4:27 PM;basak.ayverdi;10800 | AI4: IK agent üzeirne araştırmalar yapıldı . Bir IK nelere ihtiyaç duyar ve ai ile nasıl işleri hafifler üzerine araştırmalar yapıldı ;06/Mar/26 4:34 PM;omer.saritoy;7200 | AJ4: türk pazarındaki ürünler incelendi;09/Mar/26 8:54 AM;basak.ayverdi;3600 | BQ4: 0 | BR4: 21600 | BU4: 0 | BV4: 21600 | BZ4: 06/Mar/26 4:28 PM;basak.ayverdi;HR AI Agent – Capability Overview.pdf;http://192.168.124.186:8080/secure/attachment/15979/HR+AI+Agent+%E2%80%93+Capability+Overview.pdf | CT4: 0|i01ef6:5 | CU4: YZCK Sprint 4 | DL4: 09/Mar/26 8:53 AM;basak.ayverdi;https://www.hiri.ai/https://www.hiri.ai/_x000D_ https://ikai.com.tr/_x000D_ https://www.layersup.com/tr_x000D_ https://www.cbot.ai/_x000D_
A5: CRM Bayi Chatbot Analiz Raporu Worflowu | B5: YZCK-43 | C5: 23077 | E5: Story | F5: In Progress | G5: YZCK | H5: Yapay Zeka Destekli Çağrı Karşılama | I5: software | J5: elvan.gurler | M5: Medium | O5: omer.saritoy | P5: elvan.gurler | Q5: elvan.gurler | R5: 46083.575 | S5: 46094.687 | T5: 46083.665 | Y5: 0 | AA5: CRM genel müdürlük için yapılan chatbotun cevaplanmayan soruların iletildiği excelin günlük olarak iletilmesi ve performans analizi workflowu haftalık iletilecek şekilde geliştirme yapılmalıdır | AC5: elvan.gurler | AH5: İlgili Workflow için database tablosu oluşturuldu ve AI AGENT toolsu eklenerek openai model bağlantıları sağlandı ;09/Mar/26 4:49 PM;omer.saritoy;7200 | AI5: Cevaplanmayan sorular iş akışı oluşturdu ;11/Mar/26 4:23 PM;omer.saritoy;7200 | AJ5: cevaplanmayan sorular iş akışı testi yapıldı;12/Mar/26 5:16 PM;omer.saritoy;7200 | AK5: Workflow toolarına javascript kodları eklendi ve databaseden gelen veriler cevaplanmayan soruları çekecek kodlama yapısı eklendi ;13/Mar/26 4:29 PM;omer.saritoy;7200 | BQ5: 0 | BR5: 28800 | BU5: 0 | BV5: 28800 | CT5: 0|i01ef6:6 | CU5: YZCK Sprint 4
A6: CRM Genel Müdürlük Chatbot Analiz Raporu Workflow | B6: YZCK-42 | C6: 23076 | E6: Story | F6: In Progress | G6: YZCK | H6: Yapay Zeka Destekli Çağrı Karşılama | I6: software | J6: elvan.gurler | M6: Medium | O6: basak.ayverdi | P6: elvan.gurler | Q6: elvan.gurler | R6: 46083.574 | S6: 46093.72 | T6: 46100.369 | Y6: 0 | AA6: CRM genel müdürlük için yapılan chatbotun cevaplanmayan soruların iletildiği excelin günlük olarak iletilmesi ve performans analizi workflowu haftalık iletilecek şekilde geliştirme yapılmalıdır. | AC6: elvan.gurler | AH6: Cevaplanmayan sorular iş akışı oluşturuldu ;11/Mar/26 4:22 PM;omer.saritoy;10800 | AI6: Cevaplanmayan sorular iş akışı test edildi ;12/Mar/26 5:17 PM;omer.saritoy;3600 | BQ6: 0 | BR6: 14400 | BU6: 0 | BV6: 14400 | CT6: 0|i01ef6:c | CU6: YZCK Sprint 4
A7: CRM Genel Müdürlük Chatbot Entegrasyonu / Workflow Tasarımı | B7: YZCK-41 | C7: 23051 | E7: Story | F7: In Progress | G7: YZCK | H7: Yapay Zeka Destekli Çağrı Karşılama | I7: software | J7: elvan.gurler | M7: Medium | O7: basak.ayverdi | P7: elvan.gurler | Q7: elvan.gurler | R7: 46079.585 | S7: 46094.719 | T7: 46100.369 | Y7: 0 | AA7: CRM içerisinde Genel Müdürlük kullanımı için chatbot entegrasyonu yapılacak. Bu kapsamda:Chatbot ile etkileşim sırasında gerekli aksiyonları tetikleyecek *workflow* tasarımı. | AC7: elvan.gurler | AH7: ilgili iş akışı için toplantıya katılım sağlandı, promptu ve düzeni için görüşüldü;02/Mar/26 5:07 PM;basak.ayverdi;7200 | AI7: workflow tasarımı oluşturuldu ve ilgili postgresql tablosu oluşturuldu.;05/Mar/26 5:32 PM;basak.ayverdi;10800 | AJ7: unanswered question workflowundaki javascript tool kodlaması yazıldı;13/Mar/26 5:16 PM;basak.ayverdi;7200 | BQ7: 0 | BR7: 25200 | BU7: 0 | BV7: 25200 | CT7: 0|i01ef6:4 | CU7: YZCK Sprint 4
A8: CRM Bayi Chatbot Entegrasyonu / Workflow Tasarımı | B8: YZCK-40 | C8: 23050 | E8: Story | F8: In Progress | G8: YZCK | H8: Yapay Zeka Destekli Çağrı Karşılama | I8: software | J8: elvan.gurler | M8: Medium | O8: omer.saritoy | P8: elvan.gurler | Q8: elvan.gurler | R8: 46079.584 | S8: 46099.828 | T8: 46100.369 | Y8: 0 | AA8: *Açıklama:*_x000D_ CRM içerisinde bayi kullanımı için chatbot entegrasyonu yapılacak. Bu kapsamda Chatbot ile etkileşim sırasında gerekli aksiyonları tetikleyecek *workflow* tasarımı. | AC8: elvan.gurler | AH8: n8n üzerinde workflow araştırma ve deneme çalışması yapılıyor;27/Feb/26 5:16 PM;omer.saritoy;3600 | AI8: ilgili iş akışı için toplantıya katılım sağlandı, promptu ,düzeni ,Database için görüşme yapıldı ;02/Mar/26 4:43 PM;omer.saritoy;7200 | AJ8: workflow tasarımı üzerinde çalışıldı gerekli postgresql tablosu oluşturuldu ve ilk deneme yapıldı ;05/Mar/26 5:30 PM;omer.saritoy;14400 | AK8: Database bağlandıktan sonra iş akışları oluşturuldu openai modelleri bağlandı ve qdrant bağlantısı yapıldı ;09/Mar/26 4:48 PM;omer.saritoy;10800 | AL8: n8n bayiworkflow ai agent ve moddeler bağlandıktan sonra hata kontrolu error response toolsları eklendi ve kısmen iş akışı tamamlandı .;10/Mar/26 4:26 PM;omer.saritoy;7200 | AM8: Bayi workflowu için prompt hazırlığı yapıldı ;12/Mar/26 5:18 PM;omer.saritoy;7200 | AN8: Qdranta verilerin yüklenemesi için gerekli python kodları oluşturuldu ve embedded modeli ve qdrant api keyleri eklendi ve hali hazırda düzenenlenen veriler eklendi ;13/Mar/26 4:31 PM;omer.saritoy;3600 | AO8: Bayi için gelen veriler düzenlenip veri tabanına yüklendi;16/Mar/26 4:48 PM;omer.saritoy;7200 | AP8: Bayi kullanıcılarına özel CRM destek chatbotu için system prompt tasarlandı. Prompt; yalnızca CRM kullanım senaryolarını kapsayacak şekilde daraltıldı, hallucination ve yetki bypass risklerini önleyen kurallar eklendi, database-first ve clarification akışı optimize edildi;17/Mar/26 4:30 PM;basak.ayverdi;14400 | AQ8: Bu chatbot için system pomptu tasarlanıp agent tooluna eklendi ;17/Mar/26 10:48 PM;omer.saritoy;10800 | AR8: CRM süreçlerine ait soru-cevap verileri vektörel veritabanı için ayrıştırılıp düzenlendi;18/Mar/26 5:22 PM;basak.ayverdi;21600 | AS8: güncel prompt için test yapılıyor;18/Mar/26 5:22 PM;basak.ayverdi;3600 | AT8: Soru-Cevap datalarını qdrant vektör db için ayrıştırılıp düzenlendi . Güncel prompt üzerinden denemeler yapılıyor. ;18/Mar/26 7:52 PM;omer.saritoy;21600 | BQ8: 0 | BR8: 133200 | BU8: 0 | BV8: 133200 | CT8: 0|i01ef0:r | CU8: YZCK Sprint 4
A9: Ek İşler Hk. | B9: YZCK-36 | C9: 23025 | E9: Side-Jobs | F9: To Do | G9: YZCK | H9: Yapay Zeka Destekli Çağrı Karşılama | I9: software | J9: elvan.gurler | M9: Medium | O9: berrin.akan | P9: elvan.gurler | Q9: elvan.gurler | R9: 46073.701 | S9: 46094.751 | T9: 46100.369 | Y9: 0 | AA9: Arka planda yapılan işlerin loglanması | AC9: elvan.gurler | AH9: Orbina ile toplantıya katılındı.;06/Mar/26 5:55 PM;berrin.akan;3600 | AI9: Chatbot crm toplantısına katılındı._x000D_ _x000D_ ;06/Mar/26 6:22 PM;berrin.akan;1800 | AJ9: Chatbot değerlendirme toplantısına katılındı.;13/Mar/26 6:01 PM;berrin.akan;1800 | BQ9: 0 | BR9: 7200 | BU9: 0 | BV9: 7200 | CT9: 0|i01ef6:w | CU9: YZCK Sprint 4
A10: Ek İşler Hk. | B10: YZCK-35 | C10: 23024 | E10: Side-Jobs | F10: To Do | G10: YZCK | H10: Yapay Zeka Destekli Çağrı Karşılama | I10: software | J10: elvan.gurler | M10: Medium | O10: basak.ayverdi | P10: elvan.gurler | Q10: elvan.gurler | R10: 46073.7 | S10: 46098.688 | T10: 46100.369 | Y10: 0 | AA10: Arka planda yapılan işlerin loglanması | AC10: elvan.gurler | AH10: Faz-2 test sonuçları üzerinde detaylı analiz ve kapsamlı inceleme çalışmaları gerçekleştirilmiştir. Bulgular doğrultusunda aktarılması gereken veriler veri tabanına (qdrant DB) işlenmiştir. Ar-Ge teknik danışmanından alınan geri bildirimler çerçevesinde Ar-Ge proje kartı revize edilerek doküman nihai versiyonuna ulaştırılmıştır.;20/Feb/26 4:56 PM;basak.ayverdi;25200 | AI10: Mac Mini üzerinde development ortamı hazırlanarak OpenCrawl kurulumu ve temel konfigürasyonları tamamlandı, OpenAI API key tanımlanarak servis entegrasyonu ve ilk test çağrıları başarıyla gerçekleştirildi. Ayrıca lokal LLM çalışmaları için Ollama kurulup servis ayağa kaldırıldı ve temel model çalıştırma doğrulamaları yapıldı.;23/Feb/26 4:41 PM;basak.ayverdi;25200 | AJ10: OpenClaw araştırması kapsamında iki teknik toplantı gerçekleştirildi. Araştırma ve teknik değerlendirme süreci devam etmektedir.;25/Feb/26 5:07 PM;basak.ayverdi;10800 | AK10: Sprint toplantısına katılım sağlandı. Toplantı sonrasında Ürün Yönetimi tarafından paylaşılan doküman detaylı şekilde incelendi ve doküman içerisinde yer alan Agentic AI proje fikirleri teknik açıdan analiz edildi. Projede kullanılması planlanan Google AI Studio, Gemini GEMS ve Google OPAL çözümleri hakkında ön araştırma yapılarak bu teknolojilerin yetkinlikleri, entegrasyon kabiliyetleri ve olası kullanım senaryoları değerlendirildi. Araştırma ve PoC talep edilen proje kapsamında teknik fizibilite analizi gerçekleştirildi, olası sistem mimarisi ve entegrasyon yaklaşımı üzerine teknik strateji çalışması yapıldı ve PoC sürecinde izlenecek yol haritasına ilişkin ön çerçeve oluşturuldu.;26/Feb/26 5:08 PM;basak.ayverdi;25200 | AL10: agentic ai araştırmaları arge çalışması öncesi devam ediyor;27/Feb/26 4:14 PM;basak.ayverdi;10800 | AM10: Agentic AI ve Copilot agent kullanımı /API entegrasyonu nasıl yapılı üzerindeki çalışmalar hala devam ediliyor . Python Kodlarına nasıl entegre edilir ve llm nasıl kullanılır hakkında denemeler yapılıyor . N8N değerlendirme analizin sonuçlarının iletilecek ilgili mailler değiştirildi ve çoklu mail gönderme işlemi yapıldı . Chat-bot CRM değerlendirme toplantısına katılım gösterildi ._x000D_ ;02/Mar/26 5:06 PM;basak.ayverdi;18000 | AN10: koordinasyon toplantısına katılım sağlandı.;04/Mar/26 6:01 PM;basak.ayverdi;7200 | AO10: CERTI Toplantı Follow-Up - TURKKEP ve Chatbot Yaygınlaştırma, Orbina Yapay Zeka Uygulamaları ve POC İhtiyacı toplantılarına katılım sağlandı._x000D_ ;05/Mar/26 5:31 PM;basak.ayverdi;10800 | AP10: Prompta e-Devlet üzerinden KEP hesabı oluşturma/onaylama gibi yanlış kullanıcı varsayımlarını tespit edip nazikçe doğru süreci açıklayan “misconception correction” ve e-Devlet bağlamı kuralları eklendi._x000D_ “Bordro” kelimesinin sık yapılan yazım hatalarını (bodro, bordo, bordru vb.) kapsayacak şekilde payroll prompt scope’u güncellendi ve botun bordro taleplerini doğru algılaması sağlandı._x000D_ satış ve operasyon birimiyle ister toplama amacıyla görüşme yapıldı;11/Mar/26 4:23 PM;basak.ayverdi;21600 | AQ10: Sprint ve Orbina ekipleri ile proje toplantısına katılım sağlandı, mevcut ilerleme ve sonraki adımlar değerlendirildi._x000D_ Bayiler için geliştirilen botun veri yapısı üzerinde çalışma yapıldı ve bot promptunun ilk versiyonu hazırlandı._x000D_ Beautiful Soup ile hazırlanan rapor çalışmasına yönelik PoC workflow inşası gerçekleştirildi._x000D_ Workflow içerisinde kullanılabilecek scraper API alternatifleri araştırıldı ve iki servis üzerinde karar verildi.;12/Mar/26 5:06 PM;basak.ayverdi;21600 | AR10: Daily ve Yazılım ekibi toplantılarına katılım sağlandı ve n8n chatbot executions takibi yapıldı. bordro ile ilgili olan prompt güncellemesine v2 yazıldı._x000D_ ;13/Mar/26 5:15 PM;basak.ayverdi;14400 | AS10: Satış Direktörü ile ihtiyaçların toplanması amacıyla bir toplantı gerçekleştirildi. Bayii workflow’u kapsamında kullanılan soru–cevap çiftlerinin embedding hashing skorunu artırmak amacıyla veri formatlarında düzenlemeler yapıldı. Yapılan güncellemelerin ardından ilgili veri seti Qdrant vektörel veritabanına yüklendi.;16/Mar/26 5:06 PM;basak.ayverdi;21600 | AT10: idenfit ve callie şirketleri toplantılarına katılım sağlandı;17/Mar/26 4:31 PM;basak.ayverdi;7200 | BQ10: 0 | BR10: 219600 | BU10: 0 | BV10: 219600 | CT10: 0|i01ef6:r | CU10: YZCK Sprint 4
A11: Ek İşler Hk. | B11: YZCK-34 | C11: 23023 | E11: Side-Jobs | F11: To Do | G11: YZCK | H11: Yapay Zeka Destekli Çağrı Karşılama | I11: software | J11: elvan.gurler | M11: Medium | O11: omer.saritoy | P11: elvan.gurler | Q11: elvan.gurler | R11: 46073.7 | S11: 46098.951 | T11: 46100.369 | Y11: 0 | AA11: Arka planda yapılan işlerin loglanması | AC11: elvan.gurler | AH11: Co-One test çıktılarının detaylı veri inceleme ve doğrulama çalışmaları yapıldı._x000D_ _x000D_ Soru–cevap yapısının format ve içerik standardizasyonu sağlandı._x000D_ _x000D_ Qdrant aktarım sürecinde veri kontrol ve validasyon işlemleri gerçekleştirildi._x000D_ _x000D_ Proje Kartı Form önerisi üzerinde revize ve iyileştirme çalışmaları yapıldı.;20/Feb/26 4:50 PM;omer.saritoy;14400 | AI11: Mac Mini üzerinde development ortamı hazırlanarak OpenCrawl kurulumu ve temel konfigürasyonları tamamlandı, OpenAI API key tanımlanarak servis entegrasyonu ve ilk test çağrıları başarıyla gerçekleştirildi. Ayrıca lokal LLM çalışmaları için Ollama kurulup servis ayağa kaldırıldı ve temel model çalıştırma doğrulamaları yapıldı.;23/Feb/26 4:41 PM;omer.saritoy;25200 | AJ11: Araştırma ve inceleme kapsamında istenilen Openclaw kurlumu yapıldı . Openclaw için ollama modelleri indirildi ve openclaw entegrasyonu üzerine çalışlıyor . Ayrıca openai doğrudan entegre edilerek bağlantısı sağlandı . ;24/Feb/26 5:32 PM;omer.saritoy;28800 | AK11: Openclaw kurulumu yapıldı ardından ollama kurulumu başarılı ile gerçekleştirildi . Agent için gerekli araştırmalar yapıldı_x000D_ ;25/Feb/26 5:52 PM;omer.saritoy;18000 | AL11: Sprint toplantısına katılım sağlandı. Toplantı sonrası Ürün Yönetimi’nin paylaştığı doküman incelenerek Agentic AI proje fikirleri teknik açıdan değerlendirildi. Google AI Studio, Gemini GEMS ve Google OPAL için ön araştırma yapılarak yetkinlikleri ve entegrasyon opsiyonları analiz edildi. Talep edilen PoC kapsamında teknik fizibilite çalışması yapıldı, olası mimari ve entegrasyon yaklaşımı netleştirildi, PoC için başlangıç yol haritası oluşturuldu.;26/Feb/26 9:51 PM;omer.saritoy;25200 | AM11: N8N değerlendirme analizin sonuçlarının iletilecek ilgili mailler değiştirildi ve çoklu mail gönderme işlemi yapıldı . Chat-bot CRM değerlendirme toplantısına katılım gösterildi .;02/Mar/26 4:45 PM;omer.saritoy;10800 | AN11: _x000D_ koordinasyon toplantısına katılım sağlandı;05/Mar/26 2:29 PM;omer.saritoy;7200 | AO11: Günlük cevaplanmayan sorular toplantısı yapıldı CERTI Toplantı Follow-Up - TURKKEP ve Chatbot Yaygınlaştırma, Orbina Yapay Zeka Uygulamaları ve POC İhtiyacı toplantılarına katılım sağlandı . ;05/Mar/26 5:29 PM;omer.saritoy;10800 | AP11: Cevaplanmayan sorular üzerine daily toplantısına katılım sağlandı ve IK agent üzerine ik dahil olmak üzere toplantıya katılım sağlandı ;06/Mar/26 4:35 PM;omer.saritoy;3600 | AQ11: Günlük Cevaplanmayan sorular toplantısına katılım sağlandı ve Beautiful Soup üzerine araştırma yapıldı ;09/Mar/26 4:47 PM;omer.saritoy;7200 | AR11: Cevaplanmayan sorula daily toplantısına katılım sağlandı. IK Agent için neler yapılabilir üzerine araştırma yapıldı ;10/Mar/26 3:33 PM;omer.saritoy;7200 | AS11: Cevaplanmayan sorular üzerine daily toplantısı yapıldı .İsterleri üzerine Finans ve Opearasyon birimleri ile toplantı yapıldı ;11/Mar/26 4:24 PM;omer.saritoy;7200 | AT11: Sprint ve Orbina ekipleri ile proje toplantısına katılım sağlandı, mevcut ilerleme ve sonraki adımlar değerlendirildi.;12/Mar/26 5:16 PM;omer.saritoy;7200 | AU11: Cevaplanmayan sorular üzerine ayrıca Yazılım Ekibi Toplantısına katılım sağlandı . Executions takibi n8n de yapıldı ;13/Mar/26 4:32 PM;omer.saritoy;14400 | AV11: Cevaplanmayan sorular toplantısına katılım sağlandı ve executions takibi yapıldı . CRM chatbot için ayrıca görüşme yapıldı .;16/Mar/26 4:48 PM;omer.saritoy;10800 | AW11: Cevaplanmayan sorular daily,idenfit ve callie toplantılarına katılım sağlandı ve genel chatbot execution takibi yapıldı ;17/Mar/26 10:50 PM;omer.saritoy;14400 | BQ11: 0 | BR11: 212400 | BU11: 0 | BV11: 212400 | CT11: 0|i01ef6:i | CU11: YZCK Sprint 4
A12: Vectorel Veri Tabanında Q&A Verilerinin Artırılması | B12: YZCK-9 | C12: 22502 | E12: Story | F12: In Progress | G12: YZCK | H12: Yapay Zeka Destekli Çağrı Karşılama | I12: software | J12: elvan.gurler | M12: Medium | O12: omer.saritoy | P12: elvan.gurler | Q12: elvan.gurler | R12: 45978.681 | S12: 46097.701 | T12: 46100.369 | Y12: 0 | AA12: Vectorel veri tabanında Q&A verilerinin artırılmasına yönelik dokümanlardan elde edilerek yeni veriler eklenmesi gerekmektedir. | AC12: elvan.gurler | AH12: TÜRKKEP ürünleri için chatbot eğitim verisi oluşturma kapsamında, TÜRKKEP’in resmi web sitesindeki ürün açıklamaları ile paylaşılan ürün kılavuzları (PDF/PPTX) detaylı şekilde incelenmiş; tüm içerikler doğrultusunda e-Fatura Portalı, KEP, e-İmza, token yazılımları, sürücü güncellemeleri, PIN işlemleri, entegrasyon modülleri ve diğer destek dokümanları için kapsamlı, benzersiz ve arama motoru uyumlu soru–cevap (Q&A) setleri hazırlanmıştır. Tüm bilgiler sadeleştirilerek chatbot kullanımına uygun formata dönüştürülmüş, terimler standardize edilmiş ve ürünler arasındaki karışıklığı önlemek için her soru ilgili ürün adıyla birlikte yeniden yazılmıştır. Hazırlanan tüm Q&A içerikleri Excel formatında yapılandırılarak teslim edilmiş olup, süreç yeni dokümanlar ve ürün güncellemeleri geldikçe gelişmeye ve genişlemeye açık olacak şekilde tasarlanmıştır.;17/Nov/25 4:53 PM;basak.ayverdi;25200 | AI12: TÜRKKEP ürünleri için chatbot eğitim verisi oluşturma kapsamında resmi site ve ürün kılavuzları incelenerek e-Fatura Portalı, KEP, e-İmza, token yazılımları, sürücü güncellemeleri, PIN işlemleri ve entegrasyon modülleri için kapsamlı ve standart Q&A setleri hazırlanmıştır. Tüm içerikler sadeleştirilip chatbot formatına uygun hale getirilerek Excel dosyası olarak yapılandırılmış ve teslim edilmiştir.;17/Nov/25 5:04 PM;omer.saritoy;18000 | AJ12: Düzeltilmiş olan soru–cevap içeriklerini Qdrant’a yükledim; ancak tüm linklerin ve içeriklerin temizlenmesi henüz tamamlanmadığı için kalan kayıtların düzenlenmesi ve yüklenmesi süreci devam ediyor.;19/Nov/25 4:55 PM;basak.ayverdi;7200 | AK12: Excel verilerindeki sıkıntıların bir kısmı giderildi ve vector veritabanına pyhton kodu ile aktarıldı .;19/Nov/25 4:59 PM;omer.saritoy;7200 | AL12: Çağrı merkezi biriminden iletilen soru–cevap dokümanları Excel formatında düzenlendi. Düzenlenen veriler Python scriptleri kullanılarak vektör veri tabanına aktarılacak yapıya uygun hale getirildi.Excel dosyalarındaki soru–cevap içerikleri temizlendi, normalize edildi.Gereksiz sütunlar kaldırıldı, format uyumsuzlukları giderildi.;24/Nov/25 4:39 PM;omer.saritoy;7200 | AM12: Çağrı merkezinden gelen revizeleri düzenledikten sonra vektörel veritabanı için optimize edip verileri Qdrant’a yükledim. Ardından bota farklı senaryolarla test soruları yönelterek input kontrolü yaptım, karşılaştığım hataları tespit edip Orbinaya ilettim ve geri dönüşleri aldıktan sonra izlenecek yol konusunda karar verdik.;24/Nov/25 5:12 PM;basak.ayverdi;10800 | AN12: Çağrı merkezinden gelen QA verilerinin düzenlenmesi gerçekleştirildi ve düzenlenen veriler main excele aktarılıp ordanda qdrant vector veritabanına işlendi.;01/Dec/25 5:00 PM;omer.saritoy;9000 | AO12: Yeni gelen SSS içeriklerini optimize edip Qdrant veri tabanına yükledim. İçerikleri düzenleyip temizledikten sonra chatbot üzerinde farklı soru türleriyle test ettim. Yükleme sırasında ortaya çıkan Python SSL hatasını analiz edip üstüne çalıştık çözdük ve veri aktarımını başarıyla tamamladık.;01/Dec/25 5:19 PM;basak.ayverdi;9000 | AP12: İş birlikleri ve entegrasyon ile ilgili iletilen tablo veri işleme süreçlerine uygun şekilde modellenmiştir. Kontrollerin tamamlanmasının ardından veritabanına aktarım gerçekleştirilecektir. Aynı zamanda çağrı merkezinden gelen yeni soru cevap çiftleri değerlendirilmiştir.;08/Dec/25 5:15 PM;basak.ayverdi;14400 | AQ12: Çağrı merkezinden gelen sorular eklendi ve soru cevap artırımı yapıldı ;08/Dec/25 5:16 PM;omer.saritoy;7200 | AR12: Excel verileri üzerine düzenlemeler yapıldı ;09/Dec/25 5:10 PM;omer.saritoy;3600 | AS12: çağrı merkezinin yeni gönderdiği soru cevap setleri üzerinde vektorel veritabanında verimli olması adına düzenlemeler yapıldı ve veritabanına yüklendi. input checkleri yapıldı.;09/Dec/25 5:11 PM;basak.ayverdi;3600 | AT12: Şirketler vs. hakkında gelen soru cevap setleri excele aktarıldı oradan da qdrant vector dbye aktarıldı ;10/Dec/25 5:00 PM;omer.saritoy;7200 | AU12: Şirketler ve benzeri konulardaki soru–cevap setleri Excel’e aktarıldı, ardından Qdrant vector DB’ye yüklendi. Input kontrolleri yapılarak hatalar tespit edildi.;10/Dec/25 5:02 PM;basak.ayverdi;7200 | AV12: Ürün tarafından yeni gelen veriler üzerine çalışıp qdranta eklendi. Müşteri destek botunu test etmek amacıyla verilen içerikten yararlanarak doğal sohbet dilinde ek soru setleri ürettim. testleri yapıldı doğal dilde;11/Dec/25 5:20 PM;basak.ayverdi;10800 | AW12: gelen excel verileri düzenlenip qdranta aktarıldı _x000D_ ;11/Dec/25 5:21 PM;omer.saritoy;10800 | AX12: bazı soru cevap çiftlerinde mail kısmı eksikti onlar eklendi ve pushlandı. gün içinde qdranta erişim sorunu yaşandı. ;15/Dec/25 5:05 PM;basak.ayverdi;3600 | AY12: excel verilerinde gerekli mail adresleri eklendi ve qdrant vector db'sine aktarıldı ;15/Dec/25 5:05 PM;omer.saritoy;7200 | AZ12: Yapay zekâ tabanlı chatbotta mevcut SSS cevaplarını test ederek, yönlendirici ve akış bağımlı içeriklerin AI kullanımına uygunluğunu değerlendirildi.;18/Dec/25 5:16 PM;basak.ayverdi;14400 | BA12: _x000D_ Yapay zekâ tabanlı chatbotta mevcut SSS cevaplarını düzenleme ,yönlendirme ve qdranta yükleme;18/Dec/25 5:20 PM;omer.saritoy;14400 | BB12: revize edilmiş veriler düzenlendi ve qdrant'a aktarılması için yeni bir python kodu yazıldı ve qdranta başarılı bir şekilde eklendi ;22/Dec/25 4:44 PM;omer.saritoy;10800 | BC12: Çağrı merkezinden yeni gelen verilerin düzenlenmesi için yeni bir Python kodu yazıldı ve veriler Qdrant veritabanına aktarıldı. Qdrant’a aktarılan yeni verilerin testleri yapıldı.;22/Dec/25 5:10 PM;basak.ayverdi;18000 | BD12: Cevaplanmayan sorular düzenlendi çağrı merkezine yönlendirilecek ;21/Jan/26 5:09 PM;omer.saritoy;3600 | BE12: dilekçe örnekleriyle ilgili websitesindeki bilgiler önce rag yaptığımız q&a'e eklendi daha sonra qdrant veritabanına eklendi. testi sonucunda bir frontend hatası tespit edildi.;28/Jan/26 5:04 PM;basak.ayverdi;7200 | BF12: TürkKEP sitesinde bulunan Dilekçe örneklerini excel'e soru cevap olarak eklendi ve qdrant veri tabanına yüklendi ;28/Jan/26 5:06 PM;omer.saritoy;10800 | BG12: Uyumluluk tarafından gelen yeni sorular sisteme eklendi, opsiyonel sorular üretildi. Aynı soruya farklı execution’larda farklı RAG sonuçları dönmesi problemi testler sırasında tespit edildi. Orbina tarafına iletildi._x000D_ _x000D_ ;29/Jan/26 5:03 PM;basak.ayverdi;10800 | BH12: Uyumluluk ekibinden gelen yeni soru seti sisteme entegre edildi. Bu kapsamda opsiyonel soru üretimi tarafında gerekli güncellemeler tamamlandı. Test senaryoları çalıştırılırken, aynı input için farklı execution’larda tutarsız RAG çıktıları üretildiği gözlemlendi. İlgili problem analiz edilerek Orbina ekibine detaylarıyla birlikte raporlandı.;29/Jan/26 5:12 PM;omer.saritoy;10800 | BI12: qdranta veri yüklerken aldığımız eksik soru yükleme hatası yükleme yaptığımız py kodunu düzelterek düzeltildi. ;30/Jan/26 5:01 PM;basak.ayverdi;7200 | BJ12: verilerimizde duplicate olan soruların tespiti yapıldı ve py kodunda düzeltmeler yapıldı;30/Jan/26 5:03 PM;omer.saritoy;7200 | BK12: Co-One test sonuçları analiz edilerek ayrıştırılan veriler soru–cevap setine eklendi._x000D_ _x000D_ Mevcut soru–cevap setlerinde hatalı ve eksik sorular revize edildi._x000D_ _x000D_ Güncellenen veri seti Python kodları ile Qdrant vektör veritabanına işlendi.;20/Feb/26 4:50 PM;omer.saritoy;10800 | BL12: Veri setlerinde bazı sorular üzerinde düzenlemeler yapıldı ve executions yola çıkarak yeni soru ve cevaplar eklendi;27/Feb/26 5:14 PM;omer.saritoy;7200 | BM12: yeni gelen operasyon verileri değerlendirilip qdrant veritabanına eklenmiştir;06/Mar/26 4:31 PM;basak.ayverdi;7200 | BN12: Çağrı merkezinden gelen veriler incelenerek qdrant verilerine eklendi ;06/Mar/26 4:34 PM;omer.saritoy;7200 | BO12: Uyum tarafından gelen veriler qdrant veri tabanına düzenlenerek yüklendi;16/Mar/26 4:49 PM;omer.saritoy;7200 | BQ12: 0 | BR12: 324000 | BU12: 0 | BV12: 324000 | CT12: 0|i01ef0: | CU12: YZCK Sprint 1 | CV12: YZCK Sprint 3 | CW12: YZCK Sprint 4
A13: Duyuru Modülünde Onay/Ret Akışı ile Çoklu Doküman Gönderimi | B13: WIK-839 | C13: 23180 | E13: Story | F13: To Do | G13: WIK | H13: KEP İK Bulut | I13: software | J13: ceren.sertkaya | L13: https://kep-ik.turkkep.com.tr/ | M13: Medium | O13: ceren.sertkaya | P13: gulnur.aka | Q13: gulnur.aka | R13: 46098.466 | S13: 46098.529 | T13: 46100.369 | Y13: 0 | AA13: *Açıklama:*_x000D_ _x000D_ Duyuru modülünde kullanıcı birden fazla doküman ekleyip onay-ret akışyıla gönderim kullanıcılara sunulmalıdır._x000D_ _x000D_ *Amaç:* _x000D_ _x000D_ Kullanıcının birden fazla doküman eklediği durumlarda onay/ret sürecini doğru ve anlaşılır şekilde kullanabilmesini sağlamak._x000D_ _x000D_ Kullanıcı gönderim sağladıktan sonra mevcuttaki onay-ret akışıyla devam edebilmelidir. | AC13: gulnur.aka | BZ13: 17/Mar/26 11:11 AM;gulnur.aka;image-2026-03-17-12-11-02-599.png;http://192.168.124.186:8080/secure/attachment/16062/image-2026-03-17-12-11-02-599.png | CT13: 0|i00vra:zsyzgznqmf9
A14: Analiz-Onay/Ret Ekranında Ek Dosyaların Gösterimi ve Kontrolü | B14: WIK-838 | C14: 23179 | E14: Story | F14: To Do | G14: WIK | H14: KEP İK Bulut | I14: software | J14: ceren.sertkaya | L14: https://kep-ik.turkkep.com.tr/ | M14: Medium | O14: ceren.sertkaya | P14: gulnur.aka | Q14: gulnur.aka | R14: 46098.461 | S14: 46098.558 | T14: 46100.369 | Y14: 0 | AA14: *Açıklama:*_x000D_ _x000D_ Duyuru modülünde kullanıcı herhangi bir duyuruya Word, onay/ret ekranında bu dosyanın olduğu kullanıcı tarafından net şekilde anlaşılmalıdır._x000D_ _x000D_ PDF önizlemesi olmadığı durumlarda, kullanıcı ekli bir dosya olduğunu görebilmelidir._x000D_ _x000D_ *Amaç:*_x000D_ _x000D_ Kullanıcıya ek dosya olduğunu açıkça göstermek ve herhangi bir dosya türünde dosyanın görünürlüğünü sağlamak._x000D_ _x000D_ | AC14: gulnur.aka | BZ14: 17/Mar/26 11:04 AM;gulnur.aka;image-2026-03-17-12-04-10-389.png;http://192.168.124.186:8080/secure/attachment/16061/image-2026-03-17-12-04-10-389.png | CT14: 0|i00vra:zsyzgznqmezy
A15: Duyuru Metni için Karakter Limiti ve Canlı Sayaç Gösterimi | B15: WIK-837 | C15: 23178 | E15: Story | F15: To Do | G15: WIK | H15: KEP İK Bulut | I15: software | J15: ceren.sertkaya | L15: https://kep-ik.turkkep.com.tr/ | M15: Medium | O15: ceren.sertkaya | P15: gulnur.aka | Q15: gulnur.aka | R15: 46098.456 | S15: 46098.529 | T15: 46100.369 | Y15: 0 | AA15: *Açıklama:*_x000D_ _x000D_ Duyuru oluşturma ekranında yer alan “duyuru metni” (body) alanı için maksimum karakter sınırı 1800'dır. Kullanıcı yazım sırasında mevcut karakter sayısını anlık olarak görebilmeli ve limit aşıldığında gönderim engellenmelidir._x000D_ _x000D_ Amaç, kullanıcıyı yazım sırasında bilgilendirmek ve hatalı gönderimleri önlemektir._x000D_ _x000D_ Mevcut durumda kullanıcı iletiyi gönderdiği aşamada sistem uyarı vermektedir. | AC15: gulnur.aka | BZ15: 17/Mar/26 10:57 AM;gulnur.aka;image-2026-03-17-11-57-28-923.png;http://192.168.124.186:8080/secure/attachment/16060/image-2026-03-17-11-57-28-923.png | CT15: 0|i00vra:zsyzgznqmfi
A16: Onay Ret Login Ekranında Zorunlu Alanların Belirtilmesi | B16: WIK-836 | C16: 23177 | E16: Story | F16: To Do | G16: WIK | H16: KEP İK Bulut | I16: software | J16: ceren.sertkaya | L16: https://kep-ik.turkkep.com.tr/ | M16: Medium | O16: ceren.sertkaya | P16: gulnur.aka | Q16: gulnur.aka | R16: 46098.452 | S16: 46098.562 | T16: 46100.369 | Y16: 0 | AA16: *Amaç:*_x000D_ _x000D_ Kullanıcının hangi alanları doldurması gerektiğini net şekilde anlamasını sağlamak ve hatalı/eksik girişleri azaltmak._x000D_ _x000D_ Kullanıcı olara, giriş yaparken hangi alanların zorunlu olduğunu açıkca gösterilmelidir. _x000D_ _x000D_ *Kapsam:*_x000D_ _x000D_ Zorunlu alanların yanına *işareti eklenmelidir._x000D_ _x000D_ Kep Hesabı (Zorunlu)_x000D_ _x000D_ Yetkili Kodu_x000D_ _x000D_ Şifre (Zorunlu) | AC16: gulnur.aka | BZ16: 17/Mar/26 10:51 AM;gulnur.aka;image-2026-03-17-11-51-01-312.png;http://192.168.124.186:8080/secure/attachment/16059/image-2026-03-17-11-51-01-312.png | CT16: 0|i00vra:zsyzgznqmezs
A17: Analiz-Onay/Ret Akışında Süresi İçinde İşlem Yapılan Linkin Tekrar Kullanımının Engellenmesi | B17: WIK-835 | C17: 23176 | E17: Story | F17: To Do | G17: WIK | H17: KEP İK Bulut | I17: software | J17: ceren.sertkaya | L17: https://kep-ik.turkkep.com.tr/ | M17: Medium | O17: ceren.sertkaya | P17: gulnur.aka | Q17: gulnur.aka | R17: 46098.445 | S17: 46098.554 | T17: 46100.369 | Y17: 0 | AA17: *Açıklama:*_x000D_ _x000D_ Kullanıcıya gönderilen İK onay/ret linki belirli bir süre için geçerlidir. Kullanıcı bu süre içerisinde onay veya ret işlemini gerçekleştirdiğinde, ilgili linkin tekrar kullanılması engellenmelidir._x000D_ _x000D_ Mevcut durumda kullanıcı işlem yaptıktan sonra aynı linke tekrar erişim sağlayabilmektedir; onayla ret akışını tamamladıktan sonra uyarıyla karşılaşmaktadır. Bu durumun önüne geçilmesi gerekmektedir._x000D_ _x000D_ Kullanıcı kep adresinin içersinde yer alan onay link git dediğinde kullanıcıya yönlendirme yapmaması beklenmektedir. | AC17: gulnur.aka | BZ17: 17/Mar/26 10:42 AM;gulnur.aka;screenshot-1.png;http://192.168.124.186:8080/secure/attachment/16058/screenshot-1.png | CT17: 0|i00vra:zsyzgznqmezw
A18: KEP Delil Raporlarının Sıralanması | B18: WIK-834 | C18: 23162 | E18: Bug | F18: To Do | G18: WIK | H18: KEP İK Bulut | I18: software | J18: ceren.sertkaya | L18: https://kep-ik.turkkep.com.tr/ | M18: Medium | O18: can.macit | P18: ceren.sertkaya | Q18: ceren.sertkaya | R18: 46097.674 | S18: 46098.594 | T18: 46100.369 | Y18: 0 | AA18: KEP delil raporları en yeniden eskiye şekilde düzenli şekilde ''oluşturma tarihine'' baz alarak sıralanmalıdır | AC18: ceren.sertkaya | CT18: 0|i00vra:zsyzgznqmezk | CU18: WIK Sprint 2026/ 13-14 | DI18: 10
A19: Sistem Ayarları Sayfasında ''Kaydet'' Aşamasının Uyarısı | B19: WIK-833 | C19: 23161 | E19: Bug | F19: To Do | G19: WIK | H19: KEP İK Bulut | I19: software | J19: ceren.sertkaya | L19: https://kep-ik.turkkep.com.tr/ | M19: Medium | O19: can.macit | P19: ceren.sertkaya | Q19: ceren.sertkaya | R19: 46097.669 | S19: 46098.595 | T19: 46100.369 | Y19: 0 | AA19: Sistem ayarlarında firma bilgileri kaydet adımına basıldığında uyarı aşağıdaki revize edebiliriz. _x000D_ _x000D_ Yeni uyarı metini '' Sistem ayarları başarı ile kaydedilmiştir.'' | AC19: ceren.sertkaya | CT19: 0|i00vra:zsyzgznqmezr | CU19: WIK Sprint 2026/ 13-14 | DI19: 10
A20: Çalışan Ekle- Tek Başvuru Ekleme Adımı Karakter ve Parametre Kontrolü | B20: WIK-832 | C20: 23144 | E20: Bug | F20: To Do | G20: WIK | H20: KEP İK Bulut | I20: software | J20: ceren.sertkaya | L20: https://kep-ik.turkkep.com.tr/ | M20: Medium | O20: can.macit | P20: ceren.sertkaya | Q20: ceren.sertkaya | R20: 46091.61 | S20: 46098.594 | T20: 46100.369 | Y20: 0 | AA20: *E posta Hatası*_x000D_ _x000D_ Başvuru eklerken aşağıdaki ekran görüntüsündeki gibi e posta adresi eklerken Türkçe karakter kabul edilmektedir. Karakter kontrolü bulunmamaktadır._x000D_ _x000D_ Müşteri E posta adresi el ile yazması ve kopyala-yapıştır fonksiyonunu kullanarak eklemesi halinde format uygun değilse başvuru kayıt bilgisi oluşmamalı. _x000D_ _x000D_ Müşteriye hatalı giriş yaptığına dair uyarı verilmelidir._x000D_ _x000D_ *Uyarı mesajı '' Geçersiz e‑posta adresi. Lütfen doğru formatta giriniz''*_x000D_ _x000D_ *Doğum Tarihi hatası*_x000D_ _x000D_ Doğum tarihi eğer el ile yazılırsa ve 18/03/1992aşlsjdl gibi sayılar ve karakterler harici bu şekilde ekleme sağlanabilmektedir. _x000D_ _x000D_ Başvuruyu eklediğinde ''default'' bir değerle gelmektedir._x000D_ _x000D_ Doğum tarihi alanı eğer el ile girilecekse uygun şekilde giriş sağlanmalıdır. _x000D_ _x000D_ Kabul edilen tarih formatı haricinde bir karakter girişi yapılmamalıdır. _x000D_ _x000D_ Giriş yapılırken eğer kullanıcı uygun formatta giriş sağlamaz ise_x000D_ _x000D_ Müşteriye uyarı verilmelidir._x000D_ _x000D_ *Uyarı metini ''"Lütfen doğum tarihinizi geçerli formatta (GG/AA/YYYY) giriniz."*_x000D_ _x000D_ _x000D_ _x000D_ *!image-2026-03-10-15-37-19-469.png!*_x000D_ _x000D_ _x000D_ _x000D_ *Oluşan başvurudaki değerler*_x000D_ _x000D_ *!image-2026-03-10-15-38-03-883.png!* | AC20: ceren.sertkaya | BZ20: 10/Mar/26 2:37 PM;ceren.sertkaya;image-2026-03-10-15-37-19-469.png;http://192.168.124.186:8080/secure/attachment/16016/image-2026-03-10-15-37-19-469.png | CA20: 10/Mar/26 2:38 PM;ceren.sertkaya;image-2026-03-10-15-38-03-883.png;http://192.168.124.186:8080/secure/attachment/16015/image-2026-03-10-15-38-03-883.png | CT20: 0|i00vra:zsyzgznqmez | CU20: WIK Sprint 2026/ 13-14 | DI20: 20
A21: Ek İşler Hk | B21: WIK-831 | C21: 23130 | E21: Side-Jobs | F21: To Do | G21: WIK | H21: KEP İK Bulut | I21: software | J21: ceren.sertkaya | L21: https://kep-ik.turkkep.com.tr/ | M21: Medium | O21: dogukan.oncuer | P21: ceren.sertkaya | Q21: ceren.sertkaya | R21: 46090.447 | S21: 46099.712 | T21: 46100.369 | Y21: 0 | AC21: ceren.sertkaya | AH21: retrospektif;09/Mar/26 2:48 PM;dogukan.oncuer;5820 | AI21: popup backdrop kapanmama sorunu fix ve cerenle hata tespiti ve duyuru modülü readonly dizaynı;10/Mar/26 5:07 PM;dogukan.oncuer;2700 | AJ21: beytullahla webik pipeline hatası;16/Mar/26 11:33 AM;dogukan.oncuer;5400 | AK21: ;18/Mar/26 5:05 PM;dogukan.oncuer;7200 | BQ21: 0 | BR21: 21120 | BU21: 0 | BV21: 21120 | CT21: 0|i00vra:zsyzgznqmex | CU21: WIK Sprint 2026/ 11-12
A22: Ek İşler Hk | B22: WIK-830 | C22: 23129 | E22: Side-Jobs | F22: To Do | G22: WIK | H22: KEP İK Bulut | I22: software | J22: ceren.sertkaya | L22: https://kep-ik.turkkep.com.tr/ | M22: Medium | O22: onder.bar | P22: ceren.sertkaya | Q22: ceren.sertkaya | R22: 46090.447 | S22: 46090.447 | T22: 46100.369 | Y22: 0 | AC22: ceren.sertkaya | CT22: 0|i00vra:zsyzgznqmewi | CU22: WIK Sprint 2026/ 11-12
A23: Ek İşler Hk | B23: WIK-829 | C23: 23128 | E23: Side-Jobs | F23: To Do | G23: WIK | H23: KEP İK Bulut | I23: software | J23: ceren.sertkaya | L23: https://kep-ik.turkkep.com.tr/ | M23: Medium | O23: mehmetcan.olgun | P23: ceren.sertkaya | Q23: ceren.sertkaya | R23: 46090.447 | S23: 46090.447 | T23: 46100.369 | Y23: 0 | AC23: ceren.sertkaya | CT23: 0|i00vra:zsyzgznqmey | CU23: WIK Sprint 2026/ 11-12
A24: Ek İşler Hk | B24: WIK-828 | C24: 23127 | E24: Side-Jobs | F24: To Do | G24: WIK | H24: KEP İK Bulut | I24: software | J24: ceren.sertkaya | L24: https://kep-ik.turkkep.com.tr/ | M24: Medium | O24: can.macit | P24: ceren.sertkaya | Q24: ceren.sertkaya | R24: 46090.447 | S24: 46098.625 | T24: 46100.369 | Y24: 0 | AC24: ceren.sertkaya | AH24: -Rutin uygulama logları takip edildi._x000D_ _x000D_ -Sprint planlama toplantısına katılım sağlandı.;17/Mar/26 3:00 PM;can.macit;7200 | BQ24: 0 | BR24: 7200 | BU24: 0 | BV24: 7200 | CT24: 0|i00vra:zsyzgznqmew | CU24: WIK Sprint 2026/ 11-12
A25: Analiz-Çalışan Ekranı Liste Sayfasında Duyuru Detayının Pop-up Olarak Gösterilmesi | B25: WIK-827 | C25: 23110 | E25: Story | F25: Done | G25: WIK | H25: KEP İK Bulut | I25: software | J25: ceren.sertkaya | L25: https://kep-ik.turkkep.com.tr/ | M25: Medium | N25: Verified | O25: gurkan.guney | P25: gulnur.aka | Q25: gulnur.aka | R25: 46087.517 | S25: 46097.602 | T25: 46100.369 | U25: 46097.602 | Y25: 0 | AA25: *Açıklama:*_x000D_ Çalışan ekranında yer alan liste sayfasındaki Duyuru modülüne tıklanarak gönderilen duyurular görüntülenebilmektedir._x000D_ _x000D_ Mevcut yapıda kullanıcı, gönderilen bir duyurunun detayını görmek istediğinde sistem kullanıcıyı doğrudan Duyuru modülünün detay ekranına yönlendirmektedir._x000D_ _x000D_ Yapılacak geliştirme ile birlikte kullanıcı deneyimini iyileştirmek amacıyla, gönderilen duyurunun detayının yeni bir sayfaya yönlendirme yerine İK Gönderiminde yer alan “Gönderilen İleti” yapısına benzer şekilde pop-up ekran içerisinde gösterilmesi hedeflenmektedir._x000D_ _x000D_ Bu sayede kullanıcı liste ekranından ayrılmadan duyuru içeriğini görüntüleyebilecektir._x000D_ _x000D_ *Gereksinimler:*_x000D_ _x000D_ Çalışan ekranındaki liste sayfasında yer alan Duyuru modülünde gönderilen duyuruların listelenmesi mevcut şekilde devam edecektir._x000D_ _x000D_ Kullanıcının listede yer alan herhangi bir duyuruya tıklaması durumunda:_x000D_ _x000D_ Yeni sayfaya yönlendirme yapılmamalıdır._x000D_ _x000D_ Duyuru detayı pop-up ekran içerisinde açılmalıdır._x000D_ _x000D_ Pop-up ekran tasarımı İK Gönderimindeki ileti gösterimiyle uyumlu olacak şekilde tasarlanmalıdır._x000D_ _x000D_ Pop-up içerisinde duyurunun tüm detay bilgileri görüntülenmelidir. (Attach kısmında görsel yer almaktadır.)_x000D_ _x000D_ *Kabul Kriterleri:*_x000D_ # Çalışan ekranı liste sayfasındaki duyuru listesinde bir duyuruya tıklandığında yeni sayfa yönlendirmesi yapılmamalıdır._x000D_ # Duyuru detayı pop-up ekran içerisinde açılmalıdır._x000D_ # Pop-up tasarımı İK Gönderim ileti pop-up yapısı ile tutarlı olmalıdır._x000D_ # Kullanıcı pop-up ekranı kapattığında tekrar duyuru listesine dönmelidir._x000D_ # Mevcut duyuru görüntüleme varsa yetkileri ve veri yapısı korunmalıdır._x000D_ _x000D_ Dosya ekinin görüntüleme aşamasında indirilmesi ve görüntülenmesi sağlanmalıdır. | AC25: gitlab.dev | AD25: gulnur.aka | AE25: gurkan.guney | AH25: görsel popup tasarım örnekleri oluşturulması;06/Mar/26 6:18 PM;dogukan.oncuer;4200 | AI25: ;12/Mar/26 2:01 PM;dogukan.oncuer;15600 | AJ25: ;15/Mar/26 5:55 PM;gurkan.guney;1800 | AK25: ;16/Mar/26 2:01 PM;dogukan.oncuer;600 | AL25: Test ortamda yapılan kontroller başarılı.;16/Mar/26 2:27 PM;gurkan.guney;600 | BQ25: 0 | BR25: 22800 | BU25: 0 | BV25: 22800 | BZ25: 06/Mar/26 12:23 PM;gulnur.aka;image-2026-03-06-13-23-34-883.png;http://192.168.124.186:8080/secure/attachment/15973/image-2026-03-06-13-23-34-883.png | CA25: 12/Mar/26 2:47 PM;ceren.sertkaya;kep ik duyuru görüntüleme.png;http://192.168.124.186:8080/secure/attachment/16046/kep+ik+duyuru+g%C3%B6r%C3%BCnt%C3%BCleme.png | CT25: 0|i00vra:zsyzgznqmc | CU25: WIK Sprint 2026/ 11-12 | DL25: 12/Mar/26 1:56 PM;gitlab.dev;[Dogukan Oncuer|https://git-lab.turkkep.com.tr/dogukan.oncuer] mentioned this issue in [commit b4c5ac8d|https://git-lab.turkkep.com.tr/kepappteam/kep-ik/webik-frontend-v2/-/commit/b4c5ac8d4d8c86291338add55252403ae6e8e393] of [KEPAPPTEAM / KEP IK / Webik Frontend V2|https://git-lab.turkkep.com.tr/kepappteam/kep-ik/webik-frontend-v2] on branch [WIK-827|https://git-lab.turkkep.com.tr/kepappteam/kep-ik/webik-frontend-v2/-/tree/WIK-827]:{quote}WIK-827 duyuru popup {quote} | DM25: 12/Mar/26 1:58 PM;gitlab.dev;[Dogukan Oncuer|https://git-lab.turkkep.com.tr/dogukan.oncuer] mentioned this issue in [commit 3ef1ed70|https://git-lab.turkkep.com.tr/kepappteam/kep-ik/webik-frontend-v2/-/commit/3ef1ed707b95e533745aae5093703437530023f6] of [KEPAPPTEAM / KEP IK / Webik Frontend V2|https://git-lab.turkkep.com.tr/kepappteam/kep-ik/webik-frontend-v2] on branch [dev|https://git-lab.turkkep.com.tr/kepappteam/kep-ik/webik-frontend-v2/-/tree/dev]:{quote}Merge branch 'WIK-827' into 'dev' WIK-827 duyuru popup Closes WIK-827 See merge request kepappteam/kep-ik/webik-frontend-v2!215{quote} | DN25: 12/Mar/26 1:58 PM;gitlab.dev;[Dogukan Oncuer|https://git-lab.turkkep.com.tr/dogukan.oncuer] mentioned this issue in [commit 4a2bf457|https://git-lab.turkkep.com.tr/kepappteam/kep-ik/webik-frontend-v2/-/commit/4a2bf4572638e8ff4cbacfcafaf52c4c6200bc25] of [KEPAPPTEAM / KEP IK / Webik Frontend V2|https://git-lab.turkkep.com.tr/kepappteam/kep-ik/webik-frontend-v2] on branch [test|https://git-lab.turkkep.com.tr/kepappteam/kep-ik/webik-frontend-v2/-/tree/test]:{quote}Merge branch 'dev' into 'test' WIK-827 duyuru popup See merge request kepappteam/kep-ik/webik-frontend-v2!216{quote} | DO25: 12/Mar/26 2:04 PM;gitlab.dev;✅ Pipeline başarılı, WIK-827 maddesi test ortamına aktarıldı. | DP25: 15/Mar/26 5:55 PM;gurkan.guney;1- Gönderimlerde CC olmadığı için pop-up'daki CC alanı kaldırılmalıdır. _x000D_ _x000D_ 2- İletiye ait konu hem 'Konu' başlığı altında hem de 'KEP İleti Detayı' başlığı altında gösterilmiş. İki defa göstermeye gerek yoktur. Sadece 'Konu' başlığı altında gösterilmesi yeterli olur. 'KEP İleti Detayı' nın altındaki kaldırılabilir. | DQ25: 16/Mar/26 9:46 AM;gitlab.dev;[Dogukan Oncuer|https://git-lab.turkkep.com.tr/dogukan.oncuer] mentioned this issue in [commit 2a779cc0|https://git-lab.turkkep.com.tr/kepappteam/kep-ik/webik-frontend-v2/-/commit/2a779cc04b4bd319527e59c1484480d7200447c9] of [KEPAPPTEAM / KEP IK / Webik Frontend V2|https://git-lab.turkkep.com.tr/kepappteam/kep-ik/webik-frontend-v2] on branch [dev|https://git-lab.turkkep.com.tr/kepappteam/kep-ik/webik-frontend-v2/-/tree/dev]:{quote}Merge branch 'WIK-827' into 'dev' wik 827 duyuru gönderi popupu cc kaldırıldı Closes WIK-827 See merge request kepappteam/kep-ik/webik-frontend-v2!217{quote} | DR25: 16/Mar/26 10:32 AM;gitlab.dev;[Dogukan Oncuer|https://git-lab.turkkep.com.tr/dogukan.oncuer] mentioned this issue in [commit a1bc7eff|https://git-lab.turkkep.com.tr/kepappteam/kep-ik/webik-frontend-v2/-/commit/a1bc7eff79897bf2238a5c068726911fb1608b10] of [KEPAPPTEAM / KEP IK / Webik Frontend V2|https://git-lab.turkkep.com.tr/kepappteam/kep-ik/webik-frontend-v2] on branch [dev|https://git-lab.turkkep.com.tr/kepappteam/kep-ik/webik-frontend-v2/-/tree/dev]:{quote}Merge branch 'WIK-827' into 'dev' wik 827 duyuru gönderi popupu cc kaldırıldı v2 Closes WIK-827 See merge request kepappteam/kep-ik/webik-frontend-v2!220{quote} | DS25: 16/Mar/26 2:27 PM;gurkan.guney;Test ortamda yapılan kontroller başarılı.
A26: Kep Delil Raporu/ Pasif Kullanıcıların Listelenmesi ve Rapor Oluşturulabilmesi | B26: WIK-826 | C26: 23100 | E26: Story | F26: Done | G26: WIK | H26: KEP İK Bulut | I26: software | J26: ceren.sertkaya | L26: https://kep-ik.turkkep.com.tr/ | M26: Medium | N26: Verified | O26: gurkan.guney | P26: gulnur.aka | Q26: gulnur.aka | R26: 46085.48 | S26: 46091.699 | T26: 46100.369 | U26: 46090.565 | Y26: 0 | AA26: *Açıklama:*_x000D_ _x000D_ Mevcut durumda Kep Delil Raporu ekranında kullanıcı “Rapor Talebi Oluştur” seçeneğini kullandığında, çalışan listesinde yalnızca aktif kullanıcılar listelenmektedir. Pasif kullanıcılar için delil raporu oluşturulamamaktadır._x000D_ _x000D_ Geliştirme yapılması beklenen ekran: [https://testik.turkkep.com.tr/archive/evidence]_x000D_ _x000D_ *Beklenen Durum:*_x000D_ * Çalışan listesinde pasif kullanıcılar da görüntülenmelidir._x000D_ _x000D_ * Pasif kullanıcılar seçilebilir olmalıdır._x000D_ _x000D_ * Pasif kullanıcılara ait delil raporu sistem tarafından oluşturulabilmelidir._x000D_ _x000D_ Kabul Kriteleri:_x000D_ # Çalışan listesinde pasif kullanıcılar görüntülenmelidir._x000D_ # Pasif kullanıcı seçilerek rapor talebi oluşturulabilmelidir._x000D_ # Pasif kullanıcı için delil raporu başarıyla oluşturulmalıdır._x000D_ # Mevcut aktif kullanıcı akışında herhangi bir davranış farklılığı olmamalıdır._x000D_ _x000D_ | AC26: gitlab.dev | AD26: gulnur.aka | AE26: gurkan.guney | AH26: ;09/Mar/26 12:55 PM;dogukan.oncuer;1200 | AI26: Test ortamda yapılan kontroller başarılı.;09/Mar/26 1:33 PM;gurkan.guney;300 | BQ26: 0 | BR26: 1500 | BU26: 0 | BV26: 1500 | BZ26: 04/Mar/26 11:32 AM;gulnur.aka;screenshot-1.png;http://192.168.124.186:8080/secure/attachment/15964/screenshot-1.png | CT26: 0|i00vra:zsyzgznqma | CU26: WIK Sprint 2026/ 11-12 | DI26: 20 | DL26: 04/Mar/26 11:35 AM;gulnur.aka;Geliştirmenin isterleri tamamlanmıştır. Teknik analize başlanabilir. [~ceren.sertkaya]_x000D_ _x000D_ | DM26: 09/Mar/26 12:40 PM;gitlab.dev;[Dogukan Oncuer|https://git-lab.turkkep.com.tr/dogukan.oncuer] mentioned this issue in [commit d79fd607|https://git-lab.turkkep.com.tr/kepappteam/kep-ik/webik-frontend-v2/-/commit/d79fd607a74dd475d6fe92613b7423d531c256ac] of [KEPAPPTEAM / KEP IK / Webik Frontend V2|https://git-lab.turkkep.com.tr/kepappteam/kep-ik/webik-frontend-v2] on branch [WIK-826|https://git-lab.turkkep.com.tr/kepappteam/kep-ik/webik-frontend-v2/-/tree/WIK-826]:{quote}WIK-826 kep delil raporu olusturmada tüm statudeki calısanlar getirildi {quote} | DN26: 09/Mar/26 12:44 PM;gitlab.dev;[Dogukan Oncuer|https://git-lab.turkkep.com.tr/dogukan.oncuer] mentioned this issue in [commit 62e45e67|https://git-lab.turkkep.com.tr/kepappteam/kep-ik/webik-frontend-v2/-/commit/62e45e6761b68f35b73b80c91890eb3de675fb45] of [KEPAPPTEAM / KEP IK / Webik Frontend V2|https://git-lab.turkkep.com.tr/kepappteam/kep-ik/webik-frontend-v2] on branch [dev|https://git-lab.turkkep.com.tr/kepappteam/kep-ik/webik-frontend-v2/-/tree/dev]:{quote}Merge branch 'WIK-826' into 'dev' WIK-826 kep delil raporu olusturmada tüm statudeki calısanlar getirildi See merge request kepappteam/kep-ik/webik-frontend-v2!210{quote} | DO26: 09/Mar/26 12:48 PM;gitlab.dev;[Dogukan Oncuer|https://git-lab.turkkep.com.tr/dogukan.oncuer] mentioned this issue in [commit aef38740|https://git-lab.turkkep.com.tr/kepappteam/kep-ik/webik-frontend-v2/-/commit/aef38740e67a5905641cc901189e41bc15af87ae] of [KEPAPPTEAM / KEP IK / Webik Frontend V2|https://git-lab.turkkep.com.tr/kepappteam/kep-ik/webik-frontend-v2] on branch [WIK-826|https://git-lab.turkkep.com.tr/kepappteam/kep-ik/webik-frontend-v2/-/tree/WIK-826]:{quote}WIK-826 kep delil raporu olusturmada calısanlar statu fix {quote} | DP26: 09/Mar/26 12:48 PM;gitlab.dev;[Dogukan Oncuer|https://git-lab.turkkep.com.tr/dogukan.oncuer] mentioned this issue in [commit 17c3178e|https://git-lab.turkkep.com.tr/kepappteam/kep-ik/webik-frontend-v2/-/commit/17c3178e24da2c3abd0da5b7b8e525d64f409e10] of [KEPAPPTEAM / KEP IK / Webik Frontend V2|https://git-lab.turkkep.com.tr/kepappteam/kep-ik/webik-frontend-v2] on branch [dev|https://git-lab.turkkep.com.tr/kepappteam/kep-ik/webik-frontend-v2/-/tree/dev]:{quote}Merge branch 'WIK-826' into 'dev' WIK-826 kep delil raporu olusturmada calısanlar statu fix Closes WIK-826 See merge request kepappteam/kep-ik/webik-frontend-v2!211{quote} | DQ26: 09/Mar/26 12:50 PM;gitlab.dev;[Dogukan Oncuer|https://git-lab.turkkep.com.tr/dogukan.oncuer] mentioned this issue in [commit ba16639b|https://git-lab.turkkep.com.tr/kepappteam/kep-ik/webik-frontend-v2/-/commit/ba16639b96aa6f5f059680be0851ce9d05a60657] of [KEPAPPTEAM / KEP IK / Webik Frontend V2|https://git-lab.turkkep.com.tr/kepappteam/kep-ik/webik-frontend-v2] on branch [test|https://git-lab.turkkep.com.tr/kepappteam/kep-ik/webik-frontend-v2/-/tree/test]:{quote}Merge branch 'dev' into 'test' WIK-826 kep delil raporu olusturmada calısanlar statu fix See merge request kepappteam/kep-ik/webik-frontend-v2!212{quote} | DR26: 09/Mar/26 12:53 PM;gitlab.dev;✅ Pipeline başarılı, WIK-826 maddesi test ortamına aktarıldı. | DS26: 09/Mar/26 1:33 PM;gurkan.guney;Test ortamda yapılan kontroller başarılı. | DT26: 10/Mar/26 4:47 PM;gitlab.dev;[Dogukan Oncuer|https://git-lab.turkkep.com.tr/dogukan.oncuer] mentioned this issue in [commit 35c4d664|https://git-lab.turkkep.com.tr/kepappteam/kep-ik/webik-frontend-v2/-/commit/35c4d664b1645da20440637cf3882e900a8ba221] of [KEPAPPTEAM / KEP IK / Webik Frontend V2|https://git-lab.turkkep.com.tr/kepappteam/kep-ik/webik-frontend-v2] on branch [dev|https://git-lab.turkkep.com.tr/kepappteam/kep-ik/webik-frontend-v2/-/tree/dev]:{quote}Merge branch 'WIK-826' into 'dev' (wik-826) popup backdrop closing fix See merge request kepappteam/kep-ik/webik-frontend-v2!213{quote}
A27: KEP İK Dönem Servisi Metotunda Mükerer Çalışan Yüklenmesi | B27: WIK-825 | C27: 23099 | E27: Bug | F27: TO TEST | G27: WIK | H27: KEP İK Bulut | I27: software | J27: ceren.sertkaya | L27: https://kep-ik.turkkep.com.tr/ | M27: Medium | O27: gurkan.guney | P27: ceren.sertkaya | Q27: ceren.sertkaya | R27: 46084.701 | S27: 46099.698 | T27: 46100.369 | Y27: 0 | AA27: [support-desk-controller|https://webik.turkkep.com.tr:8080/swagger-ui/index.html#/support-desk-controller] modülünde post missing desk metotunda aynı aya ait dönem açılışı birden fazla yapılırsa, yüklenenler listesinde çalışanlar mükerer olarak gelmektedir._x000D_ _x000D_ İşlem bir kere yapılmalıdır. Gerekli kontrol servise eklenmelidir._x000D_ _x000D_ Sadece kullanıcı yetkilendirme açık olan organizasyonlarda yaşanmaktadır. Normal organizasyonlarda çalışanı güncelleme gözükmemiştir._x000D_ _x000D_ !image-2026-03-03-17-50-10-552.png! | AC27: ceren.sertkaya | AD27: gitlab.dev | AH27: -Support Desk controllerda ki dönem güncelleme metodunda ki mükerrer kayıt oluşturma hatası, kullanıcı yönetimi olan firmalar için düzeltildi.;17/Mar/26 2:59 PM;can.macit;21600 | BQ27: 0 | BR27: 21600 | BU27: 0 | BV27: 21600 | BZ27: 03/Mar/26 4:50 PM;ceren.sertkaya;image-2026-03-03-17-50-10-552.png;http://192.168.124.186:8080/secure/attachment/15955/image-2026-03-03-17-50-10-552.png | CT27: 0|i00vra:zsyzgznqm9 | CU27: WIK Sprint 2026/ 11-12 | DI27: 30 | DL27: 17/Mar/26 2:54 PM;gitlab.dev;[Can Macit|https://git-lab.turkkep.com.tr/can.macit] mentioned this issue in [commit 1b2bbe63|https://git-lab.turkkep.com.tr/kepappteam/kep-ik/webik-backend-v2/-/commit/1b2bbe633631d6bd7ab12f4305ca31194e294568] of [KEPAPPTEAM / KEP IK / Webik Backend V2|https://git-lab.turkkep.com.tr/kepappteam/kep-ik/webik-backend-v2] on branch [dev|https://git-lab.turkkep.com.tr/kepappteam/kep-ik/webik-backend-v2/-/tree/dev]:{quote}(WIK-825) KEP IK Support Desk Dönem güncelleme metodunda ki bug düzeltildi. {quote} | DM27: 17/Mar/26 2:55 PM;gitlab.dev;[Can Macit|https://git-lab.turkkep.com.tr/can.macit] mentioned this issue in [merge request !137|https://git-lab.turkkep.com.tr/kepappteam/kep-ik/webik-backend-v2/-/merge_requests/137] of [KEPAPPTEAM / KEP IK / Webik Backend V2|https://git-lab.turkkep.com.tr/kepappteam/kep-ik/webik-backend-v2] on branch [dev|https://git-lab.turkkep.com.tr/kepappteam/kep-ik/webik-backend-v2/-/tree/dev]:{quote}(WIK-825) Test branch merge request{quote} | DN27: 17/Mar/26 2:55 PM;gitlab.dev;[Can Macit|https://git-lab.turkkep.com.tr/can.macit] mentioned this issue in [commit 339f03e9|https://git-lab.turkkep.com.tr/kepappteam/kep-ik/webik-backend-v2/-/commit/339f03e9ea9d577611da660368f244fd36091072] of [KEPAPPTEAM / KEP IK / Webik Backend V2|https://git-lab.turkkep.com.tr/kepappteam/kep-ik/webik-backend-v2] on branch [test|https://git-lab.turkkep.com.tr/kepappteam/kep-ik/webik-backend-v2/-/tree/test]:{quote}Merge branch 'dev' into 'test' (WIK-825) Test branch merge request See merge request kepappteam/kep-ik/webik-backend-v2!137{quote} | DO27: 17/Mar/26 2:56 PM;gitlab.dev;✅ Pipeline başarılı, WIK-825 maddesi test ortamına aktarıldı.
A28: Yeni Dönem/Ay Açılışında Ayın Başında Mükerrer Dönem Oluşması | B28: WIK-823 | C28: 23084 | E28: Bug | F28: Publish | G28: WIK | H28: KEP İK Bulut | I28: software | J28: ceren.sertkaya | L28: https://kep-ik.turkkep.com.tr/ | M28: Medium | O28: mehmetcan.olgun | P28: ceren.sertkaya | Q28: ceren.sertkaya | R28: 46084.406 | S28: 46093.693 | T28: 46100.369 | Y28: 0 | AA28: job saati gece 00:00 saatinde çalışmaktadır. İlgili ay açılışını sağlayan jobın gece 03:00 olarak değiştirilmesi gerekmektedir._x000D_ _x000D_ Aynı şekilde test ortamının düzenlenmesi gerekmektedir. _x000D_ _x000D_ (Şubat ayı döneminin mükerrer kayıdının test ortamından kaldırılması ve Mart ayının açılması gerekmektedir.) | AC28: ceren.sertkaya | AH28: ;12/Mar/26 4:38 PM;mehmetcan.olgun;7200 | BQ28: 0 | BR28: 7200 | BU28: 0 | BV28: 7200 | CT28: 0|i00vra:zsyzgznqk | CU28: WIK Sprint 2026/ 11-12 | DI28: 20
A29: Ek İşler Hk | B29: WIK-819 | C29: 23033 | E29: Side-Jobs | F29: Done | G29: WIK | H29: KEP İK Bulut | I29: software | J29: ceren.sertkaya | L29: https://kep-ik.turkkep.com.tr/ | M29: Medium | N29: Done | O29: ceren.sertkaya | P29: ceren.sertkaya | Q29: ceren.sertkaya | R29: 46076.379 | S29: 46090.443 | T29: 46100.369 | U29: 46090.443 | Y29: 0 | AC29: ceren.sertkaya | AH29: can ile webik test ortamı sunucuya görsel yükleme log görme toplantısı;23/Feb/26 4:35 PM;dogukan.oncuer;2400 | AI29: backlog;03/Mar/26 6:41 PM;dogukan.oncuer;5820 | AJ29: gün değerlendirme;06/Mar/26 6:16 PM;dogukan.oncuer;1020 | AK29: sprint toplantısı;06/Mar/26 6:17 PM;dogukan.oncuer;4500 | BQ29: 0 | BR29: 13740 | BU29: 0 | BV29: 13740 | CT29: 0|i00vra:zsyzgzliigb91zw | CU29: WIK Sprint 2026/ 9-10
A30: Ek İşler Hk | B30: WIK-818 | C30: 23032 | E30: Side-Jobs | F30: Done | G30: WIK | H30: KEP İK Bulut | I30: software | J30: ceren.sertkaya | L30: https://kep-ik.turkkep.com.tr/ | M30: Medium | N30: Done | O30: ceren.sertkaya | P30: ceren.sertkaya | Q30: ceren.sertkaya | R30: 46076.379 | S30: 46090.443 | T30: 46100.369 | U30: 46090.443 | Y30: 0 | AC30: ceren.sertkaya | CT30: 0|i00vra:zsyzgzliigb91zr | CU30: WIK Sprint 2026/ 9-10
A31: Ek İşler Hk | B31: WIK-817 | C31: 23031 | E31: Side-Jobs | F31: Done | G31: WIK | H31: KEP İK Bulut | I31: software | J31: ceren.sertkaya | L31: https://kep-ik.turkkep.com.tr/ | M31: Medium | N31: Done | O31: ceren.sertkaya | P31: ceren.sertkaya | Q31: ceren.sertkaya | R31: 46076.378 | S31: 46090.443 | T31: 46100.369 | U31: 46090.443 | Y31: 0 | AC31: ceren.sertkaya | CT31: 0|i00vra:zsyzgzliigb91zi | CU31: WIK Sprint 2026/ 9-10
A32: Ek İşler Hk | B32: WIK-816 | C32: 23030 | E32: Side-Jobs | F32: Done | G32: WIK | H32: KEP İK Bulut | I32: software | J32: ceren.sertkaya | L32: https://kep-ik.turkkep.com.tr/ | M32: Medium | N32: Done | O32: ceren.sertkaya | P32: ceren.sertkaya | Q32: ceren.sertkaya | R32: 46076.378 | S32: 46090.442 | T32: 46100.369 | U32: 46090.442 | Y32: 0 | AC32: ceren.sertkaya | CT32: 0|i00vra:zsyzgzliigb91z | CU32: WIK Sprint 2026/ 9-10
A33: Belge Üzerine Eklenen Doğrulama Kodu için Ölçeklendirme | B33: WIK-793 | C33: 22881 | E33: Story | F33: TO TEST | G33: WIK | H33: KEP İK Bulut | I33: software | J33: ceren.sertkaya | L33: https://kep-ik.turkkep.com.tr/ | M33: Medium | O33: ceren.sertkaya | P33: gulnur.aka | Q33: gulnur.aka | R33: 46048.394 | S33: 46097.543 | T33: 46059.717 | Y33: 0 | AA33: *Açıklama:*_x000D_ _x000D_ Sistem ayarlarında yer alan “Belge Üzerine Doğrulama Kodu Eklensin” seçeneği işaretlendiğinde, belge üzerine eklenen doğrulama kodunun sabit boyutta oluşturulduğu görülmektedir._x000D_ _x000D_ *Bu task kapsamında;*_x000D_ _x000D_ Doğrulama kodunun belge üzerine eklenmesi sırasında ölçeklendirme (boyutlandırma) yapılabilmesi gerekmektedir. Kullanıcı tarafından belirlenen oranlara göre (ör. 0.75x, 0.50x gibi) doğrulama kodunun belge üzerindeki boyutu ayarlanabilir olmalıdır._x000D_ * Doğrulama kodu görselinin belge üzerine eklenmesi sırasında ölçeklendirme desteği_x000D_ _x000D_ * Mevcuttaki gibi 0.75x ve 0.50x oranlarının desteklenmesi_x000D_ _x000D_ * Ölçeklendirme sonrası belge yerleşiminin bozulmaması_x000D_ _x000D_ * Mevcut doğrulama kodu ekleme akışıyla uyumlu çalışması_x000D_ _x000D_ *Kabul Kriterleri:*_x000D_ * Belge Üzerine Doğrulama Kodu Eklensin” checkbox’ı işaretlendiğinde doğrulama kodu belgeye eklenmelidir._x000D_ _x000D_ * Doğrulama kodu için ölçeklendirme yapılabilmelidir (0.75x, 0.50x vb.)._x000D_ _x000D_ * Ölçeklendirme sonrası doğrulama kodu okunabilirliğini korumalıdır._x000D_ _x000D_ * Belge formatı ve içeriği bozulmamalıdır._x000D_ _x000D_ Geliştirme yapılırken doğrulama adresini de değerlendirerek sürec planlanmalıdır. | AC33: gitlab.dev | AD33: gulnur.aka | AE33: gurkan.guney | AH33: ;12/Feb/26 1:28 PM;gurkan.guney;3600 | AI33: ;20/Feb/26 3:40 PM;gurkan.guney;3600 | AJ33: ;05/Mar/26 5:47 PM;gurkan.guney;1800 | BQ33: 0 | BR33: 9000 | BU33: 0 | BV33: 20400 | BZ33: 05/Mar/26 5:46 PM;gurkan.guney;0.5.pdf;http://192.168.124.186:8080/secure/attachment/15965/0.5.pdf | CA33: 05/Mar/26 5:46 PM;gurkan.guney;0.75.pdf;http://192.168.124.186:8080/secure/attachment/15969/0.75.pdf | CB33: 05/Mar/26 5:46 PM;gurkan.guney;1.1.pdf;http://192.168.124.186:8080/secure/attachment/15967/1.1.pdf | CC33: 05/Mar/26 5:46 PM;gurkan.guney;1.25.pdf;http://192.168.124.186:8080/secure/attachment/15966/1.25.pdf | CD33: 05/Mar/26 5:46 PM;gurkan.guney;1.pdf;http://192.168.124.186:8080/secure/attachment/15968/1.pdf | CE33: 06/Mar/26 3:12 PM;gurkan.guney;yukarda 1.pdf;http://192.168.124.186:8080/secure/attachment/15974/yukarda+1.pdf | CF33: 06/Mar/26 3:12 PM;gurkan.guney;yukarda 2.pdf;http://192.168.124.186:8080/secure/attachment/15975/yukarda+2.pdf | CT33: 0|i00vra:zsyzgznqmd | CU33: WIK Sprint 2026/ 5-6 | CV33: WIK Sprint 2026/ 7-8 | CW33: WIK Sprint 2026/ 9-10 | CX33: WIK Sprint 2026/ 11-12 | DI33: 30 | DL33: 06/Feb/26 5:05 PM;gitlab.dev;[Sevket Onder Bar|https://git-lab.turkkep.com.tr/onder.bar] mentioned this issue in [commit c882d06d|https://git-lab.turkkep.com.tr/kepappteam/kep-ik/webik-backend-v2/-/commit/c882d06da33011551cb84d0fedcb73da92ae076b] of [KEPAPPTEAM / KEP IK / Webik Backend V2|https://git-lab.turkkep.com.tr/kepappteam/kep-ik/webik-backend-v2] on branch [dev|https://git-lab.turkkep.com.tr/kepappteam/kep-ik/webik-backend-v2/-/tree/dev]:{quote}(WIK-793) Belge üzerinde doğrulama kodu servis geliştirmesi tamamlandı. {quote} | DM33: 06/Feb/26 5:09 PM;gitlab.dev;[Sevket Onder Bar|https://git-lab.turkkep.com.tr/onder.bar] mentioned this issue in [merge request !129|https://git-lab.turkkep.com.tr/kepappteam/kep-ik/webik-backend-v2/-/merge_requests/129] of [KEPAPPTEAM / KEP IK / Webik Backend V2|https://git-lab.turkkep.com.tr/kepappteam/kep-ik/webik-backend-v2] on branch [dev|https://git-lab.turkkep.com.tr/kepappteam/kep-ik/webik-backend-v2/-/tree/dev]:{quote}(WIK-793) Test branch merge request{quote} | DN33: 06/Feb/26 5:10 PM;gitlab.dev;[Sevket Onder Bar|https://git-lab.turkkep.com.tr/onder.bar] mentioned this issue in [commit b8139c62|https://git-lab.turkkep.com.tr/kepappteam/kep-ik/webik-backend-v2/-/commit/b8139c6203402c7094368ee21c269f222755b6f1] of [KEPAPPTEAM / KEP IK / Webik Backend V2|https://git-lab.turkkep.com.tr/kepappteam/kep-ik/webik-backend-v2] on branch [test|https://git-lab.turkkep.com.tr/kepappteam/kep-ik/webik-backend-v2/-/tree/test]:{quote}Merge branch 'dev' into 'test' (WIK-793) Test branch merge request See merge request kepappteam/kep-ik/webik-backend-v2!129{quote} | DO33: 06/Feb/26 5:11 PM;gitlab.dev;✅ Pipeline başarılı, WIK-793 maddesi test ortamına aktarıldı. | DP33: 12/Feb/26 1:27 PM;gurkan.guney;Doğrulama Kodunun boyutlara göre pdf çıktıları ektedir._x000D_ _x000D_ 1- 0.5x olduğunda "Doğrulama Adresi : https://testik.turkkep.com.tr/Verification" metni tam ortalanmıyor. Sol tarafa yakın kalıyor. Ve bu yazı çok küçük kalıyor. Okunamıyor._x000D_ _x000D_ 2- 0.75x olduğunda "Doğrulama Adresi : https://testik.turkkep.com.tr/Verification" metni tam ortalanmıyor. Sol tarafa yakın kalıyor._x000D_ _x000D_ 3- 1.1x olduğunda "Bu Belge, 5070 Sayılı Elektronik İmza Kanunu'na Göre Güvenli Elektronik İmza İle İmzalanmıştır." metni pdf'e sığmıyor. İmzalanmıştı olarak görünüyor. Sistem ayarları sayfasında doğru görünmesine rağmen imzalı pdf'te bir kısmı görünmüyor._x000D_ _x000D_ 4- 1.25x olduğunda "Bu Belge, 5070 Sayılı Elektronik İmza Kanunu'na Göre Güvenli Elektronik İmza İle İmzalanmıştır." metni ve Doğrulama Adresi pdf'e sığmıyor. Sistem ayarları sayfasında doğru görünmesine rağmen imzalı pdf'te bir kısmı görünmüyor. | DQ33: 19/Feb/26 9:34 AM;gitlab.dev;[Sevket Onder Bar|https://git-lab.turkkep.com.tr/onder.bar] mentioned this issue in [commit 007c6535|https://git-lab.turkkep.com.tr/kepappteam/kep-ik/webik-backend-v2/-/commit/007c6535f31ef97e6d04de110a360358a9b58251] of [KEPAPPTEAM / KEP IK / Webik Backend V2|https://git-lab.turkkep.com.tr/kepappteam/kep-ik/webik-backend-v2] on branch [dev|https://git-lab.turkkep.com.tr/kepappteam/kep-ik/webik-backend-v2/-/tree/dev]:{quote}(WIK-793) Doğrulama kodu hotfix {quote} | DR33: 19/Feb/26 9:40 AM;gitlab.dev;[Sevket Onder Bar|https://git-lab.turkkep.com.tr/onder.bar] mentioned this issue in [merge request !132|https://git-lab.turkkep.com.tr/kepappteam/kep-ik/webik-backend-v2/-/merge_requests/132] of [KEPAPPTEAM / KEP IK / Webik Backend V2|https://git-lab.turkkep.com.tr/kepappteam/kep-ik/webik-backend-v2] on branch [dev|https://git-lab.turkkep.com.tr/kepappteam/kep-ik/webik-backend-v2/-/tree/dev]:{quote}(WIK-793) Test branch merge request{quote} | DS33: 19/Feb/26 9:40 AM;gitlab.dev;[Sevket Onder Bar|https://git-lab.turkkep.com.tr/onder.bar] mentioned this issue in [commit 59a3ebed|https://git-lab.turkkep.com.tr/kepappteam/kep-ik/webik-backend-v2/-/commit/59a3ebed8a4194cc546f3d04e926e0ee334085c4] of [KEPAPPTEAM / KEP IK / Webik Backend V2|https://git-lab.turkkep.com.tr/kepappteam/kep-ik/webik-backend-v2] on branch [test|https://git-lab.turkkep.com.tr/kepappteam/kep-ik/webik-backend-v2/-/tree/test]:{quote}Merge branch 'dev' into 'test' (WIK-793) Test branch merge request See merge request kepappteam/kep-ik/webik-backend-v2!132{quote} | DT33: 19/Feb/26 9:41 AM;gitlab.dev;✅ Pipeline başarılı, WIK-793 maddesi test ortamına aktarıldı. | DU33: 19/Feb/26 3:32 PM;gitlab.dev;[Sevket Onder Bar|https://git-lab.turkkep.com.tr/onder.bar] mentioned this issue in [commit 52ca620a|https://git-lab.turkkep.com.tr/kepappteam/kep-ik/webik-backend-v2/-/commit/52ca620a002f7135661c8f7dffc96267a4163bb5] of [KEPAPPTEAM / KEP IK / Webik Backend V2|https://git-lab.turkkep.com.tr/kepappteam/kep-ik/webik-backend-v2] on branch [dev|https://git-lab.turkkep.com.tr/kepappteam/kep-ik/webik-backend-v2/-/tree/dev]:{quote}(WIK-793) Doğrulama kodu hotfix v2 {quote} | DV33: 19/Feb/26 3:34 PM;gitlab.dev;[Sevket Onder Bar|https://git-lab.turkkep.com.tr/onder.bar] mentioned this issue in [merge request !133|https://git-lab.turkkep.com.tr/kepappteam/kep-ik/webik-backend-v2/-/merge_requests/133] of [KEPAPPTEAM / KEP IK / Webik Backend V2|https://git-lab.turkkep.com.tr/kepappteam/kep-ik/webik-backend-v2] on branch [dev|https://git-lab.turkkep.com.tr/kepappteam/kep-ik/webik-backend-v2/-/tree/dev]:{quote}(WIK-793) Sign text hotfix v2{quote} | DW33: 19/Feb/26 3:34 PM;gitlab.dev;[Sevket Onder Bar|https://git-lab.turkkep.com.tr/onder.bar] mentioned this issue in [commit c6dc9a8c|https://git-lab.turkkep.com.tr/kepappteam/kep-ik/webik-backend-v2/-/commit/c6dc9a8c6032ad8015d6793f33e3faf2abe55ad7] of [KEPAPPTEAM / KEP IK / Webik Backend V2|https://git-lab.turkkep.com.tr/kepappteam/kep-ik/webik-backend-v2] on branch [test|https://git-lab.turkkep.com.tr/kepappteam/kep-ik/webik-backend-v2/-/tree/test]:{quote}Merge branch 'dev' into 'test' (WIK-793) Sign text hotfix v2 See merge request kepappteam/kep-ik/webik-backend-v2!133{quote} | DX33: 19/Feb/26 3:35 PM;gitlab.dev;✅ Pipeline başarılı, WIK-793 maddesi test ortamına aktarıldı. | DY33: 20/Feb/26 3:40 PM;gurkan.guney;0.75x, 1x ve 1.1x boyutundaki doğrulama kodları pdf'de sol tarafa daha yakın duruyor. İlgili belgeler ektedir. | DZ33: 04/Mar/26 2:34 PM;gitlab.dev;[Sevket Onder Bar|https://git-lab.turkkep.com.tr/onder.bar] mentioned this issue in [commit 3fa7e5cf|https://git-lab.turkkep.com.tr/kepappteam/kep-ik/webik-backend-v2/-/commit/3fa7e5cf8cd1a150efe99f1e70def496e93ede65] of [KEPAPPTEAM / KEP IK / Webik Backend V2|https://git-lab.turkkep.com.tr/kepappteam/kep-ik/webik-backend-v2] on branch [dev|https://git-lab.turkkep.com.tr/kepappteam/kep-ik/webik-backend-v2/-/tree/dev]:{quote}(WIK-793) Doğrulama kodu X konumu dinamikleştirildi. {quote} | EA33: 04/Mar/26 2:39 PM;gitlab.dev;[Sevket Onder Bar|https://git-lab.turkkep.com.tr/onder.bar] mentioned this issue in [merge request !135|https://git-lab.turkkep.com.tr/kepappteam/kep-ik/webik-backend-v2/-/merge_requests/135] of [KEPAPPTEAM / KEP IK / Webik Backend V2|https://git-lab.turkkep.com.tr/kepappteam/kep-ik/webik-backend-v2] on branch [dev|https://git-lab.turkkep.com.tr/kepappteam/kep-ik/webik-backend-v2/-/tree/dev]:{quote}(WIK-793) Verification text has been made dynamic{quote} | EB33: 04/Mar/26 2:39 PM;gitlab.dev;[Sevket Onder Bar|https://git-lab.turkkep.com.tr/onder.bar] mentioned this issue in [commit 90a0503a|https://git-lab.turkkep.com.tr/kepappteam/kep-ik/webik-backend-v2/-/commit/90a0503a67b159bca58e9aaf5c01aaccc64c0729] of [KEPAPPTEAM / KEP IK / Webik Backend V2|https://git-lab.turkkep.com.tr/kepappteam/kep-ik/webik-backend-v2] on branch [test|https://git-lab.turkkep.com.tr/kepappteam/kep-ik/webik-backend-v2/-/tree/test]:{quote}Merge branch 'dev' into 'test' (WIK-793) Verification text has been made dynamic See merge request kepappteam/kep-ik/webik-backend-v2!135{quote} | EC33: 04/Mar/26 2:40 PM;gitlab.dev;✅ Pipeline başarılı, WIK-793 maddesi test ortamına aktarıldı. | ED33: 05/Mar/26 3:13 PM;gitlab.dev;[Sevket Onder Bar|https://git-lab.turkkep.com.tr/onder.bar] mentioned this issue in [commit 04a192a4|https://git-lab.turkkep.com.tr/kepappteam/kep-ik/webik-backend-v2/-/commit/04a192a490aaed5aea536d812883010b77fb60b0] of [KEPAPPTEAM / KEP IK / Webik Backend V2|https://git-lab.turkkep.com.tr/kepappteam/kep-ik/webik-backend-v2] on branch [dev|https://git-lab.turkkep.com.tr/kepappteam/kep-ik/webik-backend-v2/-/tree/dev]:{quote}(WIK-793) Doğrula metni v3 {quote} | EE33: 05/Mar/26 3:16 PM;gitlab.dev;[Sevket Onder Bar|https://git-lab.turkkep.com.tr/onder.bar] mentioned this issue in [merge request !136|https://git-lab.turkkep.com.tr/kepappteam/kep-ik/webik-backend-v2/-/merge_requests/136] of [KEPAPPTEAM / KEP IK / Webik Backend V2|https://git-lab.turkkep.com.tr/kepappteam/kep-ik/webik-backend-v2] on branch [dev|https://git-lab.turkkep.com.tr/kepappteam/kep-ik/webik-backend-v2/-/tree/dev]:{quote}(WIK-793) Verification text has been made static{quote} | EF33: 05/Mar/26 3:16 PM;gitlab.dev;[Sevket Onder Bar|https://git-lab.turkkep.com.tr/onder.bar] mentioned this issue in [commit b2058f2a|https://git-lab.turkkep.com.tr/kepappteam/kep-ik/webik-backend-v2/-/commit/b2058f2a9ca786b891e5300f0ec8adaf4ebd8259] of [KEPAPPTEAM / KEP IK / Webik Backend V2|https://git-lab.turkkep.com.tr/kepappteam/kep-ik/webik-backend-v2] on branch [test|https://git-lab.turkkep.com.tr/kepappteam/kep-ik/webik-backend-v2/-/tree/test]:{quote}Merge branch 'dev' into 'test' (WIK-793) Verification text has been made static See merge request kepappteam/kep-ik/webik-backend-v2!136{quote} | EG33: 05/Mar/26 3:17 PM;gitlab.dev;✅ Pipeline başarılı, WIK-793 maddesi test ortamına aktarıldı. | EH33: 05/Mar/26 5:47 PM;gurkan.guney;Test ortamda imzalı belgelerdeki doğrulama kodu ölçeklendirme ve konumlandırma örnekleri son halleri ekteki gibidir. _x000D_ _x000D_ Sistem ayarları sayfasında doğrulama kodu en üstte konulduğunda imzalı belgelerde görsel kesik görünüyor. Ekte örnekler mevcuttur. (yukarda 1, yukarda 2)_x000D_ _x000D_ [~ceren.sertkaya] kabul edilebilirliğini teyitleşebilir misiniz?
A34: Duyurunun Birden Fazla Çalışana Bağlanabilmesi | B34: WIK-792 | C34: 22880 | E34: Story | F34: To Do | G34: WIK | H34: KEP İK Bulut | I34: software | J34: ceren.sertkaya | L34: https://kep-ik.turkkep.com.tr/ | M34: Medium | O34: mehmetcan.olgun | P34: gulnur.aka | Q34: gulnur.aka | R34: 46048.384 | S34: 46098.674 | T34: 46100.369 | Y34: 0 | AA34: *Açıklama:*_x000D_ _x000D_ Bu geliştirmeyle beraber fuyurular, çalışan grupları üzerinden ilişkilendirilmelidir._x000D_ _x000D_ Yeni geliştirilen duyuru gönderim ekranı ile birlikte kullanıcı;_x000D_ * Bir veya birden fazla çalışan grubunu seçebilmelidir,_x000D_ _x000D_ * Seçilen gruplara ek olarak, bu gruplarda yer almayan çalışanları da manuel olarak seçebilmelidir._x000D_ _x000D_ *Bu kapsamda;*_x000D_ * Bir duyurunun tek bir çalışana değil, birden fazla çalışana doğrudan bağlanabilmesi gerekmektedir._x000D_ _x000D_ * Grup seçimi yapılmadan yalnızca çalışan seçimiyle de duyuru gönderilebilmelidir._x000D_ _x000D_ * Grup seçimi + manuel çalışan seçimi birlikte kullanılabilmelidir._x000D_ _x000D_ * Aynı çalışanın hem grup hem manuel seçim yoluyla eklenmesi durumunda mükerrer kayıt oluşmamalıdır._x000D_ _x000D_ | AC34: gulnur.aka | CT34: 0|i00vra:zsyzgznqmer | CU34: WIK Sprint 2026/ 9-10 | CV34: WIK Sprint 2026/ 11-12 | DL34: 09/Feb/26 2:55 PM;gulnur.aka;Task içeriği güncellenmiştir. [~ceren.sertkaya] [~mehmetcan.olgun]
A35: Duyuru Modülünde Çoklu Grup Seçimi ve Grup Dışı Çalışanları Ekleme Özelliği | B35: WIK-791 | C35: 22879 | E35: Story | F35: Development | G35: WIK | H35: KEP İK Bulut | I35: software | J35: ceren.sertkaya | L35: https://kep-ik.turkkep.com.tr/ | M35: Medium | O35: mehmetcan.olgun | P35: gulnur.aka | Q35: gulnur.aka | R35: 46048.376 | S35: 46093.479 | T35: 46100.369 | Y35: 0 | AA35: *Açıklama:*_x000D_ _x000D_ Duyuru modülünde gönderim aşamasında mevcutta tekil grup seçimi yapılabilmektedir. Bu yapı, kullanıcıların duyuruları daha esnek bir yapı kurulması amaçlanmıştır. _x000D_ * Kullanıcı, duyuru gönderim ekranında birden fazla grup seçimi yapabilmelidir._x000D_ _x000D_ * Kullanıcı bir veya birden fazla grup seçmiş olsa dahi, sistem seçilen gruplarda yer almayan çalışanları da çalışan listesinde göstermelidir ve seçim yapılabilmelidir. _x000D_ _x000D_ *Gereksinim:*_x000D_ _x000D_ _*Çoklu Grup Seçimi*_ _x000D_ * Kullanıcı duyuru gönderiminde birde fazla grup seçimi yapabilmelidir. _x000D_ * Seçilen gruplar arayüzde gösterilmelidir. _x000D_ * Grup ekleme/çıkarma işlemleri mevcutta gibi yapılabilir olmalıdır. _x000D_ _x000D_ _*Grup Dışı Kullanıcı Seçimi*__x000D_ * Bir veya birden fazla grup seçildikten sonra, sistem otomatik olarak *seçilen gruplarda yer almayan çalışanları* çalışanlar listesinde listelemelidir._x000D_ * Kullanıcı bu listeden ek alıcılar seçebilmelidir_x000D_ * Hem grup üyeleri hem de manuel seçilen kullanıcılar duyuruyu almalıdır._x000D_ _x000D_ Bu sayede duyurular hem grup bazlı hem de çalışan listesinden kullanıcılar eklenerek gönderilebilecektir._x000D_ _x000D_ *Kullanım Senaryosu:*_x000D_ * Kullanıcı "Satış Departmanı" ve "Pazarlama Departmanı" grubunu seçer. _x000D_ * Sistem, seç butonuna tıklayarak açılan çalışan listesinde, bu iki grupta olmayan tüm çalışanları listeler. _x000D_ * Kullanıcı listeden Ali ve Ayşeyi seçer. (Ali IT çalışan grubunda, Ayse ise herhangi bir çalışan grubuna bağlı değildir.)_x000D_ * Duyuru, satış pazarlama ve Ali ve Ayşe'ye gönderilir. _x000D_ _x000D_ *Kabul Kriterleri:*_x000D_ * Duyuru gönderim ekranında birden fazla grup seçimi yapılabilmelidir._x000D_ _x000D_ * Grup seçimi yapıldığında çalışan listesi sadece grup üyeleriyle kısıtlanmamalıdır._x000D_ _x000D_ * Grup dışı çalışanlar listede görünmeli ve seçilebilir olmalıdır._x000D_ _x000D_ * Seçilen grup ve çalışanlar duyuruya doğru şekilde dahil edilmelidir._x000D_ _x000D_ * Mevcut duyuru gönderim akışı bozulmamalıdır._x000D_ _x000D_ *ANALİZ*_x000D_ _x000D_ Grup seçimi yapan kullanıcı grup seç adımında birden fazla grup seçtiğinde_x000D_ _x000D_ Bu fonksiyon standart seçimde şu şekilde ilerlemektedir. Kişi seçip, daha sonra grup seçilebilmektedir. Ancak ilk seçtiğim kişi grup seçtiğimde geçersiz kılınmaktadır._x000D_ Sadece grup seçtiğimde kişi seçim tuşu seçilememektedir._x000D_ _x000D_ Fonksiyon iki aşamalı çalışabilmelidir. Kişi seçimi önce veya sonra yapabilir. Grup seçimi önce veya sonra yapışabilmektedir._x000D_ _x000D_ Mükerer Seçimler Engellenmelidir._x000D_ - Seçilen gruplarda aynı kişiler olabilir. Bu noktada aynı kişiler gelmemelidir._x000D_ - Grup seçilip çalışanlar sekmesine gelirse çalışanlar sekmesindeki kişi seçili olduğu için pasif olmalıdır._x000D_ _x000D_ Seçilen grup ve kişiler listesi ayrı ayrı gösterilmelidir. _x000D_ Kişi grup bilgisini sildiği zaman çalışan listesinden aynı çalışanlar tekrar seçilebilmelidir._x000D_ _x000D_ _x000D_ _x000D_ Çalışan grubu seçimi sağlanarak,çalışan seçimine gelindiğinde ek-1 deki görseldeki gibi grup içinde çalışanlar pasif görülmeli. Kişi çalışanın üzerine geldiğinde görseldeki şekilde tooltip açılmalıdır._x000D_ _x000D_ | AC35: ceren.sertkaya | AD35: gulnur.aka | BY35: WIK-792 | BZ35: 12/Mar/26 11:29 AM;ceren.sertkaya;Çalışan grubu secimi ek-1.jfif;http://192.168.124.186:8080/secure/attachment/16042/%C3%87al%C4%B1%C5%9Fan+grubu+secimi+ek-1.jfif | CT35: 0|i00vra:zsyzgznqmei | CU35: WIK Sprint 2026/ 7-8 | CV35: WIK Sprint 2026/ 9-10 | CW35: WIK Sprint 2026/ 11-12 | DI35: 30 | DL35: 12/Feb/26 1:33 PM;ceren.sertkaya;tekrar test eder misin?
A36: API v2.4 POC'un İncelemesi ve Olası Değişiklik Senaryolarının Değerlendirilmesi | B36: WIK-783 | C36: 22780 | E36: Story | F36: To Do | G36: WIK | H36: KEP İK Bulut | I36: software | J36: ceren.sertkaya | L36: https://kep-ik.turkkep.com.tr/ | M36: Medium | O36: mehmetcan.olgun | P36: gulnur.aka | Q36: gulnur.aka | R36: 46031.006 | S36: 46090.442 | T36: 46100.369 | Y36: 0 | AA36: *Amaç:*_x000D_ _x000D_ TÜBİTAK ücretli sürümü kapsamında sunulan API v2.4 POC’nin mevcut durumunun detaylı olarak analiz edilmesi ve olası bir paket değişikliğinin sistemimiz üzerindeki etkilerinin değerlendirilmesi amaçlanmaktadır._x000D_ _x000D_ Bu kapsamda;_x000D_ * Olası versiyon değişikliklerinin sistemin üzerindeki etkilerinin belirlenmesi,_x000D_ _x000D_ * Sistemimiz açısından riskli alanların ve bağımlılıkların tespit edilmesi,_x000D_ _x000D_ * İlgili API v2.4 POC paketinin teknik açıdan test edilmesi,_x000D_ _x000D_ * Canlı geçişinde ortaya çıkabilecek potansiyel sorunların önceden öngörülmesi,_x000D_ _x000D_ * TÜBİTAK kaynaklı olarak daha önce karşılaşılan veya karşılaşılması muhtemel durumların tespit edilmesi_x000D_ _x000D_ hedeflenmektedir._x000D_ * Türkkep _x000D_ _x000D_ _x000D_ _x000D_ JAVA için; +[https://safirdepo.b3lab.org/baglanti-paylasimi/PuZ9v3tf3gFnKqspiITEJbs9W9Tqavkh]+_x000D_ .NET için; +[https://safirdepo.b3lab.org/baglanti-paylasimi/FJa2kpVHvWiEMBk4tw1n5fLE0RIK8Zqc]+ | AC36: gulnur.aka | BY36: TIM-456 | BZ36: 09/Jan/26 12:10 AM;gulnur.aka;TURKKEP.zip;http://192.168.124.186:8080/secure/attachment/15817/TURKKEP.zip | CM36: KEP-314 | CT36: 0|i00vra:zsyzgznqme | CU36: WIK Sprint 2026/ 3-4 | CV36: WIK Sprint 2026/ 5-6 | CW36: WIK Sprint 2026/ 7-8 | CX36: WIK Sprint 2026/ 9-10 | CY36: WIK Sprint 2026/ 11-12 | DL36: 09/Jan/26 1:30 PM;gulnur.aka;Çalışma sprint dışında yer alan işlerde uygunluk kaldığında bakılarak ilerlenecektir. Bundan dolayı birden fazla sprintte tamamlanması beklenmektedir.
A37: IKENTEGRATORBIREYSEL- Ön Başvuru Süreç Linkinde Firma Bilgilerinin Gösterimi | B37: UKDS-229 | C37: 23181 | E37: Story | F37: To Do | G37: UKDS | H37: Uzaktan Kimlik Doğrulama Sistemi | I37: software | J37: ceren.sertkaya | M37: Medium | O37: can.macit | P37: gulnur.aka | Q37: gulnur.aka | R37: 46098.485 | S37: 46098.6 | T37: 46100.369 | Y37: 0 | AA37: *Açıklama:*_x000D_ _x000D_ İK modülünde bireysel ve kurumsal entegratör tiplerinde, çalışana giden ön başvuru süreç linki içeriklerinde, başvuruyu oluşturan firmanın bilgileri Türkkep İK süreçlerindeki uygulama gibi kullanıcıya görünür olmalıdır._x000D_ _x000D_ Geliştirme sadece mail kısmında yapılması beklenmektedir._x000D_ _x000D_ *Amaç:* Çalışanın, başvuru sırasında hangi firma tarafından süreç başlatıldığını net şekilde görebilmesini sağlamak._x000D_ _x000D_ *Mevcut İk Gönderimlerindeki İçerik:*_x000D_ _x000D_ Firmanız TÜRKKEP KAYITLI ELEKTRONİK POSTA HİZMETLERİ SANAYİ VE TİCARET ANONİM ŞİRKETİ tarafından adınıza yapılan KEP hesap başvurusu sistemimize tanımlanmıştır._x000D_ Aşağıdaki link üzerinden ön başvurunuzu tamamlayabilirsiniz._x000D_ _x000D_ [https://basvuruonay.turkkep.com.tr/login/oC3CoZI40Qtnbmk37yEgMA==]_x000D_ _x000D_ Detaylı bilgi için firmanızın idari işler ya da insan kaynakları birimleriyle iletişime geçebilirsiniz. _x000D_ _x000D_ Ekler kısmında dataassist gibi IKENTEGRATORBIREYSEL tipdeki çalışanlara giden içerik yer almaktadır. _x000D_ _x000D_ | AC37: gulnur.aka | BZ37: 17/Mar/26 11:38 AM;gulnur.aka;image-2026-03-17-12-38-21-042.png;http://192.168.124.186:8080/secure/attachment/16063/image-2026-03-17-12-38-21-042.png | CT37: 0|i01brq:xqw | CU37: UKDS Sprint 2026/13-14 | DI37: 30
A38: Kampanya Başvuru Sayfası Cep Telefonu Numarası Girişi | B38: UKDS-228 | C38: 23143 | E38: Bug | F38: To Do | G38: UKDS | H38: Uzaktan Kimlik Doğrulama Sistemi | I38: software | J38: ceren.sertkaya | M38: Medium | O38: can.macit | P38: ceren.sertkaya | Q38: ceren.sertkaya | R38: 46091.596 | S38: 46098.598 | T38: 46100.369 | Y38: 0 | AA38: Cep numarası parametresi alanına el ile sayı hariç bir karakter girişi sağlanmıyor._x000D_ _x000D_ Ancak kopyala yapıştır ile harflerden oluşan karaktere giriş izin verilmektedir._x000D_ _x000D_ Yapıştırma sonrası alanın değerini kontrol edip, rakam dışındaki karakterleri otomatik olarak temizlenebilir._x000D_ _x000D_ _x000D_ _x000D_ _x000D_ _x000D_ Bu tür harflerden oluşan veya harf sayı karışık bir veri yapıştırılırsa yapıştırılan veri sonucunda kullanıcıya ''Cep telefonu numaranızı başında 0 olmadan girmeniz gerekmektedir. Lütfen girdiğiniz bilgileri kontrol ediniz.'' şeklinde uyarı verebiliriz._x000D_ _x000D_ _x000D_ _x000D_ !image-2026-03-10-15-18-10-005.png!_x000D_ _x000D_ | AC38: ceren.sertkaya | BZ38: 10/Mar/26 2:18 PM;ceren.sertkaya;image-2026-03-10-15-18-10-005.png;http://192.168.124.186:8080/secure/attachment/16014/image-2026-03-10-15-18-10-005.png | CT38: 0|i01brq:xqr | CU38: UKDS Sprint 2026/13-14 | DI38: 20
A39: Ek İşler Hk | B39: UKDS-227 | C39: 23131 | E39: Side-Jobs | F39: To Do | G39: UKDS | H39: Uzaktan Kimlik Doğrulama Sistemi | I39: software | J39: ceren.sertkaya | M39: Medium | O39: can.macit | P39: ceren.sertkaya | Q39: ceren.sertkaya | R39: 46090.448 | S39: 46090.449 | T39: 46100.369 | Y39: 0 | AC39: ceren.sertkaya | CT39: 0|i00vra:zsyzgzno9y | CU39: UKDS Sprint 2026/10-11
A40: Paket Seçimi için Paket Bilgisinin Çağrılacağı Get Metotu | B40: UKDS-226 | C40: 23105 | E40: Story | F40: Done | G40: UKDS | H40: Uzaktan Kimlik Doğrulama Sistemi | I40: software | J40: ceren.sertkaya | M40: Medium | N40: Verified | O40: gurkan.guney | P40: ceren.sertkaya | Q40: ceren.sertkaya | R40: 46086.656 | S40: 46099.547 | T40: 46100.369 | U40: 46090.736 | V40: UKDS 02.05 | Y40: 0 | AA40: Müşteri paket seçimi yapabilmesi için,paket bilgilerini edinme ihtiyacı bulunmaktadır._x000D_ _x000D_ Paket bilgileri seçmeden önce hangi paketlerini seçeceğinin bilgisini çağıracağı metot eklenecektir._x000D_ _x000D_ Eğer paket bilgisi seçilmezse paket bilgisi ''HEPSİ'' olarak değerlendirilecektir. | AC40: ceren.sertkaya | AD40: gitlab.dev | AE40: gurkan.guney | AH40: -Paket listesi getirme için gerekli metod UKDS Entegrasyon servisine eklendi.;06/Mar/26 1:07 PM;can.macit;18000 | AI40: Test ortamda yapılan kontroller başarılı.;09/Mar/26 5:40 PM;gurkan.guney;7200 | BQ40: 0 | BR40: 25200 | BU40: 0 | BV40: 25200 | CM40: UKDS-218 | CT40: 0|i00vra:zsyzgzno9v | CU40: UKDS Sprint 2026/9-10 | CV40: UKDS Sprint 2026/10-11 | DI40: 30 | DL40: 06/Mar/26 1:05 PM;gitlab.dev;[Can Macit|https://git-lab.turkkep.com.tr/can.macit] mentioned this issue in [commit 4828f9bb|https://git-lab.turkkep.com.tr/kepappteam/ukds/Turkkep-UKDS/-/commit/4828f9bbb0b3ec2e3c099382dfdd8c260614c1c7] of [KEPAPPTEAM / UKDS / Turkkep UKDS|https://git-lab.turkkep.com.tr/kepappteam/ukds/Turkkep-UKDS] on branch [dev|https://git-lab.turkkep.com.tr/kepappteam/ukds/Turkkep-UKDS/-/tree/dev]:{quote}(UKDS-226) Paket listesi getirme için gerekli metod geliştirmesi ana serviste tamamlandı. {quote} | DM40: 06/Mar/26 1:05 PM;gitlab.dev;[Can Macit|https://git-lab.turkkep.com.tr/can.macit] mentioned this issue in [commit 50ccd975|https://git-lab.turkkep.com.tr/kepappteam/ukds/turkkep-ukds-integration-service/-/commit/50ccd97582130285d893437909b07ab5ace9d3b4] of [KEPAPPTEAM / UKDS / TURKKEP UKDS Integration Service|https://git-lab.turkkep.com.tr/kepappteam/ukds/turkkep-ukds-integration-service] on branch [dev|https://git-lab.turkkep.com.tr/kepappteam/ukds/turkkep-ukds-integration-service/-/tree/dev]:{quote}(UKDS-226) Paket listesi getirme için gerekli metod geliştirmesi entegrasyon serviste tamamlandı. {quote} | DN40: 06/Mar/26 2:13 PM;gitlab.dev;[Can Macit|https://git-lab.turkkep.com.tr/can.macit] mentioned this issue in [merge request !120|https://git-lab.turkkep.com.tr/kepappteam/ukds/Turkkep-UKDS/-/merge_requests/120] of [KEPAPPTEAM / UKDS / Turkkep UKDS|https://git-lab.turkkep.com.tr/kepappteam/ukds/Turkkep-UKDS] on branch [dev|https://git-lab.turkkep.com.tr/kepappteam/ukds/Turkkep-UKDS/-/tree/dev]:{quote}(UKDS-215)(UKDS-220)(UKDS-223)(UKDS-226) Test branch merge request{quote} | DO40: 06/Mar/26 2:13 PM;gitlab.dev;[Can Macit|https://git-lab.turkkep.com.tr/can.macit] mentioned this issue in [commit 35528aff|https://git-lab.turkkep.com.tr/kepappteam/ukds/Turkkep-UKDS/-/commit/35528affde1b56a70b2846fcee2b6661a8678c8b] of [KEPAPPTEAM / UKDS / Turkkep UKDS|https://git-lab.turkkep.com.tr/kepappteam/ukds/Turkkep-UKDS] on branch [test|https://git-lab.turkkep.com.tr/kepappteam/ukds/Turkkep-UKDS/-/tree/test]:{quote}Merge branch 'dev' into 'test' (UKDS-215)(UKDS-220)(UKDS-223)(UKDS-226) Test branch merge request See merge request kepappteam/ukds/Turkkep-UKDS!120{quote} | DP40: 09/Mar/26 5:40 PM;gurkan.guney;Test ortamda yapılan kontroller başarılı.
A41: Ek İşler Hk | B41: UKDS-224 | C41: 23034 | E41: Side-Jobs | F41: Done | G41: UKDS | H41: Uzaktan Kimlik Doğrulama Sistemi | I41: software | J41: ceren.sertkaya | M41: Medium | N41: Done | O41: can.macit | P41: ceren.sertkaya | Q41: ceren.sertkaya | R41: 46076.381 | S41: 46090.448 | T41: 46100.369 | U41: 46090.448 | Y41: 0 | AC41: ceren.sertkaya | AH41: -Rutin uygulama logları takip edildi._x000D_ _x000D_ -Daily toplantısına katılım sağlandı._x000D_ _x000D_ ;23/Feb/26 4:28 PM;can.macit;3600 | AI41: -Rutin uygulama logları takip edildi._x000D_ _x000D_ -Daily toplantısına katılım sağlandı._x000D_ _x000D_ -UKDS tarafında sunucu kaynak kullanım takibi yapıldı. Yoğun sorgular tekrar incelendi.;24/Feb/26 4:38 PM;can.macit;7200 | AJ41: -Rutin uygulama logları takip edildi._x000D_ _x000D_ -Daily toplantısına katılım sağlandı.;25/Feb/26 4:40 PM;can.macit;3600 | AK41: -Rutin uygulama logları takip edildi.;02/Mar/26 10:51 AM;can.macit;1800 | BQ41: 0 | BR41: 16200 | BU41: 0 | BV41: 16200 | CT41: 0|i01brq:xi | CU41: UKDS Sprint 2026/9-10
A42: Özel Müşteri Seçiminde CRM rezerv metotuna id gönderilmemesi | B42: UKDS-223 | C42: 22998 | E42: Story | F42: Done | G42: UKDS | H42: Uzaktan Kimlik Doğrulama Sistemi | I42: software | J42: ceren.sertkaya | M42: Medium | N42: Verified | O42: gurkan.guney | P42: ceren.sertkaya | Q42: ceren.sertkaya | R42: 46072.633 | S42: 46099.547 | T42: 46087.728 | U42: 46094.547 | V42: UKDS 02.05 | Y42: 0 | AA42: Özel müşteri seçimi sağlanması halinde CRM'e id gönderilmeyecektir. Ayırım iki uygulama arasında bu şekilde sağlanacaktır. (Payment order id gönderilmezse) | AC42: ceren.sertkaya | AD42: gitlab.dev | AE42: gurkan.guney | AH42: -Müşteri ödemesi/Ön Ödemeli tercihine göre CRM servisine gönderilen _x000D_ eodeme_siparis_id parametresi, başvuru özelinde de parametrik hale getirildi._x000D_ ;24/Feb/26 4:37 PM;can.macit;18000 | AI42: Test UKDS servisi üzerinden yapılan kontroller başarılı.;13/Mar/26 1:08 PM;gurkan.guney;7200 | BQ42: 0 | BR42: 25200 | BU42: 0 | BV42: 25200 | CM42: UKDS-218 | CT42: 0|i00vra:zsyzgzno9ri | CU42: UKDS Sprint 2026/9-10 | CV42: UKDS Sprint 2026/10-11 | DI42: 10 | DL42: 05/Mar/26 9:51 AM;gitlab.dev;[Can Macit|https://git-lab.turkkep.com.tr/can.macit] mentioned this issue in [commit e879ec7d|https://git-lab.turkkep.com.tr/kepappteam/ukds/Turkkep-UKDS/-/commit/e879ec7d211bafc1dd06a4bc1b10fb80eba100a3] of [KEPAPPTEAM / UKDS / Turkkep UKDS|https://git-lab.turkkep.com.tr/kepappteam/ukds/Turkkep-UKDS] on branch [dev|https://git-lab.turkkep.com.tr/kepappteam/ukds/Turkkep-UKDS/-/tree/dev]:{quote}(UKDS-223) Başvuru tipleri ve bazı parametrik değerlere göre eodeme_siparis_id değerinin rezerve metodunda gönderilmesine dair geliştirme tamamlandı. {quote} | DM42: 06/Mar/26 2:13 PM;gitlab.dev;[Can Macit|https://git-lab.turkkep.com.tr/can.macit] mentioned this issue in [merge request !120|https://git-lab.turkkep.com.tr/kepappteam/ukds/Turkkep-UKDS/-/merge_requests/120] of [KEPAPPTEAM / UKDS / Turkkep UKDS|https://git-lab.turkkep.com.tr/kepappteam/ukds/Turkkep-UKDS] on branch [dev|https://git-lab.turkkep.com.tr/kepappteam/ukds/Turkkep-UKDS/-/tree/dev]:{quote}(UKDS-215)(UKDS-220)(UKDS-223)(UKDS-226) Test branch merge request{quote} | DN42: 06/Mar/26 2:13 PM;gitlab.dev;[Can Macit|https://git-lab.turkkep.com.tr/can.macit] mentioned this issue in [commit 35528aff|https://git-lab.turkkep.com.tr/kepappteam/ukds/Turkkep-UKDS/-/commit/35528affde1b56a70b2846fcee2b6661a8678c8b] of [KEPAPPTEAM / UKDS / Turkkep UKDS|https://git-lab.turkkep.com.tr/kepappteam/ukds/Turkkep-UKDS] on branch [test|https://git-lab.turkkep.com.tr/kepappteam/ukds/Turkkep-UKDS/-/tree/test]:{quote}Merge branch 'dev' into 'test' (UKDS-215)(UKDS-220)(UKDS-223)(UKDS-226) Test branch merge request See merge request kepappteam/ukds/Turkkep-UKDS!120{quote} | DO42: 13/Mar/26 1:08 PM;gurkan.guney;Test UKDS servisi üzerinden yapılan kontroller başarılı.
A43: Varsayılan olarak ‘’Ön Ödemeli’’ seçeneği tanımının gelmesi | B43: UKDS-222 | C43: 22997 | E43: Story | F43: Done | G43: UKDS | H43: Uzaktan Kimlik Doğrulama Sistemi | I43: software | J43: ceren.sertkaya | M43: Medium | N43: Verified | O43: gurkan.guney | P43: ceren.sertkaya | Q43: ceren.sertkaya | R43: 46072.633 | S43: 46099.547 | T43: 46087.728 | U43: 46091.401 | V43: UKDS 02.05 | Y43: 0 | AA43: Müşteri Ödemeli olması için müşterinin serviste ''müşteri ödemeli'' seçimini seçmesi gerekmektedir. Bu adım seçilmemesi halinde varsayılan parametre ''ön ödemelidir'' | AC43: ceren.sertkaya | AD43: gurkan.guney | AH43: -Default değer için servisler çalışmalar yapıldı.;06/Mar/26 1:06 PM;can.macit;7200 | AI43: Test UKDS servisi üzerinden yapılan kontroller başarılı._x000D_ _x000D_ Başvuru yaparken payment3d parametresi boş gönderilirse ya da hiç gönderilmezse ön ödemeli kabul ediyor. Ön başvuru sayfasında ödeme ekranı gelmiyor._x000D_ _x000D_ UKDS Raporlama servisinde "odemeDurumu": "Bu başvuru tipi için müşteri ödemesi mevcut değil", şeklinde belirtiyor.;10/Mar/26 9:38 AM;gurkan.guney;1800 | BQ43: 0 | BR43: 9000 | BU43: 0 | BV43: 9000 | CM43: UKDS-218 | CT43: 0|i00vra:zsyzgzno9u | CU43: UKDS Sprint 2026/9-10 | CV43: UKDS Sprint 2026/10-11 | DI43: 10 | DL43: 10/Mar/26 9:38 AM;gurkan.guney;Test UKDS servisi üzerinden yapılan kontroller başarılı._x000D_ _x000D_ Başvuru yaparken payment3d parametresi boş gönderilirse ya da hiç gönderilmezse ön ödemeli kabul ediyor. Ön başvuru sayfasında ödeme ekranı gelmiyor._x000D_ _x000D_ UKDS Raporlama servisinde "odemeDurumu": "Bu başvuru tipi için müşteri ödemesi mevcut değil", şeklinde belirtiyor.
A44: Yeni başvuru ekleme adımına ‘’Özel Müşteri’’ parametresinin eklemesi. | B44: UKDS-221 | C44: 22996 | E44: Story | F44: Done | G44: UKDS | H44: Uzaktan Kimlik Doğrulama Sistemi | I44: software | J44: ceren.sertkaya | M44: Medium | N44: Verified | O44: gurkan.guney | P44: ceren.sertkaya | Q44: ceren.sertkaya | R44: 46072.631 | S44: 46099.547 | T44: 46087.728 | U44: 46091.379 | V44: UKDS 02.05 | Y44: 0 | AA44: Servis içerisinde ilgili müşteri özel müşteri parametresi seçebilecektir._x000D_ _x000D_ Özel müşteri müşterinin başvuru adımını gönderdiğinde ödeme alıp alamayacağını ve buna ilişkin parametreleri ayarlayabileceği bir seçenektir._x000D_ _x000D_ Özel müşteri seçilmediği sürece ilgili kural müşteriye yansımıyıcaktır._x000D_ _x000D_ _x000D_ _x000D_ !image-2026-02-20-16-05-03-570.png! | AC44: ceren.sertkaya | AD44: gitlab.dev | AE44: gurkan.guney | AH44: -UKDS Entegrasyon servisinde ki yeni başvuru ekleme metoduna ödemeli/ödemesiz parametresi eklendi, bu tip başvurular için başvuru özelinde tanımlamalar yapıldı ve geliştirmeleri yapıldı.;25/Feb/26 4:40 PM;can.macit;21600 | AI44: -Özel müşteri parametresinin yönetime dair geliştirmeler yapıldı._x000D_ _x000D_ -Ön yüz tarafında bu parametreye göre düzenlemeler yapıldı.;02/Mar/26 10:51 AM;can.macit;28800 | AJ44: Test UKDS servisi üzerinden yapılan kontroller başarılı._x000D_ _x000D_ Başvuru yaparken payment3d parametresi true ise müşteri ödeme yapıyor. Ön başvuru formu ekranlarında da ödeme yapacağı sayfa geliyor. _x000D_ _x000D_ _x000D_ payment3d parametresi false ise müşteri ödeme yapmıyor. Ön başvuru formu ekranlarında da ödeme yapacağı alan görünmüyor._x000D_ UKDS raporlama servisinde de odemeDurumu parametresinde ödeme yapılıp yapılmayacağı, ödemesinin yapıldığı ya da henüz yapılmadığı bilgileri dönmektedir.;10/Mar/26 9:06 AM;gurkan.guney;7200 | BQ44: 0 | BR44: 57600 | BU44: 0 | BV44: 57600 | BZ44: 20/Feb/26 3:05 PM;ceren.sertkaya;image-2026-02-20-16-05-03-570.png;http://192.168.124.186:8080/secure/attachment/15917/image-2026-02-20-16-05-03-570.png | CM44: UKDS-218 | CT44: 0|i00vra:zsyzgzno9w | CU44: UKDS Sprint 2026/9-10 | CV44: UKDS Sprint 2026/10-11 | DI44: 20 | DL44: 05/Mar/26 9:49 AM;gitlab.dev;[Can Macit|https://git-lab.turkkep.com.tr/can.macit] mentioned this issue in [commit 645caf35|https://git-lab.turkkep.com.tr/kepappteam/ukds/turkkep-ukds-integration-service/-/commit/645caf35b91ed964f699e4e2946fda3f90f2aacd] of [KEPAPPTEAM / UKDS / TURKKEP UKDS Integration Service|https://git-lab.turkkep.com.tr/kepappteam/ukds/turkkep-ukds-integration-service] on branch [dev|https://git-lab.turkkep.com.tr/kepappteam/ukds/turkkep-ukds-integration-service/-/tree/dev]:{quote}(UKDS-221) Başvuru bazında ödemeli/ödemesiz geliştirmesi tamamlandıç {quote} | DM44: 10/Mar/26 9:06 AM;gurkan.guney;Test UKDS servisi üzerinden yapılan kontroller başarılı._x000D_ _x000D_ Başvuru yaparken payment3d parametresi true ise müşteri ödeme yapıyor. Ön başvuru formu ekranlarında da ödeme yapacağı sayfa geliyor. _x000D_ _x000D_ _x000D_ payment3d parametresi false ise müşteri ödeme yapmıyor. Ön başvuru formu ekranlarında da ödeme yapacağı alan görünmüyor._x000D_ UKDS raporlama servisinde de odemeDurumu parametresinde ödeme yapılıp yapılmayacağı, ödemesinin yapıldığı ya da henüz yapılmadığı bilgileri dönmektedir.
A45: Ön ödemeli/Müşteri Ödemeli seçimleri için metot güncellenmesi | B45: UKDS-220 | C45: 22995 | E45: Story | F45: Done | G45: UKDS | H45: Uzaktan Kimlik Doğrulama Sistemi | I45: software | J45: ceren.sertkaya | M45: Medium | N45: Verified | O45: gurkan.guney | P45: ceren.sertkaya | Q45: ceren.sertkaya | R45: 46072.63 | S45: 46099.547 | T45: 46087.728 | U45: 46090.762 | V45: UKDS 02.05 | Y45: 0 | AA45: Müşterinin Ön ödemeli veya Müşteri ödemeli olduğunun ayırımının sağlanacağı metotların geliştirilmesi gerekmektedir._x000D_ _x000D_ Ön ödemeli müşteri: Teklif ile gelen müşteri adımı_x000D_ _x000D_ Müşteri ödemeli gelen: Ödeme ekranlarını sunduğumuz adımdır. _x000D_ _x000D_ Bu adımların servisten seçilmesi ve tanımı için ilgili metot geliştirilecektir. | AC45: ceren.sertkaya | AD45: gitlab.dev | AE45: gurkan.guney | AH45: -UKDS Entegratör aktarma metoduna paymentType parametresi eklendi._x000D_ _x000D_ -Bu parametreye göre ödeme sayfasının yönetimi ile ilgili düzenleme geliştirmeleri yapıldı.;23/Feb/26 4:28 PM;can.macit;25200 | AI45: Test ortamda yapılan kontroller başarılı.;09/Mar/26 6:17 PM;gurkan.guney;7200 | BQ45: 0 | BR45: 32400 | BU45: 0 | BV45: 32400 | CM45: UKDS-218 | CT45: 0|i00vra:zsyzgzno9r | CU45: UKDS Sprint 2026/9-10 | CV45: UKDS Sprint 2026/10-11 | DI45: 10 | DL45: 05/Mar/26 9:52 AM;gitlab.dev;[Can Macit|https://git-lab.turkkep.com.tr/can.macit] mentioned this issue in [commit 8f0ea606|https://git-lab.turkkep.com.tr/kepappteam/ukds/Turkkep-UKDS/-/commit/8f0ea60691b9c793a14d5a37da369e4b05c0a276] of [KEPAPPTEAM / UKDS / Turkkep UKDS|https://git-lab.turkkep.com.tr/kepappteam/ukds/Turkkep-UKDS] on branch [dev|https://git-lab.turkkep.com.tr/kepappteam/ukds/Turkkep-UKDS/-/tree/dev]:{quote}(UKDS-220) Payment type parametre eklemesi tamamlandı. {quote} | DM45: 06/Mar/26 2:13 PM;gitlab.dev;[Can Macit|https://git-lab.turkkep.com.tr/can.macit] mentioned this issue in [merge request !120|https://git-lab.turkkep.com.tr/kepappteam/ukds/Turkkep-UKDS/-/merge_requests/120] of [KEPAPPTEAM / UKDS / Turkkep UKDS|https://git-lab.turkkep.com.tr/kepappteam/ukds/Turkkep-UKDS] on branch [dev|https://git-lab.turkkep.com.tr/kepappteam/ukds/Turkkep-UKDS/-/tree/dev]:{quote}(UKDS-215)(UKDS-220)(UKDS-223)(UKDS-226) Test branch merge request{quote} | DN45: 06/Mar/26 2:13 PM;gitlab.dev;[Can Macit|https://git-lab.turkkep.com.tr/can.macit] mentioned this issue in [commit 35528aff|https://git-lab.turkkep.com.tr/kepappteam/ukds/Turkkep-UKDS/-/commit/35528affde1b56a70b2846fcee2b6661a8678c8b] of [KEPAPPTEAM / UKDS / Turkkep UKDS|https://git-lab.turkkep.com.tr/kepappteam/ukds/Turkkep-UKDS] on branch [test|https://git-lab.turkkep.com.tr/kepappteam/ukds/Turkkep-UKDS/-/tree/test]:{quote}Merge branch 'dev' into 'test' (UKDS-215)(UKDS-220)(UKDS-223)(UKDS-226) Test branch merge request See merge request kepappteam/ukds/Turkkep-UKDS!120{quote} | DO45: 09/Mar/26 6:17 PM;gurkan.guney;Test ortamda yapılan kontroller başarılı.
